Workbook

Sheet Read Me
A1: Daily Takings & Stock Tracker
A2: A free template from adamreflects.ie
A4: I built the full version of this for my own till at Belle Jewellery — cloud-based, connects to a card reader, prints receipts, the works. This isn't that. This is the plain spreadsheet version: no app, no login, no subscription, nothing that can go wrong at 5pm on a Saturday. Just open it and go.
A6: It does two jobs most small shops end up doing on paper or not at all: knowing what your till should have in it at the end of the day, and knowing what's actually on your shelves before you run out of it.
A8: HOW TO USE IT
A9: Daily Takings — Fill this in at the end of each day it takes about two minutes. Type into the pale yellow cells only; everything else works itself out.
A10: Stock Tracker — List what you sell, what it costs you, what you sell it for, and how many you've got. It'll flag anything that's dropped below your reorder level.
A11: Monthly Summary — Pick a year at the top and it totals your takings by month automatically, pulled straight from the Daily Takings tab. Nothing to type here except the year.
A13: COLOUR KEY
A14: Pale yellow with blue text = type your own numbers here. Plain white with black text = a formula, leave it alone.
A16: A COUPLE OF HONEST NOTES
A17: Expected Cash assumes any refund you give is paid out in cash from the till. If you refund to a card instead, that's fine — it just means that refund shouldn't reduce your Expected Cash, so either leave it out of the Refunds column or note it in the Notes column instead.
... A23: adamreflects.ie — built between customers, in a jewellers in Cork.

Sheet Daily Takings
A1: Daily Takings Log
A2: Fill in the pale yellow cells at close each day. Everything else calculates itself.
A4: Date | B4: Staff | C4: Opening Float (€) | D4: Cash Sales (€) | E4: Card Sales (€) | F4: Voucher / Other Sales (€) | G4: Refunds (€) | H4: Total Takings (€) | I4: Net Takings (€) | J4: Cash Counted at Close (€) | K4: Expected Cash (€) | L4: Over / Short (€) | M4: Notes
A5: EXAMPLE — overwrite me | B5: AH | C5: 100 | D5: 340.5 | E5: 512 | F5: 60 | G5: 25 | H5: =D5+E5+F5 -> 912.5 | I5: =H5-G5 -> 887.5 | J5: 414.5 | K5: =C5+D5-G5 -> 415.5 | L5: =J5-K5 -> -1 | M5: Delete this row, or overwrite it — it's just here to show the format.
H6: =IF(D6="","",D6+E6+F6) | I6: =IF(D6="","",H6-G6) | K6: =IF(D6="","",C6+D6-G6) | L6: =IF(J6="","",J6-K6)
H7: =IF(D7="","",D7+E7+F7) | I7: =IF(D7="","",H7-G7) | K7: =IF(D7="","",C7+D7-G7) | L7: =IF(J7="","",J7-K7)
H8: =IF(D8="","",D8+E8+F8) | I8: =IF(D8="","",H8-G8) | K8: =IF(D8="","",C8+D8-G8) | L8: =IF(J8="","",J8-K8)
H9: =IF(D9="","",D9+E9+F9) | I9: =IF(D9="","",H9-G9) | K9: =IF(D9="","",C9+D9-G9) | L9: =IF(J9="","",J9-K9)
H10: =IF(D10="","",D10+E10+F10) | I10: =IF(D10="","",H10-G10) | K10: =IF(D10="","",C10+D10-G10) | L10: =IF(J10="","",J10-K10)
H11: =IF(D11="","",D11+E11+F11) | I11: =IF(D11="","",H11-G11) | K11: =IF(D11="","",C11+D11-G11) | L11: =IF(J11="","",J11-K11)
H12: =IF(D12="","",D12+E12+F12) | I12: =IF(D12="","",H12-G12) | K12: =IF(D12="","",C12+D12-G12) | L12: =IF(J12="","",J12-K12)
H13: =IF(D13="","",D13+E13+F13) | I13: =IF(D13="","",H13-G13) | K13: =IF(D13="","",C13+D13-G13) | L13: =IF(J13="","",J13-K13)
H14: =IF(D14="","",D14+E14+F14) | I14: =IF(D14="","",H14-G14) | K14: =IF(D14="","",C14+D14-G14) | L14: =IF(J14="","",J14-K14)
H15: =IF(D15="","",D15+E15+F15) | I15: =IF(D15="","",H15-G15) | K15: =IF(D15="","",C15+D15-G15) | L15: =IF(J15="","",J15-K15)
H16: =IF(D16="","",D16+E16+F16) | I16: =IF(D16="","",H16-G16) | K16: =IF(D16="","",C16+D16-G16) | L16: =IF(J16="","",J16-K16)
H17: =IF(D17="","",D17+E17+F17) | I17: =IF(D17="","",H17-G17) | K17: =IF(D17="","",C17+D17-G17) | L17: =IF(J17="","",J17-K17)
... H65: =IF(D65="","",D65+E65+F65) | I65: =IF(D65="","",H65-G65) | K65: =IF(D65="","",C65+D65-G65) | L65: =IF(J65="","",J65-K65)

Sheet Stock Tracker
A1: Stock Tracker
A2: Type into the pale yellow cells. Margin and stock value work themselves out.
A4: Product / SKU | B4: Category | C4: Cost Price (€) | D4: Sell Price (€) | E4: Margin (€) | F4: Margin (%) | G4: Qty in Stock | H4: Reorder Level | I4: Reorder? | J4: Stock Value at Cost (€) | K4: Notes
A5: EXAMPLE — overwrite me | B5: Silver rings | C5: 18 | D5: 45 | E5: =IFERROR(D5-C5,"") -> 27 | F5: =IFERROR(E5/D5,"") -> 0.6 | G5: 12 | H5: 5 | I5: =IF(G5="","",IF(G5<=H5,"Reorder","OK")) -> OK | J5: =IFERROR(C5*G5,"") -> 216 | K5: Delete this row, or overwrite it.
E6: =IFERROR(D6-C6,"") -> 0 | F6: =IFERROR(E6/D6,"") | I6: =IF(G6="","",IF(G6<=H6,"Reorder","OK")) | J6: =IFERROR(C6*G6,"") -> 0
E7: =IFERROR(D7-C7,"") -> 0 | F7: =IFERROR(E7/D7,"") | I7: =IF(G7="","",IF(G7<=H7,"Reorder","OK")) | J7: =IFERROR(C7*G7,"") -> 0
E8: =IFERROR(D8-C8,"") -> 0 | F8: =IFERROR(E8/D8,"") | I8: =IF(G8="","",IF(G8<=H8,"Reorder","OK")) | J8: =IFERROR(C8*G8,"") -> 0
E9: =IFERROR(D9-C9,"") -> 0 | F9: =IFERROR(E9/D9,"") | I9: =IF(G9="","",IF(G9<=H9,"Reorder","OK")) | J9: =IFERROR(C9*G9,"") -> 0
E10: =IFERROR(D10-C10,"") -> 0 | F10: =IFERROR(E10/D10,"") | I10: =IF(G10="","",IF(G10<=H10,"Reorder","OK")) | J10: =IFERROR(C10*G10,"") -> 0
E11: =IFERROR(D11-C11,"") -> 0 | F11: =IFERROR(E11/D11,"") | I11: =IF(G11="","",IF(G11<=H11,"Reorder","OK")) | J11: =IFERROR(C11*G11,"") -> 0
E12: =IFERROR(D12-C12,"") -> 0 | F12: =IFERROR(E12/D12,"") | I12: =IF(G12="","",IF(G12<=H12,"Reorder","OK")) | J12: =IFERROR(C12*G12,"") -> 0
E13: =IFERROR(D13-C13,"") -> 0 | F13: =IFERROR(E13/D13,"") | I13: =IF(G13="","",IF(G13<=H13,"Reorder","OK")) | J13: =IFERROR(C13*G13,"") -> 0
E14: =IFERROR(D14-C14,"") -> 0 | F14: =IFERROR(E14/D14,"") | I14: =IF(G14="","",IF(G14<=H14,"Reorder","OK")) | J14: =IFERROR(C14*G14,"") -> 0
E15: =IFERROR(D15-C15,"") -> 0 | F15: =IFERROR(E15/D15,"") | I15: =IF(G15="","",IF(G15<=H15,"Reorder","OK")) | J15: =IFERROR(C15*G15,"") -> 0
E16: =IFERROR(D16-C16,"") -> 0 | F16: =IFERROR(E16/D16,"") | I16: =IF(G16="","",IF(G16<=H16,"Reorder","OK")) | J16: =IFERROR(C16*G16,"") -> 0
E17: =IFERROR(D17-C17,"") -> 0 | F17: =IFERROR(E17/D17,"") | I17: =IF(G17="","",IF(G17<=H17,"Reorder","OK")) | J17: =IFERROR(C17*G17,"") -> 0
... E65: =IFERROR(D65-C65,"") -> 0 | F65: =IFERROR(E65/D65,"") | I65: =IF(G65="","",IF(G65<=H65,"Reorder","OK")) | J65: =IFERROR(C65*G65,"") -> 0

Sheet Monthly Summary
A1: Monthly Summary
A2: Pick a year below — everything else pulls from the Daily Takings tab automatically.
A4: Year: | B4: 2026
A6: Month | B6: Total Takings (€) | C6: Total Refunds (€) | D6: Net Takings (€) | E6: Days Recorded
A7: =TEXT(DATE(2000,1,1),"mmmm") -> January | B7: =SUMIFS('Daily Takings'!$H$6:$H$65,'Daily Takings'!$A$6:$A$65,">="&DATE($B$4,1,1),'Daily Takings'!$A$6:$A$65,"<"&DATE($B$4,1+1,1)) -> 0 | C7: =SUMIFS('Daily Takings'!$G$6:$G$65,'Daily Takings'!$A$6:$A$65,">="&DATE($B$4,1,1),'Daily Takings'!$A$6:$A$65,"<"&DATE($B$4,1+1,1)) -> 0 | D7: =B7-C7 -> 0 | E7: =COUNTIFS('Daily Takings'!$A$6:$A$65,">="&DATE($B$4,1,1),'Daily Takings'!$A$6:$A$65,"<"&DATE($B$4,1+1,1)) -> 0
A8: =TEXT(DATE(2000,2,1),"mmmm") -> February | B8: =SUMIFS('Daily Takings'!$H$6:$H$65,'Daily Takings'!$A$6:$A$65,">="&DATE($B$4,2,1),'Daily Takings'!$A$6:$A$65,"<"&DATE($B$4,2+1,1)) -> 0 | C8: =SUMIFS('Daily Takings'!$G$6:$G$65,'Daily Takings'!$A$6:$A$65,">="&DATE($B$4,2,1),'Daily Takings'!$A$6:$A$65,"<"&DATE($B$4,2+1,1)) -> 0 | D8: =B8-C8 -> 0 | E8: =COUNTIFS('Daily Takings'!$A$6:$A$65,">="&DATE($B$4,2,1),'Daily Takings'!$A$6:$A$65,"<"&DATE($B$4,2+1,1)) -> 0
A9: =TEXT(DATE(2000,3,1),"mmmm") -> March | B9: =SUMIFS('Daily Takings'!$H$6:$H$65,'Daily Takings'!$A$6:$A$65,">="&DATE($B$4,3,1),'Daily Takings'!$A$6:$A$65,"<"&DATE($B$4,3+1,1)) -> 0 | C9: =SUMIFS('Daily Takings'!$G$6:$G$65,'Daily Takings'!$A$6:$A$65,">="&DATE($B$4,3,1),'Daily Takings'!$A$6:$A$65,"<"&DATE($B$4,3+1,1)) -> 0 | D9: =B9-C9 -> 0 | E9: =COUNTIFS('Daily Takings'!$A$6:$A$65,">="&DATE($B$4,3,1),'Daily Takings'!$A$6:$A$65,"<"&DATE($B$4,3+1,1)) -> 0
A10: =TEXT(DATE(2000,4,1),"mmmm") -> April | B10: =SUMIFS('Daily Takings'!$H$6:$H$65,'Daily Takings'!$A$6:$A$65,">="&DATE($B$4,4,1),'Daily Takings'!$A$6:$A$65,"<"&DATE($B$4,4+1,1)) -> 0 | C10: =SUMIFS('Daily Takings'!$G$6:$G$65,'Daily Takings'!$A$6:$A$65,">="&DATE($B$4,4,1),'Daily Takings'!$A$6:$A$65,"<"&DATE($B$4,4+1,1)) -> 0 | D10: =B10-C10 -> 0 | E10: =COUNTIFS('Daily Takings'!$A$6:$A$65,">="&DATE($B$4,4,1),'Daily Takings'!$A$6:$A$65,"<"&DATE($B$4,4+1,1)) -> 0
A11: =TEXT(DATE(2000,5,1),"mmmm") -> May | B11: =SUMIFS('Daily Takings'!$H$6:$H$65,'Daily Takings'!$A$6:$A$65,">="&DATE($B$4,5,1),'Daily Takings'!$A$6:$A$65,"<"&DATE($B$4,5+1,1)) -> 0 | C11: =SUMIFS('Daily Takings'!$G$6:$G$65,'Daily Takings'!$A$6:$A$65,">="&DATE($B$4,5,1),'Daily Takings'!$A$6:$A$65,"<"&DATE($B$4,5+1,1)) -> 0 | D11: =B11-C11 -> 0 | E11: =COUNTIFS('Daily Takings'!$A$6:$A$65,">="&DATE($B$4,5,1),'Daily Takings'!$A$6:$A$65,"<"&DATE($B$4,5+1,1)) -> 0
A12: =TEXT(DATE(2000,6,1),"mmmm") -> June | B12: =SUMIFS('Daily Takings'!$H$6:$H$65,'Daily Takings'!$A$6:$A$65,">="&DATE($B$4,6,1),'Daily Takings'!$A$6:$A$65,"<"&DATE($B$4,6+1,1)) -> 0 | C12: =SUMIFS('Daily Takings'!$G$6:$G$65,'Daily Takings'!$A$6:$A$65,">="&DATE($B$4,6,1),'Daily Takings'!$A$6:$A$65,"<"&DATE($B$4,6+1,1)) -> 0 | D12: =B12-C12 -> 0 | E12: =COUNTIFS('Daily Takings'!$A$6:$A$65,">="&DATE($B$4,6,1),'Daily Takings'!$A$6:$A$65,"<"&DATE($B$4,6+1,1)) -> 0
A13: =TEXT(DATE(2000,7,1),"mmmm") -> July | B13: =SUMIFS('Daily Takings'!$H$6:$H$65,'Daily Takings'!$A$6:$A$65,">="&DATE($B$4,7,1),'Daily Takings'!$A$6:$A$65,"<"&DATE($B$4,7+1,1)) -> 0 | C13: =SUMIFS('Daily Takings'!$G$6:$G$65,'Daily Takings'!$A$6:$A$65,">="&DATE($B$4,7,1),'Daily Takings'!$A$6:$A$65,"<"&DATE($B$4,7+1,1)) -> 0 | D13: =B13-C13 -> 0 | E13: =COUNTIFS('Daily Takings'!$A$6:$A$65,">="&DATE($B$4,7,1),'Daily Takings'!$A$6:$A$65,"<"&DATE($B$4,7+1,1)) -> 0
A14: =TEXT(DATE(2000,8,1),"mmmm") -> August | B14: =SUMIFS('Daily Takings'!$H$6:$H$65,'Daily Takings'!$A$6:$A$65,">="&DATE($B$4,8,1),'Daily Takings'!$A$6:$A$65,"<"&DATE($B$4,8+1,1)) -> 0 | C14: =SUMIFS('Daily Takings'!$G$6:$G$65,'Daily Takings'!$A$6:$A$65,">="&DATE($B$4,8,1),'Daily Takings'!$A$6:$A$65,"<"&DATE($B$4,8+1,1)) -> 0 | D14: =B14-C14 -> 0 | E14: =COUNTIFS('Daily Takings'!$A$6:$A$65,">="&DATE($B$4,8,1),'Daily Takings'!$A$6:$A$65,"<"&DATE($B$4,8+1,1)) -> 0
A15: =TEXT(DATE(2000,9,1),"mmmm") -> September | B15: =SUMIFS('Daily Takings'!$H$6:$H$65,'Daily Takings'!$A$6:$A$65,">="&DATE($B$4,9,1),'Daily Takings'!$A$6:$A$65,"<"&DATE($B$4,9+1,1)) -> 0 | C15: =SUMIFS('Daily Takings'!$G$6:$G$65,'Daily Takings'!$A$6:$A$65,">="&DATE($B$4,9,1),'Daily Takings'!$A$6:$A$65,"<"&DATE($B$4,9+1,1)) -> 0 | D15: =B15-C15 -> 0 | E15: =COUNTIFS('Daily Takings'!$A$6:$A$65,">="&DATE($B$4,9,1),'Daily Takings'!$A$6:$A$65,"<"&DATE($B$4,9+1,1)) -> 0
A16: =TEXT(DATE(2000,10,1),"mmmm") -> October | B16: =SUMIFS('Daily Takings'!$H$6:$H$65,'Daily Takings'!$A$6:$A$65,">="&DATE($B$4,10,1),'Daily Takings'!$A$6:$A$65,"<"&DATE($B$4,10+1,1)) -> 0 | C16: =SUMIFS('Daily Takings'!$G$6:$G$65,'Daily Takings'!$A$6:$A$65,">="&DATE($B$4,10,1),'Daily Takings'!$A$6:$A$65,"<"&DATE($B$4,10+1,1)) -> 0 | D16: =B16-C16 -> 0 | E16: =COUNTIFS('Daily Takings'!$A$6:$A$65,">="&DATE($B$4,10,1),'Daily Takings'!$A$6:$A$65,"<"&DATE($B$4,10+1,1)) -> 0
A17: =TEXT(DATE(2000,11,1),"mmmm") -> November | B17: =SUMIFS('Daily Takings'!$H$6:$H$65,'Daily Takings'!$A$6:$A$65,">="&DATE($B$4,11,1),'Daily Takings'!$A$6:$A$65,"<"&DATE($B$4,11+1,1)) -> 0 | C17: =SUMIFS('Daily Takings'!$G$6:$G$65,'Daily Takings'!$A$6:$A$65,">="&DATE($B$4,11,1),'Daily Takings'!$A$6:$A$65,"<"&DATE($B$4,11+1,1)) -> 0 | D17: =B17-C17 -> 0 | E17: =COUNTIFS('Daily Takings'!$A$6:$A$65,">="&DATE($B$4,11,1),'Daily Takings'!$A$6:$A$65,"<"&DATE($B$4,11+1,1)) -> 0
A18: =TEXT(DATE(2000,12,1),"mmmm") -> December | B18: =SUMIFS('Daily Takings'!$H$6:$H$65,'Daily Takings'!$A$6:$A$65,">="&DATE($B$4,12,1),'Daily Takings'!$A$6:$A$65,"<"&DATE($B$4,12+1,1)) -> 0 | C18: =SUMIFS('Daily Takings'!$G$6:$G$65,'Daily Takings'!$A$6:$A$65,">="&DATE($B$4,12,1),'Daily Takings'!$A$6:$A$65,"<"&DATE($B$4,12+1,1)) -> 0 | D18: =B18-C18 -> 0 | E18: =COUNTIFS('Daily Takings'!$A$6:$A$65,">="&DATE($B$4,12,1),'Daily Takings'!$A$6:$A$65,"<"&DATE($B$4,12+1,1)) -> 0
A19: Total | B19: =SUM(B7:B18) -> 0 | C19: =SUM(C7:C18) -> 0 | D19: =SUM(D7:D18) -> 0 | E19: =SUM(E7:E18) -> 0
