Workbook

Sheet Start Here
B2: The Year-on-Year Sales Workbook
B3: A blank template from adamreflects.ie — nothing of my shop travels with it.
B5: What this is
B6: This is the workbook I keep for my own jewellers, emptied out. It tracks every half hour the shop is open:
B7: how many people walked in, how many bought, and what they spent. Everything else in here is worked out from
B8: those three numbers.
B10: The point of it is comparison. A day's takings on its own tells you almost nothing. The same day against last
B11: week, and against the same day last year, tells you a lot.
B13: Do these three things first
B14: 1. Open the Setup tab and fill in the yellow cells. Start date, your markup, your rent. Two minutes.
B15: 2. Open the Last Year tab and paste in last year's daily takings, if you have them. If you don't, skip it —
B16: everything still works, you just won't get the year-on-year columns until this time next year.
... B57: adamreflects.ie · free to use, free to change · built between customers, in a jewellers in Cork

Sheet Setup
B2: Setup — fill in the yellow cells
B3: Everything in the workbook reads from here. Change a number and the whole thing follows.
B4: YOUR NUMBERS
B5: Week 1 start date | C5: 46027 | D5: The first day of your week 1. Every date in the workbook counts on from this.
B6: Markup divisor | C6: 5.2 | D6: Sale price divided by this = rough cost. If you sell at 3x cost, put 3. Mine is 5.2.
B7: Rent per week (€) | C7: 0 | D7: Leave 0 if you'd rather not track it.
B8: Rates / service charge per week (€) | C8: 0 | D8: Same again — 0 is fine.
B9: Packaging & consumables (% of sales) | C9: 0.03 | D9: Bags, boxes, till roll. 3% is a reasonable guess if you don't know.
B10: Tax rate (%) | C10: 0.3 | D10: Only used for the 'after tax' line. A rough steer, not a tax return.
B11: Last year's week 1 start date | C11: =C5-364 -> 45663 | D11: Defaults to 364 days before your start date, so days of the week line up.
B13: OPENING HOURS
B14: The week tabs run 9.00am to 7.00pm in half hours. If you open later or close earlier, just leave those
B15: rows blank — empty rows add up to nothing and cost you nothing. Don't delete them; the sums use them.
B17: THE TRACKED CATEGORY
B18: One column on every week tab is for a category you want to watch on its own. I use gold, because it
B19: behaves completely differently to silver. Yours might be repairs, or a brand, or anything at all.

Sheet Wk1
A1: Day | B1: Date | C1: Time | D1: Customers In | E1: Sales | F1: Vouchers Used | G1: Walk In/Out | H1: Sale Amount | I1: Conversion | J1: Avg Sale | K1: Tracked Category | L1: Notes | M1: Cash | N1: vs Last Wk € | O1: vs Last Wk Cust | P1: Est. Cost | Q1: Est. Profit | R1: Last Year Day | S1: vs Last Year
A2: =TEXT(Setup!$C$5+0,"dddd") -> Monday | B2: =Setup!$C$5+0 -> 46027 | C2: 9.00 - 9.30 | P2: =IFERROR(H2/Setup!$C$6,"") -> 0 | Q2: =IFERROR(H2-P2,"") -> 0
A3: =TEXT(Setup!$C$5+0,"dddd") -> Monday | B3: =Setup!$C$5+0 -> 46027 | C3: 9.30 - 10.00 | P3: =IFERROR(H3/Setup!$C$6,"") -> 0 | Q3: =IFERROR(H3-P3,"") -> 0
A4: =TEXT(Setup!$C$5+0,"dddd") -> Monday | B4: =Setup!$C$5+0 -> 46027 | C4: 10.00 - 10.30 | P4: =IFERROR(H4/Setup!$C$6,"") -> 0 | Q4: =IFERROR(H4-P4,"") -> 0
A5: =TEXT(Setup!$C$5+0,"dddd") -> Monday | B5: =Setup!$C$5+0 -> 46027 | C5: 10.30 - 11.00 | P5: =IFERROR(H5/Setup!$C$6,"") -> 0 | Q5: =IFERROR(H5-P5,"") -> 0
A6: =TEXT(Setup!$C$5+0,"dddd") -> Monday | B6: =Setup!$C$5+0 -> 46027 | C6: 11.00 - 11.30 | P6: =IFERROR(H6/Setup!$C$6,"") -> 0 | Q6: =IFERROR(H6-P6,"") -> 0
A7: =TEXT(Setup!$C$5+0,"dddd") -> Monday | B7: =Setup!$C$5+0 -> 46027 | C7: 11.30 - 12.00 | P7: =IFERROR(H7/Setup!$C$6,"") -> 0 | Q7: =IFERROR(H7-P7,"") -> 0
A8: =TEXT(Setup!$C$5+0,"dddd") -> Monday | B8: =Setup!$C$5+0 -> 46027 | C8: 12.00 - 12.30 | P8: =IFERROR(H8/Setup!$C$6,"") -> 0 | Q8: =IFERROR(H8-P8,"") -> 0
A9: =TEXT(Setup!$C$5+0,"dddd") -> Monday | B9: =Setup!$C$5+0 -> 46027 | C9: 12.30 - 13.00 | P9: =IFERROR(H9/Setup!$C$6,"") -> 0 | Q9: =IFERROR(H9-P9,"") -> 0
A10: =TEXT(Setup!$C$5+0,"dddd") -> Monday | B10: =Setup!$C$5+0 -> 46027 | C10: 13.00 - 13.30 | P10: =IFERROR(H10/Setup!$C$6,"") -> 0 | Q10: =IFERROR(H10-P10,"") -> 0
A11: =TEXT(Setup!$C$5+0,"dddd") -> Monday | B11: =Setup!$C$5+0 -> 46027 | C11: 13.30 - 14.00 | P11: =IFERROR(H11/Setup!$C$6,"") -> 0 | Q11: =IFERROR(H11-P11,"") -> 0
A12: =TEXT(Setup!$C$5+0,"dddd") -> Monday | B12: =Setup!$C$5+0 -> 46027 | C12: 14.00 - 14.30 | P12: =IFERROR(H12/Setup!$C$6,"") -> 0 | Q12: =IFERROR(H12-P12,"") -> 0
A13: =TEXT(Setup!$C$5+0,"dddd") -> Monday | B13: =Setup!$C$5+0 -> 46027 | C13: 14.30 - 15.00 | P13: =IFERROR(H13/Setup!$C$6,"") -> 0 | Q13: =IFERROR(H13-P13,"") -> 0
... A22: =TEXT(Setup!$C$5+0,"dddd") -> Monday | B22: =Setup!$C$5+0 -> 46027 | C22: ONLINE | P22: =IFERROR(H22/Setup!$C$6,"") -> 0 | Q22: =IFERROR(H22-P22,"") -> 0
A23: =TEXT(Setup!$C$5+0,"dddd") -> Monday | B23: =Setup!$C$5+0 -> 46027 | C23: TOTAL | D23: =SUM(D2:D22) -> 0 | E23: =SUM(E2:E22) -> 0 | F23: =SUM(F2:F22) -> 0 | G23: =SUM(G2:G22) -> 0 | H23: =SUM(H2:H22) -> 0 | I23: =IFERROR(E23/D23,"") | J23: =IFERROR(H23/E23,"") | K23: =SUM(K2:K22) -> 0 | M23: =SUM(M2:M22) -> 0 | P23: =SUM(P2:P22) -> 0 | Q23: =SUM(Q2:Q22) -> 0 | R23: =IFERROR(INDEX('Last Year'!$C$6:$C$369,MATCH(B23-364,'Last Year'!$B$6:$B$369,0)),"") -> 0 | S23: =IFERROR(H23/R23-1,"")
A24: =TEXT(Setup!$C$5+1,"dddd") -> Tuesday | B24: =Setup!$C$5+1 -> 46028 | C24: 9.00 - 9.30 | P24: =IFERROR(H24/Setup!$C$6,"") -> 0 | Q24: =IFERROR(H24-P24,"") -> 0
A25: =TEXT(Setup!$C$5+1,"dddd") -> Tuesday | B25: =Setup!$C$5+1 -> 46028 | C25: 9.30 - 10.00 | P25: =IFERROR(H25/Setup!$C$6,"") -> 0 | Q25: =IFERROR(H25-P25,"") -> 0
A26: =TEXT(Setup!$C$5+1,"dddd") -> Tuesday | B26: =Setup!$C$5+1 -> 46028 | C26: 10.00 - 10.30 | P26: =IFERROR(H26/Setup!$C$6,"") -> 0 | Q26: =IFERROR(H26-P26,"") -> 0
A27: =TEXT(Setup!$C$5+1,"dddd") -> Tuesday | B27: =Setup!$C$5+1 -> 46028 | C27: 10.30 - 11.00 | P27: =IFERROR(H27/Setup!$C$6,"") -> 0 | Q27: =IFERROR(H27-P27,"") -> 0
A28: =TEXT(Setup!$C$5+1,"dddd") -> Tuesday | B28: =Setup!$C$5+1 -> 46028 | C28: 11.00 - 11.30 | P28: =IFERROR(H28/Setup!$C$6,"") -> 0 | Q28: =IFERROR(H28-P28,"") -> 0
A29: =TEXT(Setup!$C$5+1,"dddd") -> Tuesday | B29: =Setup!$C$5+1 -> 46028 | C29: 11.30 - 12.00 | P29: =IFERROR(H29/Setup!$C$6,"") -> 0 | Q29: =IFERROR(H29-P29,"") -> 0
A30: =TEXT(Setup!$C$5+1,"dddd") -> Tuesday | B30: =Setup!$C$5+1 -> 46028 | C30: 12.00 - 12.30 | P30: =IFERROR(H30/Setup!$C$6,"") -> 0 | Q30: =IFERROR(H30-P30,"") -> 0
A31: =TEXT(Setup!$C$5+1,"dddd") -> Tuesday | B31: =Setup!$C$5+1 -> 46028 | C31: 12.30 - 13.00 | P31: =IFERROR(H31/Setup!$C$6,"") -> 0 | Q31: =IFERROR(H31-P31,"") -> 0
A32: =TEXT(Setup!$C$5+1,"dddd") -> Tuesday | B32: =Setup!$C$5+1 -> 46028 | C32: 13.00 - 13.30 | P32: =IFERROR(H32/Setup!$C$6,"") -> 0 | Q32: =IFERROR(H32-P32,"") -> 0
A33: =TEXT(Setup!$C$5+1,"dddd") -> Tuesday | B33: =Setup!$C$5+1 -> 46028 | C33: 13.30 - 14.00 | P33: =IFERROR(H33/Setup!$C$6,"") -> 0 | Q33: =IFERROR(H33-P33,"") -> 0
A34: =TEXT(Setup!$C$5+1,"dddd") -> Tuesday | B34: =Setup!$C$5+1 -> 46028 | C34: 14.00 - 14.30 | P34: =IFERROR(H34/Setup!$C$6,"") -> 0 | Q34: =IFERROR(H34-P34,"") -> 0
A35: =TEXT(Setup!$C$5+1,"dddd") -> Tuesday | B35: =Setup!$C$5+1 -> 46028 | C35: 14.30 - 15.00 | P35: =IFERROR(H35/Setup!$C$6,"") -> 0 | Q35: =IFERROR(H35-P35,"") -> 0
... A44: =TEXT(Setup!$C$5+1,"dddd") -> Tuesday | B44: =Setup!$C$5+1 -> 46028 | C44: ONLINE | P44: =IFERROR(H44/Setup!$C$6,"") -> 0 | Q44: =IFERROR(H44-P44,"") -> 0
A45: =TEXT(Setup!$C$5+1,"dddd") -> Tuesday | B45: =Setup!$C$5+1 -> 46028 | C45: TOTAL | D45: =SUM(D24:D44) -> 0 | E45: =SUM(E24:E44) -> 0 | F45: =SUM(F24:F44) -> 0 | G45: =SUM(G24:G44) -> 0 | H45: =SUM(H24:H44) -> 0 | I45: =IFERROR(E45/D45,"") | J45: =IFERROR(H45/E45,"") | K45: =SUM(K24:K44) -> 0 | M45: =SUM(M24:M44) -> 0 | P45: =SUM(P24:P44) -> 0 | Q45: =SUM(Q24:Q44) -> 0 | R45: =IFERROR(INDEX('Last Year'!$C$6:$C$369,MATCH(B45-364,'Last Year'!$B$6:$B$369,0)),"") -> 0 | S45: =IFERROR(H45/R45-1,"")
A46: =TEXT(Setup!$C$5+2,"dddd") -> Wednesday | B46: =Setup!$C$5+2 -> 46029 | C46: 9.00 - 9.30 | P46: =IFERROR(H46/Setup!$C$6,"") -> 0 | Q46: =IFERROR(H46-P46,"") -> 0
A47: =TEXT(Setup!$C$5+2,"dddd") -> Wednesday | B47: =Setup!$C$5+2 -> 46029 | C47: 9.30 - 10.00 | P47: =IFERROR(H47/Setup!$C$6,"") -> 0 | Q47: =IFERROR(H47-P47,"") -> 0
A48: =TEXT(Setup!$C$5+2,"dddd") -> Wednesday | B48: =Setup!$C$5+2 -> 46029 | C48: 10.00 - 10.30 | P48: =IFERROR(H48/Setup!$C$6,"") -> 0 | Q48: =IFERROR(H48-P48,"") -> 0
A49: =TEXT(Setup!$C$5+2,"dddd") -> Wednesday | B49: =Setup!$C$5+2 -> 46029 | C49: 10.30 - 11.00 | P49: =IFERROR(H49/Setup!$C$6,"") -> 0 | Q49: =IFERROR(H49-P49,"") -> 0
A50: =TEXT(Setup!$C$5+2,"dddd") -> Wednesday | B50: =Setup!$C$5+2 -> 46029 | C50: 11.00 - 11.30 | P50: =IFERROR(H50/Setup!$C$6,"") -> 0 | Q50: =IFERROR(H50-P50,"") -> 0
A51: =TEXT(Setup!$C$5+2,"dddd") -> Wednesday | B51: =Setup!$C$5+2 -> 46029 | C51: 11.30 - 12.00 | P51: =IFERROR(H51/Setup!$C$6,"") -> 0 | Q51: =IFERROR(H51-P51,"") -> 0
A52: =TEXT(Setup!$C$5+2,"dddd") -> Wednesday | B52: =Setup!$C$5+2 -> 46029 | C52: 12.00 - 12.30 | P52: =IFERROR(H52/Setup!$C$6,"") -> 0 | Q52: =IFERROR(H52-P52,"") -> 0
A53: =TEXT(Setup!$C$5+2,"dddd") -> Wednesday | B53: =Setup!$C$5+2 -> 46029 | C53: 12.30 - 13.00 | P53: =IFERROR(H53/Setup!$C$6,"") -> 0 | Q53: =IFERROR(H53-P53,"") -> 0
A54: =TEXT(Setup!$C$5+2,"dddd") -> Wednesday | B54: =Setup!$C$5+2 -> 46029 | C54: 13.00 - 13.30 | P54: =IFERROR(H54/Setup!$C$6,"") -> 0 | Q54: =IFERROR(H54-P54,"") -> 0
A55: =TEXT(Setup!$C$5+2,"dddd") -> Wednesday | B55: =Setup!$C$5+2 -> 46029 | C55: 13.30 - 14.00 | P55: =IFERROR(H55/Setup!$C$6,"") -> 0 | Q55: =IFERROR(H55-P55,"") -> 0
A56: =TEXT(Setup!$C$5+2,"dddd") -> Wednesday | B56: =Setup!$C$5+2 -> 46029 | C56: 14.00 - 14.30 | P56: =IFERROR(H56/Setup!$C$6,"") -> 0 | Q56: =IFERROR(H56-P56,"") -> 0
A57: =TEXT(Setup!$C$5+2,"dddd") -> Wednesday | B57: =Setup!$C$5+2 -> 46029 | C57: 14.30 - 15.00 | P57: =IFERROR(H57/Setup!$C$6,"") -> 0 | Q57: =IFERROR(H57-P57,"") -> 0
... A66: =TEXT(Setup!$C$5+2,"dddd") -> Wednesday | B66: =Setup!$C$5+2 -> 46029 | C66: ONLINE | P66: =IFERROR(H66/Setup!$C$6,"") -> 0 | Q66: =IFERROR(H66-P66,"") -> 0
A67: =TEXT(Setup!$C$5+2,"dddd") -> Wednesday | B67: =Setup!$C$5+2 -> 46029 | C67: TOTAL | D67: =SUM(D46:D66) -> 0 | E67: =SUM(E46:E66) -> 0 | F67: =SUM(F46:F66) -> 0 | G67: =SUM(G46:G66) -> 0 | H67: =SUM(H46:H66) -> 0 | I67: =IFERROR(E67/D67,"") | J67: =IFERROR(H67/E67,"") | K67: =SUM(K46:K66) -> 0 | M67: =SUM(M46:M66) -> 0 | P67: =SUM(P46:P66) -> 0 | Q67: =SUM(Q46:Q66) -> 0 | R67: =IFERROR(INDEX('Last Year'!$C$6:$C$369,MATCH(B67-364,'Last Year'!$B$6:$B$369,0)),"") -> 0 | S67: =IFERROR(H67/R67-1,"")
A68: =TEXT(Setup!$C$5+3,"dddd") -> Thursday | B68: =Setup!$C$5+3 -> 46030 | C68: 9.00 - 9.30 | P68: =IFERROR(H68/Setup!$C$6,"") -> 0 | Q68: =IFERROR(H68-P68,"") -> 0
A69: =TEXT(Setup!$C$5+3,"dddd") -> Thursday | B69: =Setup!$C$5+3 -> 46030 | C69: 9.30 - 10.00 | P69: =IFERROR(H69/Setup!$C$6,"") -> 0 | Q69: =IFERROR(H69-P69,"") -> 0
A70: =TEXT(Setup!$C$5+3,"dddd") -> Thursday | B70: =Setup!$C$5+3 -> 46030 | C70: 10.00 - 10.30 | P70: =IFERROR(H70/Setup!$C$6,"") -> 0 | Q70: =IFERROR(H70-P70,"") -> 0
A71: =TEXT(Setup!$C$5+3,"dddd") -> Thursday | B71: =Setup!$C$5+3 -> 46030 | C71: 10.30 - 11.00 | P71: =IFERROR(H71/Setup!$C$6,"") -> 0 | Q71: =IFERROR(H71-P71,"") -> 0
A72: =TEXT(Setup!$C$5+3,"dddd") -> Thursday | B72: =Setup!$C$5+3 -> 46030 | C72: 11.00 - 11.30 | P72: =IFERROR(H72/Setup!$C$6,"") -> 0 | Q72: =IFERROR(H72-P72,"") -> 0
A73: =TEXT(Setup!$C$5+3,"dddd") -> Thursday | B73: =Setup!$C$5+3 -> 46030 | C73: 11.30 - 12.00 | P73: =IFERROR(H73/Setup!$C$6,"") -> 0 | Q73: =IFERROR(H73-P73,"") -> 0
A74: =TEXT(Setup!$C$5+3,"dddd") -> Thursday | B74: =Setup!$C$5+3 -> 46030 | C74: 12.00 - 12.30 | P74: =IFERROR(H74/Setup!$C$6,"") -> 0 | Q74: =IFERROR(H74-P74,"") -> 0
A75: =TEXT(Setup!$C$5+3,"dddd") -> Thursday | B75: =Setup!$C$5+3 -> 46030 | C75: 12.30 - 13.00 | P75: =IFERROR(H75/Setup!$C$6,"") -> 0 | Q75: =IFERROR(H75-P75,"") -> 0
A76: =TEXT(Setup!$C$5+3,"dddd") -> Thursday | B76: =Setup!$C$5+3 -> 46030 | C76: 13.00 - 13.30 | P76: =IFERROR(H76/Setup!$C$6,"") -> 0 | Q76: =IFERROR(H76-P76,"") -> 0
A77: =TEXT(Setup!$C$5+3,"dddd") -> Thursday | B77: =Setup!$C$5+3 -> 46030 | C77: 13.30 - 14.00 | P77: =IFERROR(H77/Setup!$C$6,"") -> 0 | Q77: =IFERROR(H77-P77,"") -> 0
A78: =TEXT(Setup!$C$5+3,"dddd") -> Thursday | B78: =Setup!$C$5+3 -> 46030 | C78: 14.00 - 14.30 | P78: =IFERROR(H78/Setup!$C$6,"") -> 0 | Q78: =IFERROR(H78-P78,"") -> 0
A79: =TEXT(Setup!$C$5+3,"dddd") -> Thursday | B79: =Setup!$C$5+3 -> 46030 | C79: 14.30 - 15.00 | P79: =IFERROR(H79/Setup!$C$6,"") -> 0 | Q79: =IFERROR(H79-P79,"") -> 0
... A88: =TEXT(Setup!$C$5+3,"dddd") -> Thursday | B88: =Setup!$C$5+3 -> 46030 | C88: ONLINE | P88: =IFERROR(H88/Setup!$C$6,"") -> 0 | Q88: =IFERROR(H88-P88,"") -> 0
A89: =TEXT(Setup!$C$5+3,"dddd") -> Thursday | B89: =Setup!$C$5+3 -> 46030 | C89: TOTAL | D89: =SUM(D68:D88) -> 0 | E89: =SUM(E68:E88) -> 0 | F89: =SUM(F68:F88) -> 0 | G89: =SUM(G68:G88) -> 0 | H89: =SUM(H68:H88) -> 0 | I89: =IFERROR(E89/D89,"") | J89: =IFERROR(H89/E89,"") | K89: =SUM(K68:K88) -> 0 | M89: =SUM(M68:M88) -> 0 | P89: =SUM(P68:P88) -> 0 | Q89: =SUM(Q68:Q88) -> 0 | R89: =IFERROR(INDEX('Last Year'!$C$6:$C$369,MATCH(B89-364,'Last Year'!$B$6:$B$369,0)),"") -> 0 | S89: =IFERROR(H89/R89-1,"")
A90: =TEXT(Setup!$C$5+4,"dddd") -> Friday | B90: =Setup!$C$5+4 -> 46031 | C90: 9.00 - 9.30 | P90: =IFERROR(H90/Setup!$C$6,"") -> 0 | Q90: =IFERROR(H90-P90,"") -> 0
A91: =TEXT(Setup!$C$5+4,"dddd") -> Friday | B91: =Setup!$C$5+4 -> 46031 | C91: 9.30 - 10.00 | P91: =IFERROR(H91/Setup!$C$6,"") -> 0 | Q91: =IFERROR(H91-P91,"") -> 0
A92: =TEXT(Setup!$C$5+4,"dddd") -> Friday | B92: =Setup!$C$5+4 -> 46031 | C92: 10.00 - 10.30 | P92: =IFERROR(H92/Setup!$C$6,"") -> 0 | Q92: =IFERROR(H92-P92,"") -> 0
A93: =TEXT(Setup!$C$5+4,"dddd") -> Friday | B93: =Setup!$C$5+4 -> 46031 | C93: 10.30 - 11.00 | P93: =IFERROR(H93/Setup!$C$6,"") -> 0 | Q93: =IFERROR(H93-P93,"") -> 0
A94: =TEXT(Setup!$C$5+4,"dddd") -> Friday | B94: =Setup!$C$5+4 -> 46031 | C94: 11.00 - 11.30 | P94: =IFERROR(H94/Setup!$C$6,"") -> 0 | Q94: =IFERROR(H94-P94,"") -> 0
A95: =TEXT(Setup!$C$5+4,"dddd") -> Friday | B95: =Setup!$C$5+4 -> 46031 | C95: 11.30 - 12.00 | P95: =IFERROR(H95/Setup!$C$6,"") -> 0 | Q95: =IFERROR(H95-P95,"") -> 0
A96: =TEXT(Setup!$C$5+4,"dddd") -> Friday | B96: =Setup!$C$5+4 -> 46031 | C96: 12.00 - 12.30 | P96: =IFERROR(H96/Setup!$C$6,"") -> 0 | Q96: =IFERROR(H96-P96,"") -> 0
A97: =TEXT(Setup!$C$5+4,"dddd") -> Friday | B97: =Setup!$C$5+4 -> 46031 | C97: 12.30 - 13.00 | P97: =IFERROR(H97/Setup!$C$6,"") -> 0 | Q97: =IFERROR(H97-P97,"") -> 0
A98: =TEXT(Setup!$C$5+4,"dddd") -> Friday | B98: =Setup!$C$5+4 -> 46031 | C98: 13.00 - 13.30 | P98: =IFERROR(H98/Setup!$C$6,"") -> 0 | Q98: =IFERROR(H98-P98,"") -> 0
A99: =TEXT(Setup!$C$5+4,"dddd") -> Friday | B99: =Setup!$C$5+4 -> 46031 | C99: 13.30 - 14.00 | P99: =IFERROR(H99/Setup!$C$6,"") -> 0 | Q99: =IFERROR(H99-P99,"") -> 0
A100: =TEXT(Setup!$C$5+4,"dddd") -> Friday | B100: =Setup!$C$5+4 -> 46031 | C100: 14.00 - 14.30 | P100: =IFERROR(H100/Setup!$C$6,"") -> 0 | Q100: =IFERROR(H100-P100,"") -> 0
A101: =TEXT(Setup!$C$5+4,"dddd") -> Friday | B101: =Setup!$C$5+4 -> 46031 | C101: 14.30 - 15.00 | P101: =IFERROR(H101/Setup!$C$6,"") -> 0 | Q101: =IFERROR(H101-P101,"") -> 0
... A110: =TEXT(Setup!$C$5+4,"dddd") -> Friday | B110: =Setup!$C$5+4 -> 46031 | C110: ONLINE | P110: =IFERROR(H110/Setup!$C$6,"") -> 0 | Q110: =IFERROR(H110-P110,"") -> 0
A111: =TEXT(Setup!$C$5+4,"dddd") -> Friday | B111: =Setup!$C$5+4 -> 46031 | C111: TOTAL | D111: =SUM(D90:D110) -> 0 | E111: =SUM(E90:E110) -> 0 | F111: =SUM(F90:F110) -> 0 | G111: =SUM(G90:G110) -> 0 | H111: =SUM(H90:H110) -> 0 | I111: =IFERROR(E111/D111,"") | J111: =IFERROR(H111/E111,"") | K111: =SUM(K90:K110) -> 0 | M111: =SUM(M90:M110) -> 0 | P111: =SUM(P90:P110) -> 0 | Q111: =SUM(Q90:Q110) -> 0 | R111: =IFERROR(INDEX('Last Year'!$C$6:$C$369,MATCH(B111-364,'Last Year'!$B$6:$B$369,0)),"") -> 0 | S111: =IFERROR(H111/R111-1,"")
A112: =TEXT(Setup!$C$5+5,"dddd") -> Saturday | B112: =Setup!$C$5+5 -> 46032 | C112: 9.00 - 9.30 | P112: =IFERROR(H112/Setup!$C$6,"") -> 0 | Q112: =IFERROR(H112-P112,"") -> 0
A113: =TEXT(Setup!$C$5+5,"dddd") -> Saturday | B113: =Setup!$C$5+5 -> 46032 | C113: 9.30 - 10.00 | P113: =IFERROR(H113/Setup!$C$6,"") -> 0 | Q113: =IFERROR(H113-P113,"") -> 0
A114: =TEXT(Setup!$C$5+5,"dddd") -> Saturday | B114: =Setup!$C$5+5 -> 46032 | C114: 10.00 - 10.30 | P114: =IFERROR(H114/Setup!$C$6,"") -> 0 | Q114: =IFERROR(H114-P114,"") -> 0
A115: =TEXT(Setup!$C$5+5,"dddd") -> Saturday | B115: =Setup!$C$5+5 -> 46032 | C115: 10.30 - 11.00 | P115: =IFERROR(H115/Setup!$C$6,"") -> 0 | Q115: =IFERROR(H115-P115,"") -> 0
A116: =TEXT(Setup!$C$5+5,"dddd") -> Saturday | B116: =Setup!$C$5+5 -> 46032 | C116: 11.00 - 11.30 | P116: =IFERROR(H116/Setup!$C$6,"") -> 0 | Q116: =IFERROR(H116-P116,"") -> 0
A117: =TEXT(Setup!$C$5+5,"dddd") -> Saturday | B117: =Setup!$C$5+5 -> 46032 | C117: 11.30 - 12.00 | P117: =IFERROR(H117/Setup!$C$6,"") -> 0 | Q117: =IFERROR(H117-P117,"") -> 0
A118: =TEXT(Setup!$C$5+5,"dddd") -> Saturday | B118: =Setup!$C$5+5 -> 46032 | C118: 12.00 - 12.30 | P118: =IFERROR(H118/Setup!$C$6,"") -> 0 | Q118: =IFERROR(H118-P118,"") -> 0
A119: =TEXT(Setup!$C$5+5,"dddd") -> Saturday | B119: =Setup!$C$5+5 -> 46032 | C119: 12.30 - 13.00 | P119: =IFERROR(H119/Setup!$C$6,"") -> 0 | Q119: =IFERROR(H119-P119,"") -> 0
A120: =TEXT(Setup!$C$5+5,"dddd") -> Saturday | B120: =Setup!$C$5+5 -> 46032 | C120: 13.00 - 13.30 | P120: =IFERROR(H120/Setup!$C$6,"") -> 0 | Q120: =IFERROR(H120-P120,"") -> 0
A121: =TEXT(Setup!$C$5+5,"dddd") -> Saturday | B121: =Setup!$C$5+5 -> 46032 | C121: 13.30 - 14.00 | P121: =IFERROR(H121/Setup!$C$6,"") -> 0 | Q121: =IFERROR(H121-P121,"") -> 0
A122: =TEXT(Setup!$C$5+5,"dddd") -> Saturday | B122: =Setup!$C$5+5 -> 46032 | C122: 14.00 - 14.30 | P122: =IFERROR(H122/Setup!$C$6,"") -> 0 | Q122: =IFERROR(H122-P122,"") -> 0
A123: =TEXT(Setup!$C$5+5,"dddd") -> Saturday | B123: =Setup!$C$5+5 -> 46032 | C123: 14.30 - 15.00 | P123: =IFERROR(H123/Setup!$C$6,"") -> 0 | Q123: =IFERROR(H123-P123,"") -> 0
... A132: =TEXT(Setup!$C$5+5,"dddd") -> Saturday | B132: =Setup!$C$5+5 -> 46032 | C132: ONLINE | P132: =IFERROR(H132/Setup!$C$6,"") -> 0 | Q132: =IFERROR(H132-P132,"") -> 0
A133: =TEXT(Setup!$C$5+5,"dddd") -> Saturday | B133: =Setup!$C$5+5 -> 46032 | C133: TOTAL | D133: =SUM(D112:D132) -> 0 | E133: =SUM(E112:E132) -> 0 | F133: =SUM(F112:F132) -> 0 | G133: =SUM(G112:G132) -> 0 | H133: =SUM(H112:H132) -> 0 | I133: =IFERROR(E133/D133,"") | J133: =IFERROR(H133/E133,"") | K133: =SUM(K112:K132) -> 0 | M133: =SUM(M112:M132) -> 0 | P133: =SUM(P112:P132) -> 0 | Q133: =SUM(Q112:Q132) -> 0 | R133: =IFERROR(INDEX('Last Year'!$C$6:$C$369,MATCH(B133-364,'Last Year'!$B$6:$B$369,0)),"") -> 0 | S133: =IFERROR(H133/R133-1,"")
A134: =TEXT(Setup!$C$5+6,"dddd") -> Sunday | B134: =Setup!$C$5+6 -> 46033 | C134: 9.00 - 9.30 | P134: =IFERROR(H134/Setup!$C$6,"") -> 0 | Q134: =IFERROR(H134-P134,"") -> 0
A135: =TEXT(Setup!$C$5+6,"dddd") -> Sunday | B135: =Setup!$C$5+6 -> 46033 | C135: 9.30 - 10.00 | P135: =IFERROR(H135/Setup!$C$6,"") -> 0 | Q135: =IFERROR(H135-P135,"") -> 0
A136: =TEXT(Setup!$C$5+6,"dddd") -> Sunday | B136: =Setup!$C$5+6 -> 46033 | C136: 10.00 - 10.30 | P136: =IFERROR(H136/Setup!$C$6,"") -> 0 | Q136: =IFERROR(H136-P136,"") -> 0
A137: =TEXT(Setup!$C$5+6,"dddd") -> Sunday | B137: =Setup!$C$5+6 -> 46033 | C137: 10.30 - 11.00 | P137: =IFERROR(H137/Setup!$C$6,"") -> 0 | Q137: =IFERROR(H137-P137,"") -> 0
A138: =TEXT(Setup!$C$5+6,"dddd") -> Sunday | B138: =Setup!$C$5+6 -> 46033 | C138: 11.00 - 11.30 | P138: =IFERROR(H138/Setup!$C$6,"") -> 0 | Q138: =IFERROR(H138-P138,"") -> 0
A139: =TEXT(Setup!$C$5+6,"dddd") -> Sunday | B139: =Setup!$C$5+6 -> 46033 | C139: 11.30 - 12.00 | P139: =IFERROR(H139/Setup!$C$6,"") -> 0 | Q139: =IFERROR(H139-P139,"") -> 0
A140: =TEXT(Setup!$C$5+6,"dddd") -> Sunday | B140: =Setup!$C$5+6 -> 46033 | C140: 12.00 - 12.30 | P140: =IFERROR(H140/Setup!$C$6,"") -> 0 | Q140: =IFERROR(H140-P140,"") -> 0
A141: =TEXT(Setup!$C$5+6,"dddd") -> Sunday | B141: =Setup!$C$5+6 -> 46033 | C141: 12.30 - 13.00 | P141: =IFERROR(H141/Setup!$C$6,"") -> 0 | Q141: =IFERROR(H141-P141,"") -> 0
A142: =TEXT(Setup!$C$5+6,"dddd") -> Sunday | B142: =Setup!$C$5+6 -> 46033 | C142: 13.00 - 13.30 | P142: =IFERROR(H142/Setup!$C$6,"") -> 0 | Q142: =IFERROR(H142-P142,"") -> 0
A143: =TEXT(Setup!$C$5+6,"dddd") -> Sunday | B143: =Setup!$C$5+6 -> 46033 | C143: 13.30 - 14.00 | P143: =IFERROR(H143/Setup!$C$6,"") -> 0 | Q143: =IFERROR(H143-P143,"") -> 0
A144: =TEXT(Setup!$C$5+6,"dddd") -> Sunday | B144: =Setup!$C$5+6 -> 46033 | C144: 14.00 - 14.30 | P144: =IFERROR(H144/Setup!$C$6,"") -> 0 | Q144: =IFERROR(H144-P144,"") -> 0
A145: =TEXT(Setup!$C$5+6,"dddd") -> Sunday | B145: =Setup!$C$5+6 -> 46033 | C145: 14.30 - 15.00 | P145: =IFERROR(H145/Setup!$C$6,"") -> 0 | Q145: =IFERROR(H145-P145,"") -> 0
... A154: =TEXT(Setup!$C$5+6,"dddd") -> Sunday | B154: =Setup!$C$5+6 -> 46033 | C154: ONLINE | P154: =IFERROR(H154/Setup!$C$6,"") -> 0 | Q154: =IFERROR(H154-P154,"") -> 0
A155: =TEXT(Setup!$C$5+6,"dddd") -> Sunday | B155: =Setup!$C$5+6 -> 46033 | C155: TOTAL | D155: =SUM(D134:D154) -> 0 | E155: =SUM(E134:E154) -> 0 | F155: =SUM(F134:F154) -> 0 | G155: =SUM(G134:G154) -> 0 | H155: =SUM(H134:H154) -> 0 | I155: =IFERROR(E155/D155,"") | J155: =IFERROR(H155/E155,"") | K155: =SUM(K134:K154) -> 0 | M155: =SUM(M134:M154) -> 0 | P155: =SUM(P134:P154) -> 0 | Q155: =SUM(Q134:Q154) -> 0 | R155: =IFERROR(INDEX('Last Year'!$C$6:$C$369,MATCH(B155-364,'Last Year'!$B$6:$B$369,0)),"") -> 0 | S155: =IFERROR(H155/R155-1,"")
C156: FULL WEEK | D156: =D23+D45+D67+D89+D111+D133+D155 -> 0 | E156: =E23+E45+E67+E89+E111+E133+E155 -> 0 | F156: =F23+F45+F67+F89+F111+F133+F155 -> 0 | G156: =G23+G45+G67+G89+G111+G133+G155 -> 0 | H156: =H23+H45+H67+H89+H111+H133+H155 -> 0 | I156: =IFERROR(E156/D156,"") | J156: =IFERROR(H156/E156,"") | K156: =K23+K45+K67+K89+K111+K133+K155 -> 0 | M156: =M23+M45+M67+M89+M111+M133+M155 -> 0 | P156: =P23+P45+P67+P89+P111+P133+P155 -> 0 | Q156: =Q23+Q45+Q67+Q89+Q111+Q133+Q155 -> 0 | R156: =R23+R45+R67+R89+R111+R133+R155 -> 0 | S156: =IFERROR(H156/R156-1,"")
...

Sheet Wk2
A1: Day | B1: Date | C1: Time | D1: Customers In | E1: Sales | F1: Vouchers Used | G1: Walk In/Out | H1: Sale Amount | I1: Conversion | J1: Avg Sale | K1: Tracked Category | L1: Notes | M1: Cash | N1: vs Last Wk € | O1: vs Last Wk Cust | P1: Est. Cost | Q1: Est. Profit | R1: Last Year Day | S1: vs Last Year
A2: =TEXT(Setup!$C$5+7,"dddd") -> Monday | B2: =Setup!$C$5+7 -> 46034 | C2: 9.00 - 9.30 | P2: =IFERROR(H2/Setup!$C$6,"") -> 0 | Q2: =IFERROR(H2-P2,"") -> 0
A3: =TEXT(Setup!$C$5+7,"dddd") -> Monday | B3: =Setup!$C$5+7 -> 46034 | C3: 9.30 - 10.00 | P3: =IFERROR(H3/Setup!$C$6,"") -> 0 | Q3: =IFERROR(H3-P3,"") -> 0
A4: =TEXT(Setup!$C$5+7,"dddd") -> Monday | B4: =Setup!$C$5+7 -> 46034 | C4: 10.00 - 10.30 | P4: =IFERROR(H4/Setup!$C$6,"") -> 0 | Q4: =IFERROR(H4-P4,"") -> 0
A5: =TEXT(Setup!$C$5+7,"dddd") -> Monday | B5: =Setup!$C$5+7 -> 46034 | C5: 10.30 - 11.00 | P5: =IFERROR(H5/Setup!$C$6,"") -> 0 | Q5: =IFERROR(H5-P5,"") -> 0
A6: =TEXT(Setup!$C$5+7,"dddd") -> Monday | B6: =Setup!$C$5+7 -> 46034 | C6: 11.00 - 11.30 | P6: =IFERROR(H6/Setup!$C$6,"") -> 0 | Q6: =IFERROR(H6-P6,"") -> 0
A7: =TEXT(Setup!$C$5+7,"dddd") -> Monday | B7: =Setup!$C$5+7 -> 46034 | C7: 11.30 - 12.00 | P7: =IFERROR(H7/Setup!$C$6,"") -> 0 | Q7: =IFERROR(H7-P7,"") -> 0
A8: =TEXT(Setup!$C$5+7,"dddd") -> Monday | B8: =Setup!$C$5+7 -> 46034 | C8: 12.00 - 12.30 | P8: =IFERROR(H8/Setup!$C$6,"") -> 0 | Q8: =IFERROR(H8-P8,"") -> 0
A9: =TEXT(Setup!$C$5+7,"dddd") -> Monday | B9: =Setup!$C$5+7 -> 46034 | C9: 12.30 - 13.00 | P9: =IFERROR(H9/Setup!$C$6,"") -> 0 | Q9: =IFERROR(H9-P9,"") -> 0
A10: =TEXT(Setup!$C$5+7,"dddd") -> Monday | B10: =Setup!$C$5+7 -> 46034 | C10: 13.00 - 13.30 | P10: =IFERROR(H10/Setup!$C$6,"") -> 0 | Q10: =IFERROR(H10-P10,"") -> 0
A11: =TEXT(Setup!$C$5+7,"dddd") -> Monday | B11: =Setup!$C$5+7 -> 46034 | C11: 13.30 - 14.00 | P11: =IFERROR(H11/Setup!$C$6,"") -> 0 | Q11: =IFERROR(H11-P11,"") -> 0
A12: =TEXT(Setup!$C$5+7,"dddd") -> Monday | B12: =Setup!$C$5+7 -> 46034 | C12: 14.00 - 14.30 | P12: =IFERROR(H12/Setup!$C$6,"") -> 0 | Q12: =IFERROR(H12-P12,"") -> 0
A13: =TEXT(Setup!$C$5+7,"dddd") -> Monday | B13: =Setup!$C$5+7 -> 46034 | C13: 14.30 - 15.00 | P13: =IFERROR(H13/Setup!$C$6,"") -> 0 | Q13: =IFERROR(H13-P13,"") -> 0
... A22: =TEXT(Setup!$C$5+7,"dddd") -> Monday | B22: =Setup!$C$5+7 -> 46034 | C22: ONLINE | P22: =IFERROR(H22/Setup!$C$6,"") -> 0 | Q22: =IFERROR(H22-P22,"") -> 0
A23: =TEXT(Setup!$C$5+7,"dddd") -> Monday | B23: =Setup!$C$5+7 -> 46034 | C23: TOTAL | D23: =SUM(D2:D22) -> 0 | E23: =SUM(E2:E22) -> 0 | F23: =SUM(F2:F22) -> 0 | G23: =SUM(G2:G22) -> 0 | H23: =SUM(H2:H22) -> 0 | I23: =IFERROR(E23/D23,"") | J23: =IFERROR(H23/E23,"") | K23: =SUM(K2:K22) -> 0 | M23: =SUM(M2:M22) -> 0 | N23: =IFERROR(H23-Wk1!H23,"") -> 0 | O23: =IFERROR(D23-Wk1!D23,"") -> 0 | P23: =SUM(P2:P22) -> 0 | Q23: =SUM(Q2:Q22) -> 0 | R23: =IFERROR(INDEX('Last Year'!$C$6:$C$369,MATCH(B23-364,'Last Year'!$B$6:$B$369,0)),"") -> 0 | S23: =IFERROR(H23/R23-1,"")
A24: =TEXT(Setup!$C$5+8,"dddd") -> Tuesday | B24: =Setup!$C$5+8 -> 46035 | C24: 9.00 - 9.30 | P24: =IFERROR(H24/Setup!$C$6,"") -> 0 | Q24: =IFERROR(H24-P24,"") -> 0
A25: =TEXT(Setup!$C$5+8,"dddd") -> Tuesday | B25: =Setup!$C$5+8 -> 46035 | C25: 9.30 - 10.00 | P25: =IFERROR(H25/Setup!$C$6,"") -> 0 | Q25: =IFERROR(H25-P25,"") -> 0
A26: =TEXT(Setup!$C$5+8,"dddd") -> Tuesday | B26: =Setup!$C$5+8 -> 46035 | C26: 10.00 - 10.30 | P26: =IFERROR(H26/Setup!$C$6,"") -> 0 | Q26: =IFERROR(H26-P26,"") -> 0
A27: =TEXT(Setup!$C$5+8,"dddd") -> Tuesday | B27: =Setup!$C$5+8 -> 46035 | C27: 10.30 - 11.00 | P27: =IFERROR(H27/Setup!$C$6,"") -> 0 | Q27: =IFERROR(H27-P27,"") -> 0
A28: =TEXT(Setup!$C$5+8,"dddd") -> Tuesday | B28: =Setup!$C$5+8 -> 46035 | C28: 11.00 - 11.30 | P28: =IFERROR(H28/Setup!$C$6,"") -> 0 | Q28: =IFERROR(H28-P28,"") -> 0
A29: =TEXT(Setup!$C$5+8,"dddd") -> Tuesday | B29: =Setup!$C$5+8 -> 46035 | C29: 11.30 - 12.00 | P29: =IFERROR(H29/Setup!$C$6,"") -> 0 | Q29: =IFERROR(H29-P29,"") -> 0
A30: =TEXT(Setup!$C$5+8,"dddd") -> Tuesday | B30: =Setup!$C$5+8 -> 46035 | C30: 12.00 - 12.30 | P30: =IFERROR(H30/Setup!$C$6,"") -> 0 | Q30: =IFERROR(H30-P30,"") -> 0
A31: =TEXT(Setup!$C$5+8,"dddd") -> Tuesday | B31: =Setup!$C$5+8 -> 46035 | C31: 12.30 - 13.00 | P31: =IFERROR(H31/Setup!$C$6,"") -> 0 | Q31: =IFERROR(H31-P31,"") -> 0
A32: =TEXT(Setup!$C$5+8,"dddd") -> Tuesday | B32: =Setup!$C$5+8 -> 46035 | C32: 13.00 - 13.30 | P32: =IFERROR(H32/Setup!$C$6,"") -> 0 | Q32: =IFERROR(H32-P32,"") -> 0
A33: =TEXT(Setup!$C$5+8,"dddd") -> Tuesday | B33: =Setup!$C$5+8 -> 46035 | C33: 13.30 - 14.00 | P33: =IFERROR(H33/Setup!$C$6,"") -> 0 | Q33: =IFERROR(H33-P33,"") -> 0
A34: =TEXT(Setup!$C$5+8,"dddd") -> Tuesday | B34: =Setup!$C$5+8 -> 46035 | C34: 14.00 - 14.30 | P34: =IFERROR(H34/Setup!$C$6,"") -> 0 | Q34: =IFERROR(H34-P34,"") -> 0
A35: =TEXT(Setup!$C$5+8,"dddd") -> Tuesday | B35: =Setup!$C$5+8 -> 46035 | C35: 14.30 - 15.00 | P35: =IFERROR(H35/Setup!$C$6,"") -> 0 | Q35: =IFERROR(H35-P35,"") -> 0
... A44: =TEXT(Setup!$C$5+8,"dddd") -> Tuesday | B44: =Setup!$C$5+8 -> 46035 | C44: ONLINE | P44: =IFERROR(H44/Setup!$C$6,"") -> 0 | Q44: =IFERROR(H44-P44,"") -> 0
A45: =TEXT(Setup!$C$5+8,"dddd") -> Tuesday | B45: =Setup!$C$5+8 -> 46035 | C45: TOTAL | D45: =SUM(D24:D44) -> 0 | E45: =SUM(E24:E44) -> 0 | F45: =SUM(F24:F44) -> 0 | G45: =SUM(G24:G44) -> 0 | H45: =SUM(H24:H44) -> 0 | I45: =IFERROR(E45/D45,"") | J45: =IFERROR(H45/E45,"") | K45: =SUM(K24:K44) -> 0 | M45: =SUM(M24:M44) -> 0 | N45: =IFERROR(H45-Wk1!H45,"") -> 0 | O45: =IFERROR(D45-Wk1!D45,"") -> 0 | P45: =SUM(P24:P44) -> 0 | Q45: =SUM(Q24:Q44) -> 0 | R45: =IFERROR(INDEX('Last Year'!$C$6:$C$369,MATCH(B45-364,'Last Year'!$B$6:$B$369,0)),"") -> 0 | S45: =IFERROR(H45/R45-1,"")
A46: =TEXT(Setup!$C$5+9,"dddd") -> Wednesday | B46: =Setup!$C$5+9 -> 46036 | C46: 9.00 - 9.30 | P46: =IFERROR(H46/Setup!$C$6,"") -> 0 | Q46: =IFERROR(H46-P46,"") -> 0
A47: =TEXT(Setup!$C$5+9,"dddd") -> Wednesday | B47: =Setup!$C$5+9 -> 46036 | C47: 9.30 - 10.00 | P47: =IFERROR(H47/Setup!$C$6,"") -> 0 | Q47: =IFERROR(H47-P47,"") -> 0
A48: =TEXT(Setup!$C$5+9,"dddd") -> Wednesday | B48: =Setup!$C$5+9 -> 46036 | C48: 10.00 - 10.30 | P48: =IFERROR(H48/Setup!$C$6,"") -> 0 | Q48: =IFERROR(H48-P48,"") -> 0
A49: =TEXT(Setup!$C$5+9,"dddd") -> Wednesday | B49: =Setup!$C$5+9 -> 46036 | C49: 10.30 - 11.00 | P49: =IFERROR(H49/Setup!$C$6,"") -> 0 | Q49: =IFERROR(H49-P49,"") -> 0
A50: =TEXT(Setup!$C$5+9,"dddd") -> Wednesday | B50: =Setup!$C$5+9 -> 46036 | C50: 11.00 - 11.30 | P50: =IFERROR(H50/Setup!$C$6,"") -> 0 | Q50: =IFERROR(H50-P50,"") -> 0
A51: =TEXT(Setup!$C$5+9,"dddd") -> Wednesday | B51: =Setup!$C$5+9 -> 46036 | C51: 11.30 - 12.00 | P51: =IFERROR(H51/Setup!$C$6,"") -> 0 | Q51: =IFERROR(H51-P51,"") -> 0
A52: =TEXT(Setup!$C$5+9,"dddd") -> Wednesday | B52: =Setup!$C$5+9 -> 46036 | C52: 12.00 - 12.30 | P52: =IFERROR(H52/Setup!$C$6,"") -> 0 | Q52: =IFERROR(H52-P52,"") -> 0
A53: =TEXT(Setup!$C$5+9,"dddd") -> Wednesday | B53: =Setup!$C$5+9 -> 46036 | C53: 12.30 - 13.00 | P53: =IFERROR(H53/Setup!$C$6,"") -> 0 | Q53: =IFERROR(H53-P53,"") -> 0
A54: =TEXT(Setup!$C$5+9,"dddd") -> Wednesday | B54: =Setup!$C$5+9 -> 46036 | C54: 13.00 - 13.30 | P54: =IFERROR(H54/Setup!$C$6,"") -> 0 | Q54: =IFERROR(H54-P54,"") -> 0
A55: =TEXT(Setup!$C$5+9,"dddd") -> Wednesday | B55: =Setup!$C$5+9 -> 46036 | C55: 13.30 - 14.00 | P55: =IFERROR(H55/Setup!$C$6,"") -> 0 | Q55: =IFERROR(H55-P55,"") -> 0
A56: =TEXT(Setup!$C$5+9,"dddd") -> Wednesday | B56: =Setup!$C$5+9 -> 46036 | C56: 14.00 - 14.30 | P56: =IFERROR(H56/Setup!$C$6,"") -> 0 | Q56: =IFERROR(H56-P56,"") -> 0
A57: =TEXT(Setup!$C$5+9,"dddd") -> Wednesday | B57: =Setup!$C$5+9 -> 46036 | C57: 14.30 - 15.00 | P57: =IFERROR(H57/Setup!$C$6,"") -> 0 | Q57: =IFERROR(H57-P57,"") -> 0
... A66: =TEXT(Setup!$C$5+9,"dddd") -> Wednesday | B66: =Setup!$C$5+9 -> 46036 | C66: ONLINE | P66: =IFERROR(H66/Setup!$C$6,"") -> 0 | Q66: =IFERROR(H66-P66,"") -> 0
A67: =TEXT(Setup!$C$5+9,"dddd") -> Wednesday | B67: =Setup!$C$5+9 -> 46036 | C67: TOTAL | D67: =SUM(D46:D66) -> 0 | E67: =SUM(E46:E66) -> 0 | F67: =SUM(F46:F66) -> 0 | G67: =SUM(G46:G66) -> 0 | H67: =SUM(H46:H66) -> 0 | I67: =IFERROR(E67/D67,"") | J67: =IFERROR(H67/E67,"") | K67: =SUM(K46:K66) -> 0 | M67: =SUM(M46:M66) -> 0 | N67: =IFERROR(H67-Wk1!H67,"") -> 0 | O67: =IFERROR(D67-Wk1!D67,"") -> 0 | P67: =SUM(P46:P66) -> 0 | Q67: =SUM(Q46:Q66) -> 0 | R67: =IFERROR(INDEX('Last Year'!$C$6:$C$369,MATCH(B67-364,'Last Year'!$B$6:$B$369,0)),"") -> 0 | S67: =IFERROR(H67/R67-1,"")
A68: =TEXT(Setup!$C$5+10,"dddd") -> Thursday | B68: =Setup!$C$5+10 -> 46037 | C68: 9.00 - 9.30 | P68: =IFERROR(H68/Setup!$C$6,"") -> 0 | Q68: =IFERROR(H68-P68,"") -> 0
A69: =TEXT(Setup!$C$5+10,"dddd") -> Thursday | B69: =Setup!$C$5+10 -> 46037 | C69: 9.30 - 10.00 | P69: =IFERROR(H69/Setup!$C$6,"") -> 0 | Q69: =IFERROR(H69-P69,"") -> 0
A70: =TEXT(Setup!$C$5+10,"dddd") -> Thursday | B70: =Setup!$C$5+10 -> 46037 | C70: 10.00 - 10.30 | P70: =IFERROR(H70/Setup!$C$6,"") -> 0 | Q70: =IFERROR(H70-P70,"") -> 0
A71: =TEXT(Setup!$C$5+10,"dddd") -> Thursday | B71: =Setup!$C$5+10 -> 46037 | C71: 10.30 - 11.00 | P71: =IFERROR(H71/Setup!$C$6,"") -> 0 | Q71: =IFERROR(H71-P71,"") -> 0
A72: =TEXT(Setup!$C$5+10,"dddd") -> Thursday | B72: =Setup!$C$5+10 -> 46037 | C72: 11.00 - 11.30 | P72: =IFERROR(H72/Setup!$C$6,"") -> 0 | Q72: =IFERROR(H72-P72,"") -> 0
A73: =TEXT(Setup!$C$5+10,"dddd") -> Thursday | B73: =Setup!$C$5+10 -> 46037 | C73: 11.30 - 12.00 | P73: =IFERROR(H73/Setup!$C$6,"") -> 0 | Q73: =IFERROR(H73-P73,"") -> 0
A74: =TEXT(Setup!$C$5+10,"dddd") -> Thursday | B74: =Setup!$C$5+10 -> 46037 | C74: 12.00 - 12.30 | P74: =IFERROR(H74/Setup!$C$6,"") -> 0 | Q74: =IFERROR(H74-P74,"") -> 0
A75: =TEXT(Setup!$C$5+10,"dddd") -> Thursday | B75: =Setup!$C$5+10 -> 46037 | C75: 12.30 - 13.00 | P75: =IFERROR(H75/Setup!$C$6,"") -> 0 | Q75: =IFERROR(H75-P75,"") -> 0
A76: =TEXT(Setup!$C$5+10,"dddd") -> Thursday | B76: =Setup!$C$5+10 -> 46037 | C76: 13.00 - 13.30 | P76: =IFERROR(H76/Setup!$C$6,"") -> 0 | Q76: =IFERROR(H76-P76,"") -> 0
A77: =TEXT(Setup!$C$5+10,"dddd") -> Thursday | B77: =Setup!$C$5+10 -> 46037 | C77: 13.30 - 14.00 | P77: =IFERROR(H77/Setup!$C$6,"") -> 0 | Q77: =IFERROR(H77-P77,"") -> 0
A78: =TEXT(Setup!$C$5+10,"dddd") -> Thursday | B78: =Setup!$C$5+10 -> 46037 | C78: 14.00 - 14.30 | P78: =IFERROR(H78/Setup!$C$6,"") -> 0 | Q78: =IFERROR(H78-P78,"") -> 0
A79: =TEXT(Setup!$C$5+10,"dddd") -> Thursday | B79: =Setup!$C$5+10 -> 46037 | C79: 14.30 - 15.00 | P79: =IFERROR(H79/Setup!$C$6,"") -> 0 | Q79: =IFERROR(H79-P79,"") -> 0
... A88: =TEXT(Setup!$C$5+10,"dddd") -> Thursday | B88: =Setup!$C$5+10 -> 46037 | C88: ONLINE | P88: =IFERROR(H88/Setup!$C$6,"") -> 0 | Q88: =IFERROR(H88-P88,"") -> 0
A89: =TEXT(Setup!$C$5+10,"dddd") -> Thursday | B89: =Setup!$C$5+10 -> 46037 | C89: TOTAL | D89: =SUM(D68:D88) -> 0 | E89: =SUM(E68:E88) -> 0 | F89: =SUM(F68:F88) -> 0 | G89: =SUM(G68:G88) -> 0 | H89: =SUM(H68:H88) -> 0 | I89: =IFERROR(E89/D89,"") | J89: =IFERROR(H89/E89,"") | K89: =SUM(K68:K88) -> 0 | M89: =SUM(M68:M88) -> 0 | N89: =IFERROR(H89-Wk1!H89,"") -> 0 | O89: =IFERROR(D89-Wk1!D89,"") -> 0 | P89: =SUM(P68:P88) -> 0 | Q89: =SUM(Q68:Q88) -> 0 | R89: =IFERROR(INDEX('Last Year'!$C$6:$C$369,MATCH(B89-364,'Last Year'!$B$6:$B$369,0)),"") -> 0 | S89: =IFERROR(H89/R89-1,"")
A90: =TEXT(Setup!$C$5+11,"dddd") -> Friday | B90: =Setup!$C$5+11 -> 46038 | C90: 9.00 - 9.30 | P90: =IFERROR(H90/Setup!$C$6,"") -> 0 | Q90: =IFERROR(H90-P90,"") -> 0
A91: =TEXT(Setup!$C$5+11,"dddd") -> Friday | B91: =Setup!$C$5+11 -> 46038 | C91: 9.30 - 10.00 | P91: =IFERROR(H91/Setup!$C$6,"") -> 0 | Q91: =IFERROR(H91-P91,"") -> 0
A92: =TEXT(Setup!$C$5+11,"dddd") -> Friday | B92: =Setup!$C$5+11 -> 46038 | C92: 10.00 - 10.30 | P92: =IFERROR(H92/Setup!$C$6,"") -> 0 | Q92: =IFERROR(H92-P92,"") -> 0
A93: =TEXT(Setup!$C$5+11,"dddd") -> Friday | B93: =Setup!$C$5+11 -> 46038 | C93: 10.30 - 11.00 | P93: =IFERROR(H93/Setup!$C$6,"") -> 0 | Q93: =IFERROR(H93-P93,"") -> 0
A94: =TEXT(Setup!$C$5+11,"dddd") -> Friday | B94: =Setup!$C$5+11 -> 46038 | C94: 11.00 - 11.30 | P94: =IFERROR(H94/Setup!$C$6,"") -> 0 | Q94: =IFERROR(H94-P94,"") -> 0
A95: =TEXT(Setup!$C$5+11,"dddd") -> Friday | B95: =Setup!$C$5+11 -> 46038 | C95: 11.30 - 12.00 | P95: =IFERROR(H95/Setup!$C$6,"") -> 0 | Q95: =IFERROR(H95-P95,"") -> 0
A96: =TEXT(Setup!$C$5+11,"dddd") -> Friday | B96: =Setup!$C$5+11 -> 46038 | C96: 12.00 - 12.30 | P96: =IFERROR(H96/Setup!$C$6,"") -> 0 | Q96: =IFERROR(H96-P96,"") -> 0
A97: =TEXT(Setup!$C$5+11,"dddd") -> Friday | B97: =Setup!$C$5+11 -> 46038 | C97: 12.30 - 13.00 | P97: =IFERROR(H97/Setup!$C$6,"") -> 0 | Q97: =IFERROR(H97-P97,"") -> 0
A98: =TEXT(Setup!$C$5+11,"dddd") -> Friday | B98: =Setup!$C$5+11 -> 46038 | C98: 13.00 - 13.30 | P98: =IFERROR(H98/Setup!$C$6,"") -> 0 | Q98: =IFERROR(H98-P98,"") -> 0
A99: =TEXT(Setup!$C$5+11,"dddd") -> Friday | B99: =Setup!$C$5+11 -> 46038 | C99: 13.30 - 14.00 | P99: =IFERROR(H99/Setup!$C$6,"") -> 0 | Q99: =IFERROR(H99-P99,"") -> 0
A100: =TEXT(Setup!$C$5+11,"dddd") -> Friday | B100: =Setup!$C$5+11 -> 46038 | C100: 14.00 - 14.30 | P100: =IFERROR(H100/Setup!$C$6,"") -> 0 | Q100: =IFERROR(H100-P100,"") -> 0
A101: =TEXT(Setup!$C$5+11,"dddd") -> Friday | B101: =Setup!$C$5+11 -> 46038 | C101: 14.30 - 15.00 | P101: =IFERROR(H101/Setup!$C$6,"") -> 0 | Q101: =IFERROR(H101-P101,"") -> 0
... A110: =TEXT(Setup!$C$5+11,"dddd") -> Friday | B110: =Setup!$C$5+11 -> 46038 | C110: ONLINE | P110: =IFERROR(H110/Setup!$C$6,"") -> 0 | Q110: =IFERROR(H110-P110,"") -> 0
A111: =TEXT(Setup!$C$5+11,"dddd") -> Friday | B111: =Setup!$C$5+11 -> 46038 | C111: TOTAL | D111: =SUM(D90:D110) -> 0 | E111: =SUM(E90:E110) -> 0 | F111: =SUM(F90:F110) -> 0 | G111: =SUM(G90:G110) -> 0 | H111: =SUM(H90:H110) -> 0 | I111: =IFERROR(E111/D111,"") | J111: =IFERROR(H111/E111,"") | K111: =SUM(K90:K110) -> 0 | M111: =SUM(M90:M110) -> 0 | N111: =IFERROR(H111-Wk1!H111,"") -> 0 | O111: =IFERROR(D111-Wk1!D111,"") -> 0 | P111: =SUM(P90:P110) -> 0 | Q111: =SUM(Q90:Q110) -> 0 | R111: =IFERROR(INDEX('Last Year'!$C$6:$C$369,MATCH(B111-364,'Last Year'!$B$6:$B$369,0)),"") -> 0 | S111: =IFERROR(H111/R111-1,"")
A112: =TEXT(Setup!$C$5+12,"dddd") -> Saturday | B112: =Setup!$C$5+12 -> 46039 | C112: 9.00 - 9.30 | P112: =IFERROR(H112/Setup!$C$6,"") -> 0 | Q112: =IFERROR(H112-P112,"") -> 0
A113: =TEXT(Setup!$C$5+12,"dddd") -> Saturday | B113: =Setup!$C$5+12 -> 46039 | C113: 9.30 - 10.00 | P113: =IFERROR(H113/Setup!$C$6,"") -> 0 | Q113: =IFERROR(H113-P113,"") -> 0
A114: =TEXT(Setup!$C$5+12,"dddd") -> Saturday | B114: =Setup!$C$5+12 -> 46039 | C114: 10.00 - 10.30 | P114: =IFERROR(H114/Setup!$C$6,"") -> 0 | Q114: =IFERROR(H114-P114,"") -> 0
A115: =TEXT(Setup!$C$5+12,"dddd") -> Saturday | B115: =Setup!$C$5+12 -> 46039 | C115: 10.30 - 11.00 | P115: =IFERROR(H115/Setup!$C$6,"") -> 0 | Q115: =IFERROR(H115-P115,"") -> 0
A116: =TEXT(Setup!$C$5+12,"dddd") -> Saturday | B116: =Setup!$C$5+12 -> 46039 | C116: 11.00 - 11.30 | P116: =IFERROR(H116/Setup!$C$6,"") -> 0 | Q116: =IFERROR(H116-P116,"") -> 0
A117: =TEXT(Setup!$C$5+12,"dddd") -> Saturday | B117: =Setup!$C$5+12 -> 46039 | C117: 11.30 - 12.00 | P117: =IFERROR(H117/Setup!$C$6,"") -> 0 | Q117: =IFERROR(H117-P117,"") -> 0
A118: =TEXT(Setup!$C$5+12,"dddd") -> Saturday | B118: =Setup!$C$5+12 -> 46039 | C118: 12.00 - 12.30 | P118: =IFERROR(H118/Setup!$C$6,"") -> 0 | Q118: =IFERROR(H118-P118,"") -> 0
A119: =TEXT(Setup!$C$5+12,"dddd") -> Saturday | B119: =Setup!$C$5+12 -> 46039 | C119: 12.30 - 13.00 | P119: =IFERROR(H119/Setup!$C$6,"") -> 0 | Q119: =IFERROR(H119-P119,"") -> 0
A120: =TEXT(Setup!$C$5+12,"dddd") -> Saturday | B120: =Setup!$C$5+12 -> 46039 | C120: 13.00 - 13.30 | P120: =IFERROR(H120/Setup!$C$6,"") -> 0 | Q120: =IFERROR(H120-P120,"") -> 0
A121: =TEXT(Setup!$C$5+12,"dddd") -> Saturday | B121: =Setup!$C$5+12 -> 46039 | C121: 13.30 - 14.00 | P121: =IFERROR(H121/Setup!$C$6,"") -> 0 | Q121: =IFERROR(H121-P121,"") -> 0
A122: =TEXT(Setup!$C$5+12,"dddd") -> Saturday | B122: =Setup!$C$5+12 -> 46039 | C122: 14.00 - 14.30 | P122: =IFERROR(H122/Setup!$C$6,"") -> 0 | Q122: =IFERROR(H122-P122,"") -> 0
A123: =TEXT(Setup!$C$5+12,"dddd") -> Saturday | B123: =Setup!$C$5+12 -> 46039 | C123: 14.30 - 15.00 | P123: =IFERROR(H123/Setup!$C$6,"") -> 0 | Q123: =IFERROR(H123-P123,"") -> 0
... A132: =TEXT(Setup!$C$5+12,"dddd") -> Saturday | B132: =Setup!$C$5+12 -> 46039 | C132: ONLINE | P132: =IFERROR(H132/Setup!$C$6,"") -> 0 | Q132: =IFERROR(H132-P132,"") -> 0
A133: =TEXT(Setup!$C$5+12,"dddd") -> Saturday | B133: =Setup!$C$5+12 -> 46039 | C133: TOTAL | D133: =SUM(D112:D132) -> 0 | E133: =SUM(E112:E132) -> 0 | F133: =SUM(F112:F132) -> 0 | G133: =SUM(G112:G132) -> 0 | H133: =SUM(H112:H132) -> 0 | I133: =IFERROR(E133/D133,"") | J133: =IFERROR(H133/E133,"") | K133: =SUM(K112:K132) -> 0 | M133: =SUM(M112:M132) -> 0 | N133: =IFERROR(H133-Wk1!H133,"") -> 0 | O133: =IFERROR(D133-Wk1!D133,"") -> 0 | P133: =SUM(P112:P132) -> 0 | Q133: =SUM(Q112:Q132) -> 0 | R133: =IFERROR(INDEX('Last Year'!$C$6:$C$369,MATCH(B133-364,'Last Year'!$B$6:$B$369,0)),"") -> 0 | S133: =IFERROR(H133/R133-1,"")
A134: =TEXT(Setup!$C$5+13,"dddd") -> Sunday | B134: =Setup!$C$5+13 -> 46040 | C134: 9.00 - 9.30 | P134: =IFERROR(H134/Setup!$C$6,"") -> 0 | Q134: =IFERROR(H134-P134,"") -> 0
A135: =TEXT(Setup!$C$5+13,"dddd") -> Sunday | B135: =Setup!$C$5+13 -> 46040 | C135: 9.30 - 10.00 | P135: =IFERROR(H135/Setup!$C$6,"") -> 0 | Q135: =IFERROR(H135-P135,"") -> 0
A136: =TEXT(Setup!$C$5+13,"dddd") -> Sunday | B136: =Setup!$C$5+13 -> 46040 | C136: 10.00 - 10.30 | P136: =IFERROR(H136/Setup!$C$6,"") -> 0 | Q136: =IFERROR(H136-P136,"") -> 0
A137: =TEXT(Setup!$C$5+13,"dddd") -> Sunday | B137: =Setup!$C$5+13 -> 46040 | C137: 10.30 - 11.00 | P137: =IFERROR(H137/Setup!$C$6,"") -> 0 | Q137: =IFERROR(H137-P137,"") -> 0
A138: =TEXT(Setup!$C$5+13,"dddd") -> Sunday | B138: =Setup!$C$5+13 -> 46040 | C138: 11.00 - 11.30 | P138: =IFERROR(H138/Setup!$C$6,"") -> 0 | Q138: =IFERROR(H138-P138,"") -> 0
A139: =TEXT(Setup!$C$5+13,"dddd") -> Sunday | B139: =Setup!$C$5+13 -> 46040 | C139: 11.30 - 12.00 | P139: =IFERROR(H139/Setup!$C$6,"") -> 0 | Q139: =IFERROR(H139-P139,"") -> 0
A140: =TEXT(Setup!$C$5+13,"dddd") -> Sunday | B140: =Setup!$C$5+13 -> 46040 | C140: 12.00 - 12.30 | P140: =IFERROR(H140/Setup!$C$6,"") -> 0 | Q140: =IFERROR(H140-P140,"") -> 0
A141: =TEXT(Setup!$C$5+13,"dddd") -> Sunday | B141: =Setup!$C$5+13 -> 46040 | C141: 12.30 - 13.00 | P141: =IFERROR(H141/Setup!$C$6,"") -> 0 | Q141: =IFERROR(H141-P141,"") -> 0
A142: =TEXT(Setup!$C$5+13,"dddd") -> Sunday | B142: =Setup!$C$5+13 -> 46040 | C142: 13.00 - 13.30 | P142: =IFERROR(H142/Setup!$C$6,"") -> 0 | Q142: =IFERROR(H142-P142,"") -> 0
A143: =TEXT(Setup!$C$5+13,"dddd") -> Sunday | B143: =Setup!$C$5+13 -> 46040 | C143: 13.30 - 14.00 | P143: =IFERROR(H143/Setup!$C$6,"") -> 0 | Q143: =IFERROR(H143-P143,"") -> 0
A144: =TEXT(Setup!$C$5+13,"dddd") -> Sunday | B144: =Setup!$C$5+13 -> 46040 | C144: 14.00 - 14.30 | P144: =IFERROR(H144/Setup!$C$6,"") -> 0 | Q144: =IFERROR(H144-P144,"") -> 0
A145: =TEXT(Setup!$C$5+13,"dddd") -> Sunday | B145: =Setup!$C$5+13 -> 46040 | C145: 14.30 - 15.00 | P145: =IFERROR(H145/Setup!$C$6,"") -> 0 | Q145: =IFERROR(H145-P145,"") -> 0
... A154: =TEXT(Setup!$C$5+13,"dddd") -> Sunday | B154: =Setup!$C$5+13 -> 46040 | C154: ONLINE | P154: =IFERROR(H154/Setup!$C$6,"") -> 0 | Q154: =IFERROR(H154-P154,"") -> 0
A155: =TEXT(Setup!$C$5+13,"dddd") -> Sunday | B155: =Setup!$C$5+13 -> 46040 | C155: TOTAL | D155: =SUM(D134:D154) -> 0 | E155: =SUM(E134:E154) -> 0 | F155: =SUM(F134:F154) -> 0 | G155: =SUM(G134:G154) -> 0 | H155: =SUM(H134:H154) -> 0 | I155: =IFERROR(E155/D155,"") | J155: =IFERROR(H155/E155,"") | K155: =SUM(K134:K154) -> 0 | M155: =SUM(M134:M154) -> 0 | N155: =IFERROR(H155-Wk1!H155,"") -> 0 | O155: =IFERROR(D155-Wk1!D155,"") -> 0 | P155: =SUM(P134:P154) -> 0 | Q155: =SUM(Q134:Q154) -> 0 | R155: =IFERROR(INDEX('Last Year'!$C$6:$C$369,MATCH(B155-364,'Last Year'!$B$6:$B$369,0)),"") -> 0 | S155: =IFERROR(H155/R155-1,"")
C156: FULL WEEK | D156: =D23+D45+D67+D89+D111+D133+D155 -> 0 | E156: =E23+E45+E67+E89+E111+E133+E155 -> 0 | F156: =F23+F45+F67+F89+F111+F133+F155 -> 0 | G156: =G23+G45+G67+G89+G111+G133+G155 -> 0 | H156: =H23+H45+H67+H89+H111+H133+H155 -> 0 | I156: =IFERROR(E156/D156,"") | J156: =IFERROR(H156/E156,"") | K156: =K23+K45+K67+K89+K111+K133+K155 -> 0 | M156: =M23+M45+M67+M89+M111+M133+M155 -> 0 | P156: =P23+P45+P67+P89+P111+P133+P155 -> 0 | Q156: =Q23+Q45+Q67+Q89+Q111+Q133+Q155 -> 0 | R156: =R23+R45+R67+R89+R111+R133+R155 -> 0 | S156: =IFERROR(H156/R156-1,"")
...

Sheet Wk3
A1: Day | B1: Date | C1: Time | D1: Customers In | E1: Sales | F1: Vouchers Used | G1: Walk In/Out | H1: Sale Amount | I1: Conversion | J1: Avg Sale | K1: Tracked Category | L1: Notes | M1: Cash | N1: vs Last Wk € | O1: vs Last Wk Cust | P1: Est. Cost | Q1: Est. Profit | R1: Last Year Day | S1: vs Last Year
A2: =TEXT(Setup!$C$5+14,"dddd") -> Monday | B2: =Setup!$C$5+14 -> 46041 | C2: 9.00 - 9.30 | P2: =IFERROR(H2/Setup!$C$6,"") -> 0 | Q2: =IFERROR(H2-P2,"") -> 0
A3: =TEXT(Setup!$C$5+14,"dddd") -> Monday | B3: =Setup!$C$5+14 -> 46041 | C3: 9.30 - 10.00 | P3: =IFERROR(H3/Setup!$C$6,"") -> 0 | Q3: =IFERROR(H3-P3,"") -> 0
A4: =TEXT(Setup!$C$5+14,"dddd") -> Monday | B4: =Setup!$C$5+14 -> 46041 | C4: 10.00 - 10.30 | P4: =IFERROR(H4/Setup!$C$6,"") -> 0 | Q4: =IFERROR(H4-P4,"") -> 0
A5: =TEXT(Setup!$C$5+14,"dddd") -> Monday | B5: =Setup!$C$5+14 -> 46041 | C5: 10.30 - 11.00 | P5: =IFERROR(H5/Setup!$C$6,"") -> 0 | Q5: =IFERROR(H5-P5,"") -> 0
A6: =TEXT(Setup!$C$5+14,"dddd") -> Monday | B6: =Setup!$C$5+14 -> 46041 | C6: 11.00 - 11.30 | P6: =IFERROR(H6/Setup!$C$6,"") -> 0 | Q6: =IFERROR(H6-P6,"") -> 0
A7: =TEXT(Setup!$C$5+14,"dddd") -> Monday | B7: =Setup!$C$5+14 -> 46041 | C7: 11.30 - 12.00 | P7: =IFERROR(H7/Setup!$C$6,"") -> 0 | Q7: =IFERROR(H7-P7,"") -> 0
A8: =TEXT(Setup!$C$5+14,"dddd") -> Monday | B8: =Setup!$C$5+14 -> 46041 | C8: 12.00 - 12.30 | P8: =IFERROR(H8/Setup!$C$6,"") -> 0 | Q8: =IFERROR(H8-P8,"") -> 0
A9: =TEXT(Setup!$C$5+14,"dddd") -> Monday | B9: =Setup!$C$5+14 -> 46041 | C9: 12.30 - 13.00 | P9: =IFERROR(H9/Setup!$C$6,"") -> 0 | Q9: =IFERROR(H9-P9,"") -> 0
A10: =TEXT(Setup!$C$5+14,"dddd") -> Monday | B10: =Setup!$C$5+14 -> 46041 | C10: 13.00 - 13.30 | P10: =IFERROR(H10/Setup!$C$6,"") -> 0 | Q10: =IFERROR(H10-P10,"") -> 0
A11: =TEXT(Setup!$C$5+14,"dddd") -> Monday | B11: =Setup!$C$5+14 -> 46041 | C11: 13.30 - 14.00 | P11: =IFERROR(H11/Setup!$C$6,"") -> 0 | Q11: =IFERROR(H11-P11,"") -> 0
A12: =TEXT(Setup!$C$5+14,"dddd") -> Monday | B12: =Setup!$C$5+14 -> 46041 | C12: 14.00 - 14.30 | P12: =IFERROR(H12/Setup!$C$6,"") -> 0 | Q12: =IFERROR(H12-P12,"") -> 0
A13: =TEXT(Setup!$C$5+14,"dddd") -> Monday | B13: =Setup!$C$5+14 -> 46041 | C13: 14.30 - 15.00 | P13: =IFERROR(H13/Setup!$C$6,"") -> 0 | Q13: =IFERROR(H13-P13,"") -> 0
... A22: =TEXT(Setup!$C$5+14,"dddd") -> Monday | B22: =Setup!$C$5+14 -> 46041 | C22: ONLINE | P22: =IFERROR(H22/Setup!$C$6,"") -> 0 | Q22: =IFERROR(H22-P22,"") -> 0
A23: =TEXT(Setup!$C$5+14,"dddd") -> Monday | B23: =Setup!$C$5+14 -> 46041 | C23: TOTAL | D23: =SUM(D2:D22) -> 0 | E23: =SUM(E2:E22) -> 0 | F23: =SUM(F2:F22) -> 0 | G23: =SUM(G2:G22) -> 0 | H23: =SUM(H2:H22) -> 0 | I23: =IFERROR(E23/D23,"") | J23: =IFERROR(H23/E23,"") | K23: =SUM(K2:K22) -> 0 | M23: =SUM(M2:M22) -> 0 | N23: =IFERROR(H23-Wk2!H23,"") -> 0 | O23: =IFERROR(D23-Wk2!D23,"") -> 0 | P23: =SUM(P2:P22) -> 0 | Q23: =SUM(Q2:Q22) -> 0 | R23: =IFERROR(INDEX('Last Year'!$C$6:$C$369,MATCH(B23-364,'Last Year'!$B$6:$B$369,0)),"") -> 0 | S23: =IFERROR(H23/R23-1,"")
A24: =TEXT(Setup!$C$5+15,"dddd") -> Tuesday | B24: =Setup!$C$5+15 -> 46042 | C24: 9.00 - 9.30 | P24: =IFERROR(H24/Setup!$C$6,"") -> 0 | Q24: =IFERROR(H24-P24,"") -> 0
A25: =TEXT(Setup!$C$5+15,"dddd") -> Tuesday | B25: =Setup!$C$5+15 -> 46042 | C25: 9.30 - 10.00 | P25: =IFERROR(H25/Setup!$C$6,"") -> 0 | Q25: =IFERROR(H25-P25,"") -> 0
A26: =TEXT(Setup!$C$5+15,"dddd") -> Tuesday | B26: =Setup!$C$5+15 -> 46042 | C26: 10.00 - 10.30 | P26: =IFERROR(H26/Setup!$C$6,"") -> 0 | Q26: =IFERROR(H26-P26,"") -> 0
A27: =TEXT(Setup!$C$5+15,"dddd") -> Tuesday | B27: =Setup!$C$5+15 -> 46042 | C27: 10.30 - 11.00 | P27: =IFERROR(H27/Setup!$C$6,"") -> 0 | Q27: =IFERROR(H27-P27,"") -> 0
A28: =TEXT(Setup!$C$5+15,"dddd") -> Tuesday | B28: =Setup!$C$5+15 -> 46042 | C28: 11.00 - 11.30 | P28: =IFERROR(H28/Setup!$C$6,"") -> 0 | Q28: =IFERROR(H28-P28,"") -> 0
A29: =TEXT(Setup!$C$5+15,"dddd") -> Tuesday | B29: =Setup!$C$5+15 -> 46042 | C29: 11.30 - 12.00 | P29: =IFERROR(H29/Setup!$C$6,"") -> 0 | Q29: =IFERROR(H29-P29,"") -> 0
A30: =TEXT(Setup!$C$5+15,"dddd") -> Tuesday | B30: =Setup!$C$5+15 -> 46042 | C30: 12.00 - 12.30 | P30: =IFERROR(H30/Setup!$C$6,"") -> 0 | Q30: =IFERROR(H30-P30,"") -> 0
A31: =TEXT(Setup!$C$5+15,"dddd") -> Tuesday | B31: =Setup!$C$5+15 -> 46042 | C31: 12.30 - 13.00 | P31: =IFERROR(H31/Setup!$C$6,"") -> 0 | Q31: =IFERROR(H31-P31,"") -> 0
A32: =TEXT(Setup!$C$5+15,"dddd") -> Tuesday | B32: =Setup!$C$5+15 -> 46042 | C32: 13.00 - 13.30 | P32: =IFERROR(H32/Setup!$C$6,"") -> 0 | Q32: =IFERROR(H32-P32,"") -> 0
A33: =TEXT(Setup!$C$5+15,"dddd") -> Tuesday | B33: =Setup!$C$5+15 -> 46042 | C33: 13.30 - 14.00 | P33: =IFERROR(H33/Setup!$C$6,"") -> 0 | Q33: =IFERROR(H33-P33,"") -> 0
A34: =TEXT(Setup!$C$5+15,"dddd") -> Tuesday | B34: =Setup!$C$5+15 -> 46042 | C34: 14.00 - 14.30 | P34: =IFERROR(H34/Setup!$C$6,"") -> 0 | Q34: =IFERROR(H34-P34,"") -> 0
A35: =TEXT(Setup!$C$5+15,"dddd") -> Tuesday | B35: =Setup!$C$5+15 -> 46042 | C35: 14.30 - 15.00 | P35: =IFERROR(H35/Setup!$C$6,"") -> 0 | Q35: =IFERROR(H35-P35,"") -> 0
... A44: =TEXT(Setup!$C$5+15,"dddd") -> Tuesday | B44: =Setup!$C$5+15 -> 46042 | C44: ONLINE | P44: =IFERROR(H44/Setup!$C$6,"") -> 0 | Q44: =IFERROR(H44-P44,"") -> 0
A45: =TEXT(Setup!$C$5+15,"dddd") -> Tuesday | B45: =Setup!$C$5+15 -> 46042 | C45: TOTAL | D45: =SUM(D24:D44) -> 0 | E45: =SUM(E24:E44) -> 0 | F45: =SUM(F24:F44) -> 0 | G45: =SUM(G24:G44) -> 0 | H45: =SUM(H24:H44) -> 0 | I45: =IFERROR(E45/D45,"") | J45: =IFERROR(H45/E45,"") | K45: =SUM(K24:K44) -> 0 | M45: =SUM(M24:M44) -> 0 | N45: =IFERROR(H45-Wk2!H45,"") -> 0 | O45: =IFERROR(D45-Wk2!D45,"") -> 0 | P45: =SUM(P24:P44) -> 0 | Q45: =SUM(Q24:Q44) -> 0 | R45: =IFERROR(INDEX('Last Year'!$C$6:$C$369,MATCH(B45-364,'Last Year'!$B$6:$B$369,0)),"") -> 0 | S45: =IFERROR(H45/R45-1,"")
A46: =TEXT(Setup!$C$5+16,"dddd") -> Wednesday | B46: =Setup!$C$5+16 -> 46043 | C46: 9.00 - 9.30 | P46: =IFERROR(H46/Setup!$C$6,"") -> 0 | Q46: =IFERROR(H46-P46,"") -> 0
A47: =TEXT(Setup!$C$5+16,"dddd") -> Wednesday | B47: =Setup!$C$5+16 -> 46043 | C47: 9.30 - 10.00 | P47: =IFERROR(H47/Setup!$C$6,"") -> 0 | Q47: =IFERROR(H47-P47,"") -> 0
A48: =TEXT(Setup!$C$5+16,"dddd") -> Wednesday | B48: =Setup!$C$5+16 -> 46043 | C48: 10.00 - 10.30 | P48: =IFERROR(H48/Setup!$C$6,"") -> 0 | Q48: =IFERROR(H48-P48,"") -> 0
A49: =TEXT(Setup!$C$5+16,"dddd") -> Wednesday | B49: =Setup!$C$5+16 -> 46043 | C49: 10.30 - 11.00 | P49: =IFERROR(H49/Setup!$C$6,"") -> 0 | Q49: =IFERROR(H49-P49,"") -> 0
A50: =TEXT(Setup!$C$5+16,"dddd") -> Wednesday | B50: =Setup!$C$5+16 -> 46043 | C50: 11.00 - 11.30 | P50: =IFERROR(H50/Setup!$C$6,"") -> 0 | Q50: =IFERROR(H50-P50,"") -> 0
A51: =TEXT(Setup!$C$5+16,"dddd") -> Wednesday | B51: =Setup!$C$5+16 -> 46043 | C51: 11.30 - 12.00 | P51: =IFERROR(H51/Setup!$C$6,"") -> 0 | Q51: =IFERROR(H51-P51,"") -> 0
A52: =TEXT(Setup!$C$5+16,"dddd") -> Wednesday | B52: =Setup!$C$5+16 -> 46043 | C52: 12.00 - 12.30 | P52: =IFERROR(H52/Setup!$C$6,"") -> 0 | Q52: =IFERROR(H52-P52,"") -> 0
A53: =TEXT(Setup!$C$5+16,"dddd") -> Wednesday | B53: =Setup!$C$5+16 -> 46043 | C53: 12.30 - 13.00 | P53: =IFERROR(H53/Setup!$C$6,"") -> 0 | Q53: =IFERROR(H53-P53,"") -> 0
A54: =TEXT(Setup!$C$5+16,"dddd") -> Wednesday | B54: =Setup!$C$5+16 -> 46043 | C54: 13.00 - 13.30 | P54: =IFERROR(H54/Setup!$C$6,"") -> 0 | Q54: =IFERROR(H54-P54,"") -> 0
A55: =TEXT(Setup!$C$5+16,"dddd") -> Wednesday | B55: =Setup!$C$5+16 -> 46043 | C55: 13.30 - 14.00 | P55: =IFERROR(H55/Setup!$C$6,"") -> 0 | Q55: =IFERROR(H55-P55,"") -> 0
A56: =TEXT(Setup!$C$5+16,"dddd") -> Wednesday | B56: =Setup!$C$5+16 -> 46043 | C56: 14.00 - 14.30 | P56: =IFERROR(H56/Setup!$C$6,"") -> 0 | Q56: =IFERROR(H56-P56,"") -> 0
A57: =TEXT(Setup!$C$5+16,"dddd") -> Wednesday | B57: =Setup!$C$5+16 -> 46043 | C57: 14.30 - 15.00 | P57: =IFERROR(H57/Setup!$C$6,"") -> 0 | Q57: =IFERROR(H57-P57,"") -> 0
... A66: =TEXT(Setup!$C$5+16,"dddd") -> Wednesday | B66: =Setup!$C$5+16 -> 46043 | C66: ONLINE | P66: =IFERROR(H66/Setup!$C$6,"") -> 0 | Q66: =IFERROR(H66-P66,"") -> 0
A67: =TEXT(Setup!$C$5+16,"dddd") -> Wednesday | B67: =Setup!$C$5+16 -> 46043 | C67: TOTAL | D67: =SUM(D46:D66) -> 0 | E67: =SUM(E46:E66) -> 0 | F67: =SUM(F46:F66) -> 0 | G67: =SUM(G46:G66) -> 0 | H67: =SUM(H46:H66) -> 0 | I67: =IFERROR(E67/D67,"") | J67: =IFERROR(H67/E67,"") | K67: =SUM(K46:K66) -> 0 | M67: =SUM(M46:M66) -> 0 | N67: =IFERROR(H67-Wk2!H67,"") -> 0 | O67: =IFERROR(D67-Wk2!D67,"") -> 0 | P67: =SUM(P46:P66) -> 0 | Q67: =SUM(Q46:Q66) -> 0 | R67: =IFERROR(INDEX('Last Year'!$C$6:$C$369,MATCH(B67-364,'Last Year'!$B$6:$B$369,0)),"") -> 0 | S67: =IFERROR(H67/R67-1,"")
A68: =TEXT(Setup!$C$5+17,"dddd") -> Thursday | B68: =Setup!$C$5+17 -> 46044 | C68: 9.00 - 9.30 | P68: =IFERROR(H68/Setup!$C$6,"") -> 0 | Q68: =IFERROR(H68-P68,"") -> 0
A69: =TEXT(Setup!$C$5+17,"dddd") -> Thursday | B69: =Setup!$C$5+17 -> 46044 | C69: 9.30 - 10.00 | P69: =IFERROR(H69/Setup!$C$6,"") -> 0 | Q69: =IFERROR(H69-P69,"") -> 0
A70: =TEXT(Setup!$C$5+17,"dddd") -> Thursday | B70: =Setup!$C$5+17 -> 46044 | C70: 10.00 - 10.30 | P70: =IFERROR(H70/Setup!$C$6,"") -> 0 | Q70: =IFERROR(H70-P70,"") -> 0
A71: =TEXT(Setup!$C$5+17,"dddd") -> Thursday | B71: =Setup!$C$5+17 -> 46044 | C71: 10.30 - 11.00 | P71: =IFERROR(H71/Setup!$C$6,"") -> 0 | Q71: =IFERROR(H71-P71,"") -> 0
A72: =TEXT(Setup!$C$5+17,"dddd") -> Thursday | B72: =Setup!$C$5+17 -> 46044 | C72: 11.00 - 11.30 | P72: =IFERROR(H72/Setup!$C$6,"") -> 0 | Q72: =IFERROR(H72-P72,"") -> 0
A73: =TEXT(Setup!$C$5+17,"dddd") -> Thursday | B73: =Setup!$C$5+17 -> 46044 | C73: 11.30 - 12.00 | P73: =IFERROR(H73/Setup!$C$6,"") -> 0 | Q73: =IFERROR(H73-P73,"") -> 0
A74: =TEXT(Setup!$C$5+17,"dddd") -> Thursday | B74: =Setup!$C$5+17 -> 46044 | C74: 12.00 - 12.30 | P74: =IFERROR(H74/Setup!$C$6,"") -> 0 | Q74: =IFERROR(H74-P74,"") -> 0
A75: =TEXT(Setup!$C$5+17,"dddd") -> Thursday | B75: =Setup!$C$5+17 -> 46044 | C75: 12.30 - 13.00 | P75: =IFERROR(H75/Setup!$C$6,"") -> 0 | Q75: =IFERROR(H75-P75,"") -> 0
A76: =TEXT(Setup!$C$5+17,"dddd") -> Thursday | B76: =Setup!$C$5+17 -> 46044 | C76: 13.00 - 13.30 | P76: =IFERROR(H76/Setup!$C$6,"") -> 0 | Q76: =IFERROR(H76-P76,"") -> 0
A77: =TEXT(Setup!$C$5+17,"dddd") -> Thursday | B77: =Setup!$C$5+17 -> 46044 | C77: 13.30 - 14.00 | P77: =IFERROR(H77/Setup!$C$6,"") -> 0 | Q77: =IFERROR(H77-P77,"") -> 0
A78: =TEXT(Setup!$C$5+17,"dddd") -> Thursday | B78: =Setup!$C$5+17 -> 46044 | C78: 14.00 - 14.30 | P78: =IFERROR(H78/Setup!$C$6,"") -> 0 | Q78: =IFERROR(H78-P78,"") -> 0
A79: =TEXT(Setup!$C$5+17,"dddd") -> Thursday | B79: =Setup!$C$5+17 -> 46044 | C79: 14.30 - 15.00 | P79: =IFERROR(H79/Setup!$C$6,"") -> 0 | Q79: =IFERROR(H79-P79,"") -> 0
... A88: =TEXT(Setup!$C$5+17,"dddd") -> Thursday | B88: =Setup!$C$5+17 -> 46044 | C88: ONLINE | P88: =IFERROR(H88/Setup!$C$6,"") -> 0 | Q88: =IFERROR(H88-P88,"") -> 0
A89: =TEXT(Setup!$C$5+17,"dddd") -> Thursday | B89: =Setup!$C$5+17 -> 46044 | C89: TOTAL | D89: =SUM(D68:D88) -> 0 | E89: =SUM(E68:E88) -> 0 | F89: =SUM(F68:F88) -> 0 | G89: =SUM(G68:G88) -> 0 | H89: =SUM(H68:H88) -> 0 | I89: =IFERROR(E89/D89,"") | J89: =IFERROR(H89/E89,"") | K89: =SUM(K68:K88) -> 0 | M89: =SUM(M68:M88) -> 0 | N89: =IFERROR(H89-Wk2!H89,"") -> 0 | O89: =IFERROR(D89-Wk2!D89,"") -> 0 | P89: =SUM(P68:P88) -> 0 | Q89: =SUM(Q68:Q88) -> 0 | R89: =IFERROR(INDEX('Last Year'!$C$6:$C$369,MATCH(B89-364,'Last Year'!$B$6:$B$369,0)),"") -> 0 | S89: =IFERROR(H89/R89-1,"")
A90: =TEXT(Setup!$C$5+18,"dddd") -> Friday | B90: =Setup!$C$5+18 -> 46045 | C90: 9.00 - 9.30 | P90: =IFERROR(H90/Setup!$C$6,"") -> 0 | Q90: =IFERROR(H90-P90,"") -> 0
A91: =TEXT(Setup!$C$5+18,"dddd") -> Friday | B91: =Setup!$C$5+18 -> 46045 | C91: 9.30 - 10.00 | P91: =IFERROR(H91/Setup!$C$6,"") -> 0 | Q91: =IFERROR(H91-P91,"") -> 0
A92: =TEXT(Setup!$C$5+18,"dddd") -> Friday | B92: =Setup!$C$5+18 -> 46045 | C92: 10.00 - 10.30 | P92: =IFERROR(H92/Setup!$C$6,"") -> 0 | Q92: =IFERROR(H92-P92,"") -> 0
A93: =TEXT(Setup!$C$5+18,"dddd") -> Friday | B93: =Setup!$C$5+18 -> 46045 | C93: 10.30 - 11.00 | P93: =IFERROR(H93/Setup!$C$6,"") -> 0 | Q93: =IFERROR(H93-P93,"") -> 0
A94: =TEXT(Setup!$C$5+18,"dddd") -> Friday | B94: =Setup!$C$5+18 -> 46045 | C94: 11.00 - 11.30 | P94: =IFERROR(H94/Setup!$C$6,"") -> 0 | Q94: =IFERROR(H94-P94,"") -> 0
A95: =TEXT(Setup!$C$5+18,"dddd") -> Friday | B95: =Setup!$C$5+18 -> 46045 | C95: 11.30 - 12.00 | P95: =IFERROR(H95/Setup!$C$6,"") -> 0 | Q95: =IFERROR(H95-P95,"") -> 0
A96: =TEXT(Setup!$C$5+18,"dddd") -> Friday | B96: =Setup!$C$5+18 -> 46045 | C96: 12.00 - 12.30 | P96: =IFERROR(H96/Setup!$C$6,"") -> 0 | Q96: =IFERROR(H96-P96,"") -> 0
A97: =TEXT(Setup!$C$5+18,"dddd") -> Friday | B97: =Setup!$C$5+18 -> 46045 | C97: 12.30 - 13.00 | P97: =IFERROR(H97/Setup!$C$6,"") -> 0 | Q97: =IFERROR(H97-P97,"") -> 0
A98: =TEXT(Setup!$C$5+18,"dddd") -> Friday | B98: =Setup!$C$5+18 -> 46045 | C98: 13.00 - 13.30 | P98: =IFERROR(H98/Setup!$C$6,"") -> 0 | Q98: =IFERROR(H98-P98,"") -> 0
A99: =TEXT(Setup!$C$5+18,"dddd") -> Friday | B99: =Setup!$C$5+18 -> 46045 | C99: 13.30 - 14.00 | P99: =IFERROR(H99/Setup!$C$6,"") -> 0 | Q99: =IFERROR(H99-P99,"") -> 0
A100: =TEXT(Setup!$C$5+18,"dddd") -> Friday | B100: =Setup!$C$5+18 -> 46045 | C100: 14.00 - 14.30 | P100: =IFERROR(H100/Setup!$C$6,"") -> 0 | Q100: =IFERROR(H100-P100,"") -> 0
A101: =TEXT(Setup!$C$5+18,"dddd") -> Friday | B101: =Setup!$C$5+18 -> 46045 | C101: 14.30 - 15.00 | P101: =IFERROR(H101/Setup!$C$6,"") -> 0 | Q101: =IFERROR(H101-P101,"") -> 0
... A110: =TEXT(Setup!$C$5+18,"dddd") -> Friday | B110: =Setup!$C$5+18 -> 46045 | C110: ONLINE | P110: =IFERROR(H110/Setup!$C$6,"") -> 0 | Q110: =IFERROR(H110-P110,"") -> 0
A111: =TEXT(Setup!$C$5+18,"dddd") -> Friday | B111: =Setup!$C$5+18 -> 46045 | C111: TOTAL | D111: =SUM(D90:D110) -> 0 | E111: =SUM(E90:E110) -> 0 | F111: =SUM(F90:F110) -> 0 | G111: =SUM(G90:G110) -> 0 | H111: =SUM(H90:H110) -> 0 | I111: =IFERROR(E111/D111,"") | J111: =IFERROR(H111/E111,"") | K111: =SUM(K90:K110) -> 0 | M111: =SUM(M90:M110) -> 0 | N111: =IFERROR(H111-Wk2!H111,"") -> 0 | O111: =IFERROR(D111-Wk2!D111,"") -> 0 | P111: =SUM(P90:P110) -> 0 | Q111: =SUM(Q90:Q110) -> 0 | R111: =IFERROR(INDEX('Last Year'!$C$6:$C$369,MATCH(B111-364,'Last Year'!$B$6:$B$369,0)),"") -> 0 | S111: =IFERROR(H111/R111-1,"")
A112: =TEXT(Setup!$C$5+19,"dddd") -> Saturday | B112: =Setup!$C$5+19 -> 46046 | C112: 9.00 - 9.30 | P112: =IFERROR(H112/Setup!$C$6,"") -> 0 | Q112: =IFERROR(H112-P112,"") -> 0
A113: =TEXT(Setup!$C$5+19,"dddd") -> Saturday | B113: =Setup!$C$5+19 -> 46046 | C113: 9.30 - 10.00 | P113: =IFERROR(H113/Setup!$C$6,"") -> 0 | Q113: =IFERROR(H113-P113,"") -> 0
A114: =TEXT(Setup!$C$5+19,"dddd") -> Saturday | B114: =Setup!$C$5+19 -> 46046 | C114: 10.00 - 10.30 | P114: =IFERROR(H114/Setup!$C$6,"") -> 0 | Q114: =IFERROR(H114-P114,"") -> 0
A115: =TEXT(Setup!$C$5+19,"dddd") -> Saturday | B115: =Setup!$C$5+19 -> 46046 | C115: 10.30 - 11.00 | P115: =IFERROR(H115/Setup!$C$6,"") -> 0 | Q115: =IFERROR(H115-P115,"") -> 0
A116: =TEXT(Setup!$C$5+19,"dddd") -> Saturday | B116: =Setup!$C$5+19 -> 46046 | C116: 11.00 - 11.30 | P116: =IFERROR(H116/Setup!$C$6,"") -> 0 | Q116: =IFERROR(H116-P116,"") -> 0
A117: =TEXT(Setup!$C$5+19,"dddd") -> Saturday | B117: =Setup!$C$5+19 -> 46046 | C117: 11.30 - 12.00 | P117: =IFERROR(H117/Setup!$C$6,"") -> 0 | Q117: =IFERROR(H117-P117,"") -> 0
A118: =TEXT(Setup!$C$5+19,"dddd") -> Saturday | B118: =Setup!$C$5+19 -> 46046 | C118: 12.00 - 12.30 | P118: =IFERROR(H118/Setup!$C$6,"") -> 0 | Q118: =IFERROR(H118-P118,"") -> 0
A119: =TEXT(Setup!$C$5+19,"dddd") -> Saturday | B119: =Setup!$C$5+19 -> 46046 | C119: 12.30 - 13.00 | P119: =IFERROR(H119/Setup!$C$6,"") -> 0 | Q119: =IFERROR(H119-P119,"") -> 0
A120: =TEXT(Setup!$C$5+19,"dddd") -> Saturday | B120: =Setup!$C$5+19 -> 46046 | C120: 13.00 - 13.30 | P120: =IFERROR(H120/Setup!$C$6,"") -> 0 | Q120: =IFERROR(H120-P120,"") -> 0
A121: =TEXT(Setup!$C$5+19,"dddd") -> Saturday | B121: =Setup!$C$5+19 -> 46046 | C121: 13.30 - 14.00 | P121: =IFERROR(H121/Setup!$C$6,"") -> 0 | Q121: =IFERROR(H121-P121,"") -> 0
A122: =TEXT(Setup!$C$5+19,"dddd") -> Saturday | B122: =Setup!$C$5+19 -> 46046 | C122: 14.00 - 14.30 | P122: =IFERROR(H122/Setup!$C$6,"") -> 0 | Q122: =IFERROR(H122-P122,"") -> 0
A123: =TEXT(Setup!$C$5+19,"dddd") -> Saturday | B123: =Setup!$C$5+19 -> 46046 | C123: 14.30 - 15.00 | P123: =IFERROR(H123/Setup!$C$6,"") -> 0 | Q123: =IFERROR(H123-P123,"") -> 0
... A132: =TEXT(Setup!$C$5+19,"dddd") -> Saturday | B132: =Setup!$C$5+19 -> 46046 | C132: ONLINE | P132: =IFERROR(H132/Setup!$C$6,"") -> 0 | Q132: =IFERROR(H132-P132,"") -> 0
A133: =TEXT(Setup!$C$5+19,"dddd") -> Saturday | B133: =Setup!$C$5+19 -> 46046 | C133: TOTAL | D133: =SUM(D112:D132) -> 0 | E133: =SUM(E112:E132) -> 0 | F133: =SUM(F112:F132) -> 0 | G133: =SUM(G112:G132) -> 0 | H133: =SUM(H112:H132) -> 0 | I133: =IFERROR(E133/D133,"") | J133: =IFERROR(H133/E133,"") | K133: =SUM(K112:K132) -> 0 | M133: =SUM(M112:M132) -> 0 | N133: =IFERROR(H133-Wk2!H133,"") -> 0 | O133: =IFERROR(D133-Wk2!D133,"") -> 0 | P133: =SUM(P112:P132) -> 0 | Q133: =SUM(Q112:Q132) -> 0 | R133: =IFERROR(INDEX('Last Year'!$C$6:$C$369,MATCH(B133-364,'Last Year'!$B$6:$B$369,0)),"") -> 0 | S133: =IFERROR(H133/R133-1,"")
A134: =TEXT(Setup!$C$5+20,"dddd") -> Sunday | B134: =Setup!$C$5+20 -> 46047 | C134: 9.00 - 9.30 | P134: =IFERROR(H134/Setup!$C$6,"") -> 0 | Q134: =IFERROR(H134-P134,"") -> 0
A135: =TEXT(Setup!$C$5+20,"dddd") -> Sunday | B135: =Setup!$C$5+20 -> 46047 | C135: 9.30 - 10.00 | P135: =IFERROR(H135/Setup!$C$6,"") -> 0 | Q135: =IFERROR(H135-P135,"") -> 0
A136: =TEXT(Setup!$C$5+20,"dddd") -> Sunday | B136: =Setup!$C$5+20 -> 46047 | C136: 10.00 - 10.30 | P136: =IFERROR(H136/Setup!$C$6,"") -> 0 | Q136: =IFERROR(H136-P136,"") -> 0
A137: =TEXT(Setup!$C$5+20,"dddd") -> Sunday | B137: =Setup!$C$5+20 -> 46047 | C137: 10.30 - 11.00 | P137: =IFERROR(H137/Setup!$C$6,"") -> 0 | Q137: =IFERROR(H137-P137,"") -> 0
A138: =TEXT(Setup!$C$5+20,"dddd") -> Sunday | B138: =Setup!$C$5+20 -> 46047 | C138: 11.00 - 11.30 | P138: =IFERROR(H138/Setup!$C$6,"") -> 0 | Q138: =IFERROR(H138-P138,"") -> 0
A139: =TEXT(Setup!$C$5+20,"dddd") -> Sunday | B139: =Setup!$C$5+20 -> 46047 | C139: 11.30 - 12.00 | P139: =IFERROR(H139/Setup!$C$6,"") -> 0 | Q139: =IFERROR(H139-P139,"") -> 0
A140: =TEXT(Setup!$C$5+20,"dddd") -> Sunday | B140: =Setup!$C$5+20 -> 46047 | C140: 12.00 - 12.30 | P140: =IFERROR(H140/Setup!$C$6,"") -> 0 | Q140: =IFERROR(H140-P140,"") -> 0
A141: =TEXT(Setup!$C$5+20,"dddd") -> Sunday | B141: =Setup!$C$5+20 -> 46047 | C141: 12.30 - 13.00 | P141: =IFERROR(H141/Setup!$C$6,"") -> 0 | Q141: =IFERROR(H141-P141,"") -> 0
A142: =TEXT(Setup!$C$5+20,"dddd") -> Sunday | B142: =Setup!$C$5+20 -> 46047 | C142: 13.00 - 13.30 | P142: =IFERROR(H142/Setup!$C$6,"") -> 0 | Q142: =IFERROR(H142-P142,"") -> 0
A143: =TEXT(Setup!$C$5+20,"dddd") -> Sunday | B143: =Setup!$C$5+20 -> 46047 | C143: 13.30 - 14.00 | P143: =IFERROR(H143/Setup!$C$6,"") -> 0 | Q143: =IFERROR(H143-P143,"") -> 0
A144: =TEXT(Setup!$C$5+20,"dddd") -> Sunday | B144: =Setup!$C$5+20 -> 46047 | C144: 14.00 - 14.30 | P144: =IFERROR(H144/Setup!$C$6,"") -> 0 | Q144: =IFERROR(H144-P144,"") -> 0
A145: =TEXT(Setup!$C$5+20,"dddd") -> Sunday | B145: =Setup!$C$5+20 -> 46047 | C145: 14.30 - 15.00 | P145: =IFERROR(H145/Setup!$C$6,"") -> 0 | Q145: =IFERROR(H145-P145,"") -> 0
... A154: =TEXT(Setup!$C$5+20,"dddd") -> Sunday | B154: =Setup!$C$5+20 -> 46047 | C154: ONLINE | P154: =IFERROR(H154/Setup!$C$6,"") -> 0 | Q154: =IFERROR(H154-P154,"") -> 0
A155: =TEXT(Setup!$C$5+20,"dddd") -> Sunday | B155: =Setup!$C$5+20 -> 46047 | C155: TOTAL | D155: =SUM(D134:D154) -> 0 | E155: =SUM(E134:E154) -> 0 | F155: =SUM(F134:F154) -> 0 | G155: =SUM(G134:G154) -> 0 | H155: =SUM(H134:H154) -> 0 | I155: =IFERROR(E155/D155,"") | J155: =IFERROR(H155/E155,"") | K155: =SUM(K134:K154) -> 0 | M155: =SUM(M134:M154) -> 0 | N155: =IFERROR(H155-Wk2!H155,"") -> 0 | O155: =IFERROR(D155-Wk2!D155,"") -> 0 | P155: =SUM(P134:P154) -> 0 | Q155: =SUM(Q134:Q154) -> 0 | R155: =IFERROR(INDEX('Last Year'!$C$6:$C$369,MATCH(B155-364,'Last Year'!$B$6:$B$369,0)),"") -> 0 | S155: =IFERROR(H155/R155-1,"")
C156: FULL WEEK | D156: =D23+D45+D67+D89+D111+D133+D155 -> 0 | E156: =E23+E45+E67+E89+E111+E133+E155 -> 0 | F156: =F23+F45+F67+F89+F111+F133+F155 -> 0 | G156: =G23+G45+G67+G89+G111+G133+G155 -> 0 | H156: =H23+H45+H67+H89+H111+H133+H155 -> 0 | I156: =IFERROR(E156/D156,"") | J156: =IFERROR(H156/E156,"") | K156: =K23+K45+K67+K89+K111+K133+K155 -> 0 | M156: =M23+M45+M67+M89+M111+M133+M155 -> 0 | P156: =P23+P45+P67+P89+P111+P133+P155 -> 0 | Q156: =Q23+Q45+Q67+Q89+Q111+Q133+Q155 -> 0 | R156: =R23+R45+R67+R89+R111+R133+R155 -> 0 | S156: =IFERROR(H156/R156-1,"")
...

Sheet Wk4
A1: Day | B1: Date | C1: Time | D1: Customers In | E1: Sales | F1: Vouchers Used | G1: Walk In/Out | H1: Sale Amount | I1: Conversion | J1: Avg Sale | K1: Tracked Category | L1: Notes | M1: Cash | N1: vs Last Wk € | O1: vs Last Wk Cust | P1: Est. Cost | Q1: Est. Profit | R1: Last Year Day | S1: vs Last Year
A2: =TEXT(Setup!$C$5+21,"dddd") -> Monday | B2: =Setup!$C$5+21 -> 46048 | C2: 9.00 - 9.30 | P2: =IFERROR(H2/Setup!$C$6,"") -> 0 | Q2: =IFERROR(H2-P2,"") -> 0
A3: =TEXT(Setup!$C$5+21,"dddd") -> Monday | B3: =Setup!$C$5+21 -> 46048 | C3: 9.30 - 10.00 | P3: =IFERROR(H3/Setup!$C$6,"") -> 0 | Q3: =IFERROR(H3-P3,"") -> 0
A4: =TEXT(Setup!$C$5+21,"dddd") -> Monday | B4: =Setup!$C$5+21 -> 46048 | C4: 10.00 - 10.30 | P4: =IFERROR(H4/Setup!$C$6,"") -> 0 | Q4: =IFERROR(H4-P4,"") -> 0
A5: =TEXT(Setup!$C$5+21,"dddd") -> Monday | B5: =Setup!$C$5+21 -> 46048 | C5: 10.30 - 11.00 | P5: =IFERROR(H5/Setup!$C$6,"") -> 0 | Q5: =IFERROR(H5-P5,"") -> 0
A6: =TEXT(Setup!$C$5+21,"dddd") -> Monday | B6: =Setup!$C$5+21 -> 46048 | C6: 11.00 - 11.30 | P6: =IFERROR(H6/Setup!$C$6,"") -> 0 | Q6: =IFERROR(H6-P6,"") -> 0
A7: =TEXT(Setup!$C$5+21,"dddd") -> Monday | B7: =Setup!$C$5+21 -> 46048 | C7: 11.30 - 12.00 | P7: =IFERROR(H7/Setup!$C$6,"") -> 0 | Q7: =IFERROR(H7-P7,"") -> 0
A8: =TEXT(Setup!$C$5+21,"dddd") -> Monday | B8: =Setup!$C$5+21 -> 46048 | C8: 12.00 - 12.30 | P8: =IFERROR(H8/Setup!$C$6,"") -> 0 | Q8: =IFERROR(H8-P8,"") -> 0
A9: =TEXT(Setup!$C$5+21,"dddd") -> Monday | B9: =Setup!$C$5+21 -> 46048 | C9: 12.30 - 13.00 | P9: =IFERROR(H9/Setup!$C$6,"") -> 0 | Q9: =IFERROR(H9-P9,"") -> 0
A10: =TEXT(Setup!$C$5+21,"dddd") -> Monday | B10: =Setup!$C$5+21 -> 46048 | C10: 13.00 - 13.30 | P10: =IFERROR(H10/Setup!$C$6,"") -> 0 | Q10: =IFERROR(H10-P10,"") -> 0
A11: =TEXT(Setup!$C$5+21,"dddd") -> Monday | B11: =Setup!$C$5+21 -> 46048 | C11: 13.30 - 14.00 | P11: =IFERROR(H11/Setup!$C$6,"") -> 0 | Q11: =IFERROR(H11-P11,"") -> 0
A12: =TEXT(Setup!$C$5+21,"dddd") -> Monday | B12: =Setup!$C$5+21 -> 46048 | C12: 14.00 - 14.30 | P12: =IFERROR(H12/Setup!$C$6,"") -> 0 | Q12: =IFERROR(H12-P12,"") -> 0
A13: =TEXT(Setup!$C$5+21,"dddd") -> Monday | B13: =Setup!$C$5+21 -> 46048 | C13: 14.30 - 15.00 | P13: =IFERROR(H13/Setup!$C$6,"") -> 0 | Q13: =IFERROR(H13-P13,"") -> 0
... A22: =TEXT(Setup!$C$5+21,"dddd") -> Monday | B22: =Setup!$C$5+21 -> 46048 | C22: ONLINE | P22: =IFERROR(H22/Setup!$C$6,"") -> 0 | Q22: =IFERROR(H22-P22,"") -> 0
A23: =TEXT(Setup!$C$5+21,"dddd") -> Monday | B23: =Setup!$C$5+21 -> 46048 | C23: TOTAL | D23: =SUM(D2:D22) -> 0 | E23: =SUM(E2:E22) -> 0 | F23: =SUM(F2:F22) -> 0 | G23: =SUM(G2:G22) -> 0 | H23: =SUM(H2:H22) -> 0 | I23: =IFERROR(E23/D23,"") | J23: =IFERROR(H23/E23,"") | K23: =SUM(K2:K22) -> 0 | M23: =SUM(M2:M22) -> 0 | N23: =IFERROR(H23-Wk3!H23,"") -> 0 | O23: =IFERROR(D23-Wk3!D23,"") -> 0 | P23: =SUM(P2:P22) -> 0 | Q23: =SUM(Q2:Q22) -> 0 | R23: =IFERROR(INDEX('Last Year'!$C$6:$C$369,MATCH(B23-364,'Last Year'!$B$6:$B$369,0)),"") -> 0 | S23: =IFERROR(H23/R23-1,"")
A24: =TEXT(Setup!$C$5+22,"dddd") -> Tuesday | B24: =Setup!$C$5+22 -> 46049 | C24: 9.00 - 9.30 | P24: =IFERROR(H24/Setup!$C$6,"") -> 0 | Q24: =IFERROR(H24-P24,"") -> 0
A25: =TEXT(Setup!$C$5+22,"dddd") -> Tuesday | B25: =Setup!$C$5+22 -> 46049 | C25: 9.30 - 10.00 | P25: =IFERROR(H25/Setup!$C$6,"") -> 0 | Q25: =IFERROR(H25-P25,"") -> 0
A26: =TEXT(Setup!$C$5+22,"dddd") -> Tuesday | B26: =Setup!$C$5+22 -> 46049 | C26: 10.00 - 10.30 | P26: =IFERROR(H26/Setup!$C$6,"") -> 0 | Q26: =IFERROR(H26-P26,"") -> 0
A27: =TEXT(Setup!$C$5+22,"dddd") -> Tuesday | B27: =Setup!$C$5+22 -> 46049 | C27: 10.30 - 11.00 | P27: =IFERROR(H27/Setup!$C$6,"") -> 0 | Q27: =IFERROR(H27-P27,"") -> 0
A28: =TEXT(Setup!$C$5+22,"dddd") -> Tuesday | B28: =Setup!$C$5+22 -> 46049 | C28: 11.00 - 11.30 | P28: =IFERROR(H28/Setup!$C$6,"") -> 0 | Q28: =IFERROR(H28-P28,"") -> 0
A29: =TEXT(Setup!$C$5+22,"dddd") -> Tuesday | B29: =Setup!$C$5+22 -> 46049 | C29: 11.30 - 12.00 | P29: =IFERROR(H29/Setup!$C$6,"") -> 0 | Q29: =IFERROR(H29-P29,"") -> 0
A30: =TEXT(Setup!$C$5+22,"dddd") -> Tuesday | B30: =Setup!$C$5+22 -> 46049 | C30: 12.00 - 12.30 | P30: =IFERROR(H30/Setup!$C$6,"") -> 0 | Q30: =IFERROR(H30-P30,"") -> 0
A31: =TEXT(Setup!$C$5+22,"dddd") -> Tuesday | B31: =Setup!$C$5+22 -> 46049 | C31: 12.30 - 13.00 | P31: =IFERROR(H31/Setup!$C$6,"") -> 0 | Q31: =IFERROR(H31-P31,"") -> 0
A32: =TEXT(Setup!$C$5+22,"dddd") -> Tuesday | B32: =Setup!$C$5+22 -> 46049 | C32: 13.00 - 13.30 | P32: =IFERROR(H32/Setup!$C$6,"") -> 0 | Q32: =IFERROR(H32-P32,"") -> 0
A33: =TEXT(Setup!$C$5+22,"dddd") -> Tuesday | B33: =Setup!$C$5+22 -> 46049 | C33: 13.30 - 14.00 | P33: =IFERROR(H33/Setup!$C$6,"") -> 0 | Q33: =IFERROR(H33-P33,"") -> 0
A34: =TEXT(Setup!$C$5+22,"dddd") -> Tuesday | B34: =Setup!$C$5+22 -> 46049 | C34: 14.00 - 14.30 | P34: =IFERROR(H34/Setup!$C$6,"") -> 0 | Q34: =IFERROR(H34-P34,"") -> 0
A35: =TEXT(Setup!$C$5+22,"dddd") -> Tuesday | B35: =Setup!$C$5+22 -> 46049 | C35: 14.30 - 15.00 | P35: =IFERROR(H35/Setup!$C$6,"") -> 0 | Q35: =IFERROR(H35-P35,"") -> 0
... A44: =TEXT(Setup!$C$5+22,"dddd") -> Tuesday | B44: =Setup!$C$5+22 -> 46049 | C44: ONLINE | P44: =IFERROR(H44/Setup!$C$6,"") -> 0 | Q44: =IFERROR(H44-P44,"") -> 0
A45: =TEXT(Setup!$C$5+22,"dddd") -> Tuesday | B45: =Setup!$C$5+22 -> 46049 | C45: TOTAL | D45: =SUM(D24:D44) -> 0 | E45: =SUM(E24:E44) -> 0 | F45: =SUM(F24:F44) -> 0 | G45: =SUM(G24:G44) -> 0 | H45: =SUM(H24:H44) -> 0 | I45: =IFERROR(E45/D45,"") | J45: =IFERROR(H45/E45,"") | K45: =SUM(K24:K44) -> 0 | M45: =SUM(M24:M44) -> 0 | N45: =IFERROR(H45-Wk3!H45,"") -> 0 | O45: =IFERROR(D45-Wk3!D45,"") -> 0 | P45: =SUM(P24:P44) -> 0 | Q45: =SUM(Q24:Q44) -> 0 | R45: =IFERROR(INDEX('Last Year'!$C$6:$C$369,MATCH(B45-364,'Last Year'!$B$6:$B$369,0)),"") -> 0 | S45: =IFERROR(H45/R45-1,"")
A46: =TEXT(Setup!$C$5+23,"dddd") -> Wednesday | B46: =Setup!$C$5+23 -> 46050 | C46: 9.00 - 9.30 | P46: =IFERROR(H46/Setup!$C$6,"") -> 0 | Q46: =IFERROR(H46-P46,"") -> 0
A47: =TEXT(Setup!$C$5+23,"dddd") -> Wednesday | B47: =Setup!$C$5+23 -> 46050 | C47: 9.30 - 10.00 | P47: =IFERROR(H47/Setup!$C$6,"") -> 0 | Q47: =IFERROR(H47-P47,"") -> 0
A48: =TEXT(Setup!$C$5+23,"dddd") -> Wednesday | B48: =Setup!$C$5+23 -> 46050 | C48: 10.00 - 10.30 | P48: =IFERROR(H48/Setup!$C$6,"") -> 0 | Q48: =IFERROR(H48-P48,"") -> 0
A49: =TEXT(Setup!$C$5+23,"dddd") -> Wednesday | B49: =Setup!$C$5+23 -> 46050 | C49: 10.30 - 11.00 | P49: =IFERROR(H49/Setup!$C$6,"") -> 0 | Q49: =IFERROR(H49-P49,"") -> 0
A50: =TEXT(Setup!$C$5+23,"dddd") -> Wednesday | B50: =Setup!$C$5+23 -> 46050 | C50: 11.00 - 11.30 | P50: =IFERROR(H50/Setup!$C$6,"") -> 0 | Q50: =IFERROR(H50-P50,"") -> 0
A51: =TEXT(Setup!$C$5+23,"dddd") -> Wednesday | B51: =Setup!$C$5+23 -> 46050 | C51: 11.30 - 12.00 | P51: =IFERROR(H51/Setup!$C$6,"") -> 0 | Q51: =IFERROR(H51-P51,"") -> 0
A52: =TEXT(Setup!$C$5+23,"dddd") -> Wednesday | B52: =Setup!$C$5+23 -> 46050 | C52: 12.00 - 12.30 | P52: =IFERROR(H52/Setup!$C$6,"") -> 0 | Q52: =IFERROR(H52-P52,"") -> 0
A53: =TEXT(Setup!$C$5+23,"dddd") -> Wednesday | B53: =Setup!$C$5+23 -> 46050 | C53: 12.30 - 13.00 | P53: =IFERROR(H53/Setup!$C$6,"") -> 0 | Q53: =IFERROR(H53-P53,"") -> 0
A54: =TEXT(Setup!$C$5+23,"dddd") -> Wednesday | B54: =Setup!$C$5+23 -> 46050 | C54: 13.00 - 13.30 | P54: =IFERROR(H54/Setup!$C$6,"") -> 0 | Q54: =IFERROR(H54-P54,"") -> 0
A55: =TEXT(Setup!$C$5+23,"dddd") -> Wednesday | B55: =Setup!$C$5+23 -> 46050 | C55: 13.30 - 14.00 | P55: =IFERROR(H55/Setup!$C$6,"") -> 0 | Q55: =IFERROR(H55-P55,"") -> 0
A56: =TEXT(Setup!$C$5+23,"dddd") -> Wednesday | B56: =Setup!$C$5+23 -> 46050 | C56: 14.00 - 14.30 | P56: =IFERROR(H56/Setup!$C$6,"") -> 0 | Q56: =IFERROR(H56-P56,"") -> 0
A57: =TEXT(Setup!$C$5+23,"dddd") -> Wednesday | B57: =Setup!$C$5+23 -> 46050 | C57: 14.30 - 15.00 | P57: =IFERROR(H57/Setup!$C$6,"") -> 0 | Q57: =IFERROR(H57-P57,"") -> 0
... A66: =TEXT(Setup!$C$5+23,"dddd") -> Wednesday | B66: =Setup!$C$5+23 -> 46050 | C66: ONLINE | P66: =IFERROR(H66/Setup!$C$6,"") -> 0 | Q66: =IFERROR(H66-P66,"") -> 0
A67: =TEXT(Setup!$C$5+23,"dddd") -> Wednesday | B67: =Setup!$C$5+23 -> 46050 | C67: TOTAL | D67: =SUM(D46:D66) -> 0 | E67: =SUM(E46:E66) -> 0 | F67: =SUM(F46:F66) -> 0 | G67: =SUM(G46:G66) -> 0 | H67: =SUM(H46:H66) -> 0 | I67: =IFERROR(E67/D67,"") | J67: =IFERROR(H67/E67,"") | K67: =SUM(K46:K66) -> 0 | M67: =SUM(M46:M66) -> 0 | N67: =IFERROR(H67-Wk3!H67,"") -> 0 | O67: =IFERROR(D67-Wk3!D67,"") -> 0 | P67: =SUM(P46:P66) -> 0 | Q67: =SUM(Q46:Q66) -> 0 | R67: =IFERROR(INDEX('Last Year'!$C$6:$C$369,MATCH(B67-364,'Last Year'!$B$6:$B$369,0)),"") -> 0 | S67: =IFERROR(H67/R67-1,"")
A68: =TEXT(Setup!$C$5+24,"dddd") -> Thursday | B68: =Setup!$C$5+24 -> 46051 | C68: 9.00 - 9.30 | P68: =IFERROR(H68/Setup!$C$6,"") -> 0 | Q68: =IFERROR(H68-P68,"") -> 0
A69: =TEXT(Setup!$C$5+24,"dddd") -> Thursday | B69: =Setup!$C$5+24 -> 46051 | C69: 9.30 - 10.00 | P69: =IFERROR(H69/Setup!$C$6,"") -> 0 | Q69: =IFERROR(H69-P69,"") -> 0
A70: =TEXT(Setup!$C$5+24,"dddd") -> Thursday | B70: =Setup!$C$5+24 -> 46051 | C70: 10.00 - 10.30 | P70: =IFERROR(H70/Setup!$C$6,"") -> 0 | Q70: =IFERROR(H70-P70,"") -> 0
A71: =TEXT(Setup!$C$5+24,"dddd") -> Thursday | B71: =Setup!$C$5+24 -> 46051 | C71: 10.30 - 11.00 | P71: =IFERROR(H71/Setup!$C$6,"") -> 0 | Q71: =IFERROR(H71-P71,"") -> 0
A72: =TEXT(Setup!$C$5+24,"dddd") -> Thursday | B72: =Setup!$C$5+24 -> 46051 | C72: 11.00 - 11.30 | P72: =IFERROR(H72/Setup!$C$6,"") -> 0 | Q72: =IFERROR(H72-P72,"") -> 0
A73: =TEXT(Setup!$C$5+24,"dddd") -> Thursday | B73: =Setup!$C$5+24 -> 46051 | C73: 11.30 - 12.00 | P73: =IFERROR(H73/Setup!$C$6,"") -> 0 | Q73: =IFERROR(H73-P73,"") -> 0
A74: =TEXT(Setup!$C$5+24,"dddd") -> Thursday | B74: =Setup!$C$5+24 -> 46051 | C74: 12.00 - 12.30 | P74: =IFERROR(H74/Setup!$C$6,"") -> 0 | Q74: =IFERROR(H74-P74,"") -> 0
A75: =TEXT(Setup!$C$5+24,"dddd") -> Thursday | B75: =Setup!$C$5+24 -> 46051 | C75: 12.30 - 13.00 | P75: =IFERROR(H75/Setup!$C$6,"") -> 0 | Q75: =IFERROR(H75-P75,"") -> 0
A76: =TEXT(Setup!$C$5+24,"dddd") -> Thursday | B76: =Setup!$C$5+24 -> 46051 | C76: 13.00 - 13.30 | P76: =IFERROR(H76/Setup!$C$6,"") -> 0 | Q76: =IFERROR(H76-P76,"") -> 0
A77: =TEXT(Setup!$C$5+24,"dddd") -> Thursday | B77: =Setup!$C$5+24 -> 46051 | C77: 13.30 - 14.00 | P77: =IFERROR(H77/Setup!$C$6,"") -> 0 | Q77: =IFERROR(H77-P77,"") -> 0
A78: =TEXT(Setup!$C$5+24,"dddd") -> Thursday | B78: =Setup!$C$5+24 -> 46051 | C78: 14.00 - 14.30 | P78: =IFERROR(H78/Setup!$C$6,"") -> 0 | Q78: =IFERROR(H78-P78,"") -> 0
A79: =TEXT(Setup!$C$5+24,"dddd") -> Thursday | B79: =Setup!$C$5+24 -> 46051 | C79: 14.30 - 15.00 | P79: =IFERROR(H79/Setup!$C$6,"") -> 0 | Q79: =IFERROR(H79-P79,"") -> 0
... A88: =TEXT(Setup!$C$5+24,"dddd") -> Thursday | B88: =Setup!$C$5+24 -> 46051 | C88: ONLINE | P88: =IFERROR(H88/Setup!$C$6,"") -> 0 | Q88: =IFERROR(H88-P88,"") -> 0
A89: =TEXT(Setup!$C$5+24,"dddd") -> Thursday | B89: =Setup!$C$5+24 -> 46051 | C89: TOTAL | D89: =SUM(D68:D88) -> 0 | E89: =SUM(E68:E88) -> 0 | F89: =SUM(F68:F88) -> 0 | G89: =SUM(G68:G88) -> 0 | H89: =SUM(H68:H88) -> 0 | I89: =IFERROR(E89/D89,"") | J89: =IFERROR(H89/E89,"") | K89: =SUM(K68:K88) -> 0 | M89: =SUM(M68:M88) -> 0 | N89: =IFERROR(H89-Wk3!H89,"") -> 0 | O89: =IFERROR(D89-Wk3!D89,"") -> 0 | P89: =SUM(P68:P88) -> 0 | Q89: =SUM(Q68:Q88) -> 0 | R89: =IFERROR(INDEX('Last Year'!$C$6:$C$369,MATCH(B89-364,'Last Year'!$B$6:$B$369,0)),"") -> 0 | S89: =IFERROR(H89/R89-1,"")
A90: =TEXT(Setup!$C$5+25,"dddd") -> Friday | B90: =Setup!$C$5+25 -> 46052 | C90: 9.00 - 9.30 | P90: =IFERROR(H90/Setup!$C$6,"") -> 0 | Q90: =IFERROR(H90-P90,"") -> 0
A91: =TEXT(Setup!$C$5+25,"dddd") -> Friday | B91: =Setup!$C$5+25 -> 46052 | C91: 9.30 - 10.00 | P91: =IFERROR(H91/Setup!$C$6,"") -> 0 | Q91: =IFERROR(H91-P91,"") -> 0
A92: =TEXT(Setup!$C$5+25,"dddd") -> Friday | B92: =Setup!$C$5+25 -> 46052 | C92: 10.00 - 10.30 | P92: =IFERROR(H92/Setup!$C$6,"") -> 0 | Q92: =IFERROR(H92-P92,"") -> 0
A93: =TEXT(Setup!$C$5+25,"dddd") -> Friday | B93: =Setup!$C$5+25 -> 46052 | C93: 10.30 - 11.00 | P93: =IFERROR(H93/Setup!$C$6,"") -> 0 | Q93: =IFERROR(H93-P93,"") -> 0
A94: =TEXT(Setup!$C$5+25,"dddd") -> Friday | B94: =Setup!$C$5+25 -> 46052 | C94: 11.00 - 11.30 | P94: =IFERROR(H94/Setup!$C$6,"") -> 0 | Q94: =IFERROR(H94-P94,"") -> 0
A95: =TEXT(Setup!$C$5+25,"dddd") -> Friday | B95: =Setup!$C$5+25 -> 46052 | C95: 11.30 - 12.00 | P95: =IFERROR(H95/Setup!$C$6,"") -> 0 | Q95: =IFERROR(H95-P95,"") -> 0
A96: =TEXT(Setup!$C$5+25,"dddd") -> Friday | B96: =Setup!$C$5+25 -> 46052 | C96: 12.00 - 12.30 | P96: =IFERROR(H96/Setup!$C$6,"") -> 0 | Q96: =IFERROR(H96-P96,"") -> 0
A97: =TEXT(Setup!$C$5+25,"dddd") -> Friday | B97: =Setup!$C$5+25 -> 46052 | C97: 12.30 - 13.00 | P97: =IFERROR(H97/Setup!$C$6,"") -> 0 | Q97: =IFERROR(H97-P97,"") -> 0
A98: =TEXT(Setup!$C$5+25,"dddd") -> Friday | B98: =Setup!$C$5+25 -> 46052 | C98: 13.00 - 13.30 | P98: =IFERROR(H98/Setup!$C$6,"") -> 0 | Q98: =IFERROR(H98-P98,"") -> 0
A99: =TEXT(Setup!$C$5+25,"dddd") -> Friday | B99: =Setup!$C$5+25 -> 46052 | C99: 13.30 - 14.00 | P99: =IFERROR(H99/Setup!$C$6,"") -> 0 | Q99: =IFERROR(H99-P99,"") -> 0
A100: =TEXT(Setup!$C$5+25,"dddd") -> Friday | B100: =Setup!$C$5+25 -> 46052 | C100: 14.00 - 14.30 | P100: =IFERROR(H100/Setup!$C$6,"") -> 0 | Q100: =IFERROR(H100-P100,"") -> 0
A101: =TEXT(Setup!$C$5+25,"dddd") -> Friday | B101: =Setup!$C$5+25 -> 46052 | C101: 14.30 - 15.00 | P101: =IFERROR(H101/Setup!$C$6,"") -> 0 | Q101: =IFERROR(H101-P101,"") -> 0
... A110: =TEXT(Setup!$C$5+25,"dddd") -> Friday | B110: =Setup!$C$5+25 -> 46052 | C110: ONLINE | P110: =IFERROR(H110/Setup!$C$6,"") -> 0 | Q110: =IFERROR(H110-P110,"") -> 0
A111: =TEXT(Setup!$C$5+25,"dddd") -> Friday | B111: =Setup!$C$5+25 -> 46052 | C111: TOTAL | D111: =SUM(D90:D110) -> 0 | E111: =SUM(E90:E110) -> 0 | F111: =SUM(F90:F110) -> 0 | G111: =SUM(G90:G110) -> 0 | H111: =SUM(H90:H110) -> 0 | I111: =IFERROR(E111/D111,"") | J111: =IFERROR(H111/E111,"") | K111: =SUM(K90:K110) -> 0 | M111: =SUM(M90:M110) -> 0 | N111: =IFERROR(H111-Wk3!H111,"") -> 0 | O111: =IFERROR(D111-Wk3!D111,"") -> 0 | P111: =SUM(P90:P110) -> 0 | Q111: =SUM(Q90:Q110) -> 0 | R111: =IFERROR(INDEX('Last Year'!$C$6:$C$369,MATCH(B111-364,'Last Year'!$B$6:$B$369,0)),"") -> 0 | S111: =IFERROR(H111/R111-1,"")
A112: =TEXT(Setup!$C$5+26,"dddd") -> Saturday | B112: =Setup!$C$5+26 -> 46053 | C112: 9.00 - 9.30 | P112: =IFERROR(H112/Setup!$C$6,"") -> 0 | Q112: =IFERROR(H112-P112,"") -> 0
A113: =TEXT(Setup!$C$5+26,"dddd") -> Saturday | B113: =Setup!$C$5+26 -> 46053 | C113: 9.30 - 10.00 | P113: =IFERROR(H113/Setup!$C$6,"") -> 0 | Q113: =IFERROR(H113-P113,"") -> 0
A114: =TEXT(Setup!$C$5+26,"dddd") -> Saturday | B114: =Setup!$C$5+26 -> 46053 | C114: 10.00 - 10.30 | P114: =IFERROR(H114/Setup!$C$6,"") -> 0 | Q114: =IFERROR(H114-P114,"") -> 0
A115: =TEXT(Setup!$C$5+26,"dddd") -> Saturday | B115: =Setup!$C$5+26 -> 46053 | C115: 10.30 - 11.00 | P115: =IFERROR(H115/Setup!$C$6,"") -> 0 | Q115: =IFERROR(H115-P115,"") -> 0
A116: =TEXT(Setup!$C$5+26,"dddd") -> Saturday | B116: =Setup!$C$5+26 -> 46053 | C116: 11.00 - 11.30 | P116: =IFERROR(H116/Setup!$C$6,"") -> 0 | Q116: =IFERROR(H116-P116,"") -> 0
A117: =TEXT(Setup!$C$5+26,"dddd") -> Saturday | B117: =Setup!$C$5+26 -> 46053 | C117: 11.30 - 12.00 | P117: =IFERROR(H117/Setup!$C$6,"") -> 0 | Q117: =IFERROR(H117-P117,"") -> 0
A118: =TEXT(Setup!$C$5+26,"dddd") -> Saturday | B118: =Setup!$C$5+26 -> 46053 | C118: 12.00 - 12.30 | P118: =IFERROR(H118/Setup!$C$6,"") -> 0 | Q118: =IFERROR(H118-P118,"") -> 0
A119: =TEXT(Setup!$C$5+26,"dddd") -> Saturday | B119: =Setup!$C$5+26 -> 46053 | C119: 12.30 - 13.00 | P119: =IFERROR(H119/Setup!$C$6,"") -> 0 | Q119: =IFERROR(H119-P119,"") -> 0
A120: =TEXT(Setup!$C$5+26,"dddd") -> Saturday | B120: =Setup!$C$5+26 -> 46053 | C120: 13.00 - 13.30 | P120: =IFERROR(H120/Setup!$C$6,"") -> 0 | Q120: =IFERROR(H120-P120,"") -> 0
A121: =TEXT(Setup!$C$5+26,"dddd") -> Saturday | B121: =Setup!$C$5+26 -> 46053 | C121: 13.30 - 14.00 | P121: =IFERROR(H121/Setup!$C$6,"") -> 0 | Q121: =IFERROR(H121-P121,"") -> 0
A122: =TEXT(Setup!$C$5+26,"dddd") -> Saturday | B122: =Setup!$C$5+26 -> 46053 | C122: 14.00 - 14.30 | P122: =IFERROR(H122/Setup!$C$6,"") -> 0 | Q122: =IFERROR(H122-P122,"") -> 0
A123: =TEXT(Setup!$C$5+26,"dddd") -> Saturday | B123: =Setup!$C$5+26 -> 46053 | C123: 14.30 - 15.00 | P123: =IFERROR(H123/Setup!$C$6,"") -> 0 | Q123: =IFERROR(H123-P123,"") -> 0
... A132: =TEXT(Setup!$C$5+26,"dddd") -> Saturday | B132: =Setup!$C$5+26 -> 46053 | C132: ONLINE | P132: =IFERROR(H132/Setup!$C$6,"") -> 0 | Q132: =IFERROR(H132-P132,"") -> 0
A133: =TEXT(Setup!$C$5+26,"dddd") -> Saturday | B133: =Setup!$C$5+26 -> 46053 | C133: TOTAL | D133: =SUM(D112:D132) -> 0 | E133: =SUM(E112:E132) -> 0 | F133: =SUM(F112:F132) -> 0 | G133: =SUM(G112:G132) -> 0 | H133: =SUM(H112:H132) -> 0 | I133: =IFERROR(E133/D133,"") | J133: =IFERROR(H133/E133,"") | K133: =SUM(K112:K132) -> 0 | M133: =SUM(M112:M132) -> 0 | N133: =IFERROR(H133-Wk3!H133,"") -> 0 | O133: =IFERROR(D133-Wk3!D133,"") -> 0 | P133: =SUM(P112:P132) -> 0 | Q133: =SUM(Q112:Q132) -> 0 | R133: =IFERROR(INDEX('Last Year'!$C$6:$C$369,MATCH(B133-364,'Last Year'!$B$6:$B$369,0)),"") -> 0 | S133: =IFERROR(H133/R133-1,"")
A134: =TEXT(Setup!$C$5+27,"dddd") -> Sunday | B134: =Setup!$C$5+27 -> 46054 | C134: 9.00 - 9.30 | P134: =IFERROR(H134/Setup!$C$6,"") -> 0 | Q134: =IFERROR(H134-P134,"") -> 0
A135: =TEXT(Setup!$C$5+27,"dddd") -> Sunday | B135: =Setup!$C$5+27 -> 46054 | C135: 9.30 - 10.00 | P135: =IFERROR(H135/Setup!$C$6,"") -> 0 | Q135: =IFERROR(H135-P135,"") -> 0
A136: =TEXT(Setup!$C$5+27,"dddd") -> Sunday | B136: =Setup!$C$5+27 -> 46054 | C136: 10.00 - 10.30 | P136: =IFERROR(H136/Setup!$C$6,"") -> 0 | Q136: =IFERROR(H136-P136,"") -> 0
A137: =TEXT(Setup!$C$5+27,"dddd") -> Sunday | B137: =Setup!$C$5+27 -> 46054 | C137: 10.30 - 11.00 | P137: =IFERROR(H137/Setup!$C$6,"") -> 0 | Q137: =IFERROR(H137-P137,"") -> 0
A138: =TEXT(Setup!$C$5+27,"dddd") -> Sunday | B138: =Setup!$C$5+27 -> 46054 | C138: 11.00 - 11.30 | P138: =IFERROR(H138/Setup!$C$6,"") -> 0 | Q138: =IFERROR(H138-P138,"") -> 0
A139: =TEXT(Setup!$C$5+27,"dddd") -> Sunday | B139: =Setup!$C$5+27 -> 46054 | C139: 11.30 - 12.00 | P139: =IFERROR(H139/Setup!$C$6,"") -> 0 | Q139: =IFERROR(H139-P139,"") -> 0
A140: =TEXT(Setup!$C$5+27,"dddd") -> Sunday | B140: =Setup!$C$5+27 -> 46054 | C140: 12.00 - 12.30 | P140: =IFERROR(H140/Setup!$C$6,"") -> 0 | Q140: =IFERROR(H140-P140,"") -> 0
A141: =TEXT(Setup!$C$5+27,"dddd") -> Sunday | B141: =Setup!$C$5+27 -> 46054 | C141: 12.30 - 13.00 | P141: =IFERROR(H141/Setup!$C$6,"") -> 0 | Q141: =IFERROR(H141-P141,"") -> 0
A142: =TEXT(Setup!$C$5+27,"dddd") -> Sunday | B142: =Setup!$C$5+27 -> 46054 | C142: 13.00 - 13.30 | P142: =IFERROR(H142/Setup!$C$6,"") -> 0 | Q142: =IFERROR(H142-P142,"") -> 0
A143: =TEXT(Setup!$C$5+27,"dddd") -> Sunday | B143: =Setup!$C$5+27 -> 46054 | C143: 13.30 - 14.00 | P143: =IFERROR(H143/Setup!$C$6,"") -> 0 | Q143: =IFERROR(H143-P143,"") -> 0
A144: =TEXT(Setup!$C$5+27,"dddd") -> Sunday | B144: =Setup!$C$5+27 -> 46054 | C144: 14.00 - 14.30 | P144: =IFERROR(H144/Setup!$C$6,"") -> 0 | Q144: =IFERROR(H144-P144,"") -> 0
A145: =TEXT(Setup!$C$5+27,"dddd") -> Sunday | B145: =Setup!$C$5+27 -> 46054 | C145: 14.30 - 15.00 | P145: =IFERROR(H145/Setup!$C$6,"") -> 0 | Q145: =IFERROR(H145-P145,"") -> 0
... A154: =TEXT(Setup!$C$5+27,"dddd") -> Sunday | B154: =Setup!$C$5+27 -> 46054 | C154: ONLINE | P154: =IFERROR(H154/Setup!$C$6,"") -> 0 | Q154: =IFERROR(H154-P154,"") -> 0
A155: =TEXT(Setup!$C$5+27,"dddd") -> Sunday | B155: =Setup!$C$5+27 -> 46054 | C155: TOTAL | D155: =SUM(D134:D154) -> 0 | E155: =SUM(E134:E154) -> 0 | F155: =SUM(F134:F154) -> 0 | G155: =SUM(G134:G154) -> 0 | H155: =SUM(H134:H154) -> 0 | I155: =IFERROR(E155/D155,"") | J155: =IFERROR(H155/E155,"") | K155: =SUM(K134:K154) -> 0 | M155: =SUM(M134:M154) -> 0 | N155: =IFERROR(H155-Wk3!H155,"") -> 0 | O155: =IFERROR(D155-Wk3!D155,"") -> 0 | P155: =SUM(P134:P154) -> 0 | Q155: =SUM(Q134:Q154) -> 0 | R155: =IFERROR(INDEX('Last Year'!$C$6:$C$369,MATCH(B155-364,'Last Year'!$B$6:$B$369,0)),"") -> 0 | S155: =IFERROR(H155/R155-1,"")
C156: FULL WEEK | D156: =D23+D45+D67+D89+D111+D133+D155 -> 0 | E156: =E23+E45+E67+E89+E111+E133+E155 -> 0 | F156: =F23+F45+F67+F89+F111+F133+F155 -> 0 | G156: =G23+G45+G67+G89+G111+G133+G155 -> 0 | H156: =H23+H45+H67+H89+H111+H133+H155 -> 0 | I156: =IFERROR(E156/D156,"") | J156: =IFERROR(H156/E156,"") | K156: =K23+K45+K67+K89+K111+K133+K155 -> 0 | M156: =M23+M45+M67+M89+M111+M133+M155 -> 0 | P156: =P23+P45+P67+P89+P111+P133+P155 -> 0 | Q156: =Q23+Q45+Q67+Q89+Q111+Q133+Q155 -> 0 | R156: =R23+R45+R67+R89+R111+R133+R155 -> 0 | S156: =IFERROR(H156/R156-1,"")
...

Sheet Wk5
A1: Day | B1: Date | C1: Time | D1: Customers In | E1: Sales | F1: Vouchers Used | G1: Walk In/Out | H1: Sale Amount | I1: Conversion | J1: Avg Sale | K1: Tracked Category | L1: Notes | M1: Cash | N1: vs Last Wk € | O1: vs Last Wk Cust | P1: Est. Cost | Q1: Est. Profit | R1: Last Year Day | S1: vs Last Year
A2: =TEXT(Setup!$C$5+28,"dddd") -> Monday | B2: =Setup!$C$5+28 -> 46055 | C2: 9.00 - 9.30 | P2: =IFERROR(H2/Setup!$C$6,"") -> 0 | Q2: =IFERROR(H2-P2,"") -> 0
A3: =TEXT(Setup!$C$5+28,"dddd") -> Monday | B3: =Setup!$C$5+28 -> 46055 | C3: 9.30 - 10.00 | P3: =IFERROR(H3/Setup!$C$6,"") -> 0 | Q3: =IFERROR(H3-P3,"") -> 0
A4: =TEXT(Setup!$C$5+28,"dddd") -> Monday | B4: =Setup!$C$5+28 -> 46055 | C4: 10.00 - 10.30 | P4: =IFERROR(H4/Setup!$C$6,"") -> 0 | Q4: =IFERROR(H4-P4,"") -> 0
A5: =TEXT(Setup!$C$5+28,"dddd") -> Monday | B5: =Setup!$C$5+28 -> 46055 | C5: 10.30 - 11.00 | P5: =IFERROR(H5/Setup!$C$6,"") -> 0 | Q5: =IFERROR(H5-P5,"") -> 0
A6: =TEXT(Setup!$C$5+28,"dddd") -> Monday | B6: =Setup!$C$5+28 -> 46055 | C6: 11.00 - 11.30 | P6: =IFERROR(H6/Setup!$C$6,"") -> 0 | Q6: =IFERROR(H6-P6,"") -> 0
A7: =TEXT(Setup!$C$5+28,"dddd") -> Monday | B7: =Setup!$C$5+28 -> 46055 | C7: 11.30 - 12.00 | P7: =IFERROR(H7/Setup!$C$6,"") -> 0 | Q7: =IFERROR(H7-P7,"") -> 0
A8: =TEXT(Setup!$C$5+28,"dddd") -> Monday | B8: =Setup!$C$5+28 -> 46055 | C8: 12.00 - 12.30 | P8: =IFERROR(H8/Setup!$C$6,"") -> 0 | Q8: =IFERROR(H8-P8,"") -> 0
A9: =TEXT(Setup!$C$5+28,"dddd") -> Monday | B9: =Setup!$C$5+28 -> 46055 | C9: 12.30 - 13.00 | P9: =IFERROR(H9/Setup!$C$6,"") -> 0 | Q9: =IFERROR(H9-P9,"") -> 0
A10: =TEXT(Setup!$C$5+28,"dddd") -> Monday | B10: =Setup!$C$5+28 -> 46055 | C10: 13.00 - 13.30 | P10: =IFERROR(H10/Setup!$C$6,"") -> 0 | Q10: =IFERROR(H10-P10,"") -> 0
A11: =TEXT(Setup!$C$5+28,"dddd") -> Monday | B11: =Setup!$C$5+28 -> 46055 | C11: 13.30 - 14.00 | P11: =IFERROR(H11/Setup!$C$6,"") -> 0 | Q11: =IFERROR(H11-P11,"") -> 0
A12: =TEXT(Setup!$C$5+28,"dddd") -> Monday | B12: =Setup!$C$5+28 -> 46055 | C12: 14.00 - 14.30 | P12: =IFERROR(H12/Setup!$C$6,"") -> 0 | Q12: =IFERROR(H12-P12,"") -> 0
A13: =TEXT(Setup!$C$5+28,"dddd") -> Monday | B13: =Setup!$C$5+28 -> 46055 | C13: 14.30 - 15.00 | P13: =IFERROR(H13/Setup!$C$6,"") -> 0 | Q13: =IFERROR(H13-P13,"") -> 0
... A22: =TEXT(Setup!$C$5+28,"dddd") -> Monday | B22: =Setup!$C$5+28 -> 46055 | C22: ONLINE | P22: =IFERROR(H22/Setup!$C$6,"") -> 0 | Q22: =IFERROR(H22-P22,"") -> 0
A23: =TEXT(Setup!$C$5+28,"dddd") -> Monday | B23: =Setup!$C$5+28 -> 46055 | C23: TOTAL | D23: =SUM(D2:D22) -> 0 | E23: =SUM(E2:E22) -> 0 | F23: =SUM(F2:F22) -> 0 | G23: =SUM(G2:G22) -> 0 | H23: =SUM(H2:H22) -> 0 | I23: =IFERROR(E23/D23,"") | J23: =IFERROR(H23/E23,"") | K23: =SUM(K2:K22) -> 0 | M23: =SUM(M2:M22) -> 0 | N23: =IFERROR(H23-Wk4!H23,"") -> 0 | O23: =IFERROR(D23-Wk4!D23,"") -> 0 | P23: =SUM(P2:P22) -> 0 | Q23: =SUM(Q2:Q22) -> 0 | R23: =IFERROR(INDEX('Last Year'!$C$6:$C$369,MATCH(B23-364,'Last Year'!$B$6:$B$369,0)),"") -> 0 | S23: =IFERROR(H23/R23-1,"")
A24: =TEXT(Setup!$C$5+29,"dddd") -> Tuesday | B24: =Setup!$C$5+29 -> 46056 | C24: 9.00 - 9.30 | P24: =IFERROR(H24/Setup!$C$6,"") -> 0 | Q24: =IFERROR(H24-P24,"") -> 0
A25: =TEXT(Setup!$C$5+29,"dddd") -> Tuesday | B25: =Setup!$C$5+29 -> 46056 | C25: 9.30 - 10.00 | P25: =IFERROR(H25/Setup!$C$6,"") -> 0 | Q25: =IFERROR(H25-P25,"") -> 0
A26: =TEXT(Setup!$C$5+29,"dddd") -> Tuesday | B26: =Setup!$C$5+29 -> 46056 | C26: 10.00 - 10.30 | P26: =IFERROR(H26/Setup!$C$6,"") -> 0 | Q26: =IFERROR(H26-P26,"") -> 0
A27: =TEXT(Setup!$C$5+29,"dddd") -> Tuesday | B27: =Setup!$C$5+29 -> 46056 | C27: 10.30 - 11.00 | P27: =IFERROR(H27/Setup!$C$6,"") -> 0 | Q27: =IFERROR(H27-P27,"") -> 0
A28: =TEXT(Setup!$C$5+29,"dddd") -> Tuesday | B28: =Setup!$C$5+29 -> 46056 | C28: 11.00 - 11.30 | P28: =IFERROR(H28/Setup!$C$6,"") -> 0 | Q28: =IFERROR(H28-P28,"") -> 0
A29: =TEXT(Setup!$C$5+29,"dddd") -> Tuesday | B29: =Setup!$C$5+29 -> 46056 | C29: 11.30 - 12.00 | P29: =IFERROR(H29/Setup!$C$6,"") -> 0 | Q29: =IFERROR(H29-P29,"") -> 0
A30: =TEXT(Setup!$C$5+29,"dddd") -> Tuesday | B30: =Setup!$C$5+29 -> 46056 | C30: 12.00 - 12.30 | P30: =IFERROR(H30/Setup!$C$6,"") -> 0 | Q30: =IFERROR(H30-P30,"") -> 0
A31: =TEXT(Setup!$C$5+29,"dddd") -> Tuesday | B31: =Setup!$C$5+29 -> 46056 | C31: 12.30 - 13.00 | P31: =IFERROR(H31/Setup!$C$6,"") -> 0 | Q31: =IFERROR(H31-P31,"") -> 0
A32: =TEXT(Setup!$C$5+29,"dddd") -> Tuesday | B32: =Setup!$C$5+29 -> 46056 | C32: 13.00 - 13.30 | P32: =IFERROR(H32/Setup!$C$6,"") -> 0 | Q32: =IFERROR(H32-P32,"") -> 0
A33: =TEXT(Setup!$C$5+29,"dddd") -> Tuesday | B33: =Setup!$C$5+29 -> 46056 | C33: 13.30 - 14.00 | P33: =IFERROR(H33/Setup!$C$6,"") -> 0 | Q33: =IFERROR(H33-P33,"") -> 0
A34: =TEXT(Setup!$C$5+29,"dddd") -> Tuesday | B34: =Setup!$C$5+29 -> 46056 | C34: 14.00 - 14.30 | P34: =IFERROR(H34/Setup!$C$6,"") -> 0 | Q34: =IFERROR(H34-P34,"") -> 0
A35: =TEXT(Setup!$C$5+29,"dddd") -> Tuesday | B35: =Setup!$C$5+29 -> 46056 | C35: 14.30 - 15.00 | P35: =IFERROR(H35/Setup!$C$6,"") -> 0 | Q35: =IFERROR(H35-P35,"") -> 0
... A44: =TEXT(Setup!$C$5+29,"dddd") -> Tuesday | B44: =Setup!$C$5+29 -> 46056 | C44: ONLINE | P44: =IFERROR(H44/Setup!$C$6,"") -> 0 | Q44: =IFERROR(H44-P44,"") -> 0
A45: =TEXT(Setup!$C$5+29,"dddd") -> Tuesday | B45: =Setup!$C$5+29 -> 46056 | C45: TOTAL | D45: =SUM(D24:D44) -> 0 | E45: =SUM(E24:E44) -> 0 | F45: =SUM(F24:F44) -> 0 | G45: =SUM(G24:G44) -> 0 | H45: =SUM(H24:H44) -> 0 | I45: =IFERROR(E45/D45,"") | J45: =IFERROR(H45/E45,"") | K45: =SUM(K24:K44) -> 0 | M45: =SUM(M24:M44) -> 0 | N45: =IFERROR(H45-Wk4!H45,"") -> 0 | O45: =IFERROR(D45-Wk4!D45,"") -> 0 | P45: =SUM(P24:P44) -> 0 | Q45: =SUM(Q24:Q44) -> 0 | R45: =IFERROR(INDEX('Last Year'!$C$6:$C$369,MATCH(B45-364,'Last Year'!$B$6:$B$369,0)),"") -> 0 | S45: =IFERROR(H45/R45-1,"")
A46: =TEXT(Setup!$C$5+30,"dddd") -> Wednesday | B46: =Setup!$C$5+30 -> 46057 | C46: 9.00 - 9.30 | P46: =IFERROR(H46/Setup!$C$6,"") -> 0 | Q46: =IFERROR(H46-P46,"") -> 0
A47: =TEXT(Setup!$C$5+30,"dddd") -> Wednesday | B47: =Setup!$C$5+30 -> 46057 | C47: 9.30 - 10.00 | P47: =IFERROR(H47/Setup!$C$6,"") -> 0 | Q47: =IFERROR(H47-P47,"") -> 0
A48: =TEXT(Setup!$C$5+30,"dddd") -> Wednesday | B48: =Setup!$C$5+30 -> 46057 | C48: 10.00 - 10.30 | P48: =IFERROR(H48/Setup!$C$6,"") -> 0 | Q48: =IFERROR(H48-P48,"") -> 0
A49: =TEXT(Setup!$C$5+30,"dddd") -> Wednesday | B49: =Setup!$C$5+30 -> 46057 | C49: 10.30 - 11.00 | P49: =IFERROR(H49/Setup!$C$6,"") -> 0 | Q49: =IFERROR(H49-P49,"") -> 0
A50: =TEXT(Setup!$C$5+30,"dddd") -> Wednesday | B50: =Setup!$C$5+30 -> 46057 | C50: 11.00 - 11.30 | P50: =IFERROR(H50/Setup!$C$6,"") -> 0 | Q50: =IFERROR(H50-P50,"") -> 0
A51: =TEXT(Setup!$C$5+30,"dddd") -> Wednesday | B51: =Setup!$C$5+30 -> 46057 | C51: 11.30 - 12.00 | P51: =IFERROR(H51/Setup!$C$6,"") -> 0 | Q51: =IFERROR(H51-P51,"") -> 0
A52: =TEXT(Setup!$C$5+30,"dddd") -> Wednesday | B52: =Setup!$C$5+30 -> 46057 | C52: 12.00 - 12.30 | P52: =IFERROR(H52/Setup!$C$6,"") -> 0 | Q52: =IFERROR(H52-P52,"") -> 0
A53: =TEXT(Setup!$C$5+30,"dddd") -> Wednesday | B53: =Setup!$C$5+30 -> 46057 | C53: 12.30 - 13.00 | P53: =IFERROR(H53/Setup!$C$6,"") -> 0 | Q53: =IFERROR(H53-P53,"") -> 0
A54: =TEXT(Setup!$C$5+30,"dddd") -> Wednesday | B54: =Setup!$C$5+30 -> 46057 | C54: 13.00 - 13.30 | P54: =IFERROR(H54/Setup!$C$6,"") -> 0 | Q54: =IFERROR(H54-P54,"") -> 0
A55: =TEXT(Setup!$C$5+30,"dddd") -> Wednesday | B55: =Setup!$C$5+30 -> 46057 | C55: 13.30 - 14.00 | P55: =IFERROR(H55/Setup!$C$6,"") -> 0 | Q55: =IFERROR(H55-P55,"") -> 0
A56: =TEXT(Setup!$C$5+30,"dddd") -> Wednesday | B56: =Setup!$C$5+30 -> 46057 | C56: 14.00 - 14.30 | P56: =IFERROR(H56/Setup!$C$6,"") -> 0 | Q56: =IFERROR(H56-P56,"") -> 0
A57: =TEXT(Setup!$C$5+30,"dddd") -> Wednesday | B57: =Setup!$C$5+30 -> 46057 | C57: 14.30 - 15.00 | P57: =IFERROR(H57/Setup!$C$6,"") -> 0 | Q57: =IFERROR(H57-P57,"") -> 0
... A66: =TEXT(Setup!$C$5+30,"dddd") -> Wednesday | B66: =Setup!$C$5+30 -> 46057 | C66: ONLINE | P66: =IFERROR(H66/Setup!$C$6,"") -> 0 | Q66: =IFERROR(H66-P66,"") -> 0
A67: =TEXT(Setup!$C$5+30,"dddd") -> Wednesday | B67: =Setup!$C$5+30 -> 46057 | C67: TOTAL | D67: =SUM(D46:D66) -> 0 | E67: =SUM(E46:E66) -> 0 | F67: =SUM(F46:F66) -> 0 | G67: =SUM(G46:G66) -> 0 | H67: =SUM(H46:H66) -> 0 | I67: =IFERROR(E67/D67,"") | J67: =IFERROR(H67/E67,"") | K67: =SUM(K46:K66) -> 0 | M67: =SUM(M46:M66) -> 0 | N67: =IFERROR(H67-Wk4!H67,"") -> 0 | O67: =IFERROR(D67-Wk4!D67,"") -> 0 | P67: =SUM(P46:P66) -> 0 | Q67: =SUM(Q46:Q66) -> 0 | R67: =IFERROR(INDEX('Last Year'!$C$6:$C$369,MATCH(B67-364,'Last Year'!$B$6:$B$369,0)),"") -> 0 | S67: =IFERROR(H67/R67-1,"")
A68: =TEXT(Setup!$C$5+31,"dddd") -> Thursday | B68: =Setup!$C$5+31 -> 46058 | C68: 9.00 - 9.30 | P68: =IFERROR(H68/Setup!$C$6,"") -> 0 | Q68: =IFERROR(H68-P68,"") -> 0
A69: =TEXT(Setup!$C$5+31,"dddd") -> Thursday | B69: =Setup!$C$5+31 -> 46058 | C69: 9.30 - 10.00 | P69: =IFERROR(H69/Setup!$C$6,"") -> 0 | Q69: =IFERROR(H69-P69,"") -> 0
A70: =TEXT(Setup!$C$5+31,"dddd") -> Thursday | B70: =Setup!$C$5+31 -> 46058 | C70: 10.00 - 10.30 | P70: =IFERROR(H70/Setup!$C$6,"") -> 0 | Q70: =IFERROR(H70-P70,"") -> 0
A71: =TEXT(Setup!$C$5+31,"dddd") -> Thursday | B71: =Setup!$C$5+31 -> 46058 | C71: 10.30 - 11.00 | P71: =IFERROR(H71/Setup!$C$6,"") -> 0 | Q71: =IFERROR(H71-P71,"") -> 0
A72: =TEXT(Setup!$C$5+31,"dddd") -> Thursday | B72: =Setup!$C$5+31 -> 46058 | C72: 11.00 - 11.30 | P72: =IFERROR(H72/Setup!$C$6,"") -> 0 | Q72: =IFERROR(H72-P72,"") -> 0
A73: =TEXT(Setup!$C$5+31,"dddd") -> Thursday | B73: =Setup!$C$5+31 -> 46058 | C73: 11.30 - 12.00 | P73: =IFERROR(H73/Setup!$C$6,"") -> 0 | Q73: =IFERROR(H73-P73,"") -> 0
A74: =TEXT(Setup!$C$5+31,"dddd") -> Thursday | B74: =Setup!$C$5+31 -> 46058 | C74: 12.00 - 12.30 | P74: =IFERROR(H74/Setup!$C$6,"") -> 0 | Q74: =IFERROR(H74-P74,"") -> 0
A75: =TEXT(Setup!$C$5+31,"dddd") -> Thursday | B75: =Setup!$C$5+31 -> 46058 | C75: 12.30 - 13.00 | P75: =IFERROR(H75/Setup!$C$6,"") -> 0 | Q75: =IFERROR(H75-P75,"") -> 0
A76: =TEXT(Setup!$C$5+31,"dddd") -> Thursday | B76: =Setup!$C$5+31 -> 46058 | C76: 13.00 - 13.30 | P76: =IFERROR(H76/Setup!$C$6,"") -> 0 | Q76: =IFERROR(H76-P76,"") -> 0
A77: =TEXT(Setup!$C$5+31,"dddd") -> Thursday | B77: =Setup!$C$5+31 -> 46058 | C77: 13.30 - 14.00 | P77: =IFERROR(H77/Setup!$C$6,"") -> 0 | Q77: =IFERROR(H77-P77,"") -> 0
A78: =TEXT(Setup!$C$5+31,"dddd") -> Thursday | B78: =Setup!$C$5+31 -> 46058 | C78: 14.00 - 14.30 | P78: =IFERROR(H78/Setup!$C$6,"") -> 0 | Q78: =IFERROR(H78-P78,"") -> 0
A79: =TEXT(Setup!$C$5+31,"dddd") -> Thursday | B79: =Setup!$C$5+31 -> 46058 | C79: 14.30 - 15.00 | P79: =IFERROR(H79/Setup!$C$6,"") -> 0 | Q79: =IFERROR(H79-P79,"") -> 0
... A88: =TEXT(Setup!$C$5+31,"dddd") -> Thursday | B88: =Setup!$C$5+31 -> 46058 | C88: ONLINE | P88: =IFERROR(H88/Setup!$C$6,"") -> 0 | Q88: =IFERROR(H88-P88,"") -> 0
A89: =TEXT(Setup!$C$5+31,"dddd") -> Thursday | B89: =Setup!$C$5+31 -> 46058 | C89: TOTAL | D89: =SUM(D68:D88) -> 0 | E89: =SUM(E68:E88) -> 0 | F89: =SUM(F68:F88) -> 0 | G89: =SUM(G68:G88) -> 0 | H89: =SUM(H68:H88) -> 0 | I89: =IFERROR(E89/D89,"") | J89: =IFERROR(H89/E89,"") | K89: =SUM(K68:K88) -> 0 | M89: =SUM(M68:M88) -> 0 | N89: =IFERROR(H89-Wk4!H89,"") -> 0 | O89: =IFERROR(D89-Wk4!D89,"") -> 0 | P89: =SUM(P68:P88) -> 0 | Q89: =SUM(Q68:Q88) -> 0 | R89: =IFERROR(INDEX('Last Year'!$C$6:$C$369,MATCH(B89-364,'Last Year'!$B$6:$B$369,0)),"") -> 0 | S89: =IFERROR(H89/R89-1,"")
A90: =TEXT(Setup!$C$5+32,"dddd") -> Friday | B90: =Setup!$C$5+32 -> 46059 | C90: 9.00 - 9.30 | P90: =IFERROR(H90/Setup!$C$6,"") -> 0 | Q90: =IFERROR(H90-P90,"") -> 0
A91: =TEXT(Setup!$C$5+32,"dddd") -> Friday | B91: =Setup!$C$5+32 -> 46059 | C91: 9.30 - 10.00 | P91: =IFERROR(H91/Setup!$C$6,"") -> 0 | Q91: =IFERROR(H91-P91,"") -> 0
A92: =TEXT(Setup!$C$5+32,"dddd") -> Friday | B92: =Setup!$C$5+32 -> 46059 | C92: 10.00 - 10.30 | P92: =IFERROR(H92/Setup!$C$6,"") -> 0 | Q92: =IFERROR(H92-P92,"") -> 0
A93: =TEXT(Setup!$C$5+32,"dddd") -> Friday | B93: =Setup!$C$5+32 -> 46059 | C93: 10.30 - 11.00 | P93: =IFERROR(H93/Setup!$C$6,"") -> 0 | Q93: =IFERROR(H93-P93,"") -> 0
A94: =TEXT(Setup!$C$5+32,"dddd") -> Friday | B94: =Setup!$C$5+32 -> 46059 | C94: 11.00 - 11.30 | P94: =IFERROR(H94/Setup!$C$6,"") -> 0 | Q94: =IFERROR(H94-P94,"") -> 0
A95: =TEXT(Setup!$C$5+32,"dddd") -> Friday | B95: =Setup!$C$5+32 -> 46059 | C95: 11.30 - 12.00 | P95: =IFERROR(H95/Setup!$C$6,"") -> 0 | Q95: =IFERROR(H95-P95,"") -> 0
A96: =TEXT(Setup!$C$5+32,"dddd") -> Friday | B96: =Setup!$C$5+32 -> 46059 | C96: 12.00 - 12.30 | P96: =IFERROR(H96/Setup!$C$6,"") -> 0 | Q96: =IFERROR(H96-P96,"") -> 0
A97: =TEXT(Setup!$C$5+32,"dddd") -> Friday | B97: =Setup!$C$5+32 -> 46059 | C97: 12.30 - 13.00 | P97: =IFERROR(H97/Setup!$C$6,"") -> 0 | Q97: =IFERROR(H97-P97,"") -> 0
A98: =TEXT(Setup!$C$5+32,"dddd") -> Friday | B98: =Setup!$C$5+32 -> 46059 | C98: 13.00 - 13.30 | P98: =IFERROR(H98/Setup!$C$6,"") -> 0 | Q98: =IFERROR(H98-P98,"") -> 0
A99: =TEXT(Setup!$C$5+32,"dddd") -> Friday | B99: =Setup!$C$5+32 -> 46059 | C99: 13.30 - 14.00 | P99: =IFERROR(H99/Setup!$C$6,"") -> 0 | Q99: =IFERROR(H99-P99,"") -> 0
A100: =TEXT(Setup!$C$5+32,"dddd") -> Friday | B100: =Setup!$C$5+32 -> 46059 | C100: 14.00 - 14.30 | P100: =IFERROR(H100/Setup!$C$6,"") -> 0 | Q100: =IFERROR(H100-P100,"") -> 0
A101: =TEXT(Setup!$C$5+32,"dddd") -> Friday | B101: =Setup!$C$5+32 -> 46059 | C101: 14.30 - 15.00 | P101: =IFERROR(H101/Setup!$C$6,"") -> 0 | Q101: =IFERROR(H101-P101,"") -> 0
... A110: =TEXT(Setup!$C$5+32,"dddd") -> Friday | B110: =Setup!$C$5+32 -> 46059 | C110: ONLINE | P110: =IFERROR(H110/Setup!$C$6,"") -> 0 | Q110: =IFERROR(H110-P110,"") -> 0
A111: =TEXT(Setup!$C$5+32,"dddd") -> Friday | B111: =Setup!$C$5+32 -> 46059 | C111: TOTAL | D111: =SUM(D90:D110) -> 0 | E111: =SUM(E90:E110) -> 0 | F111: =SUM(F90:F110) -> 0 | G111: =SUM(G90:G110) -> 0 | H111: =SUM(H90:H110) -> 0 | I111: =IFERROR(E111/D111,"") | J111: =IFERROR(H111/E111,"") | K111: =SUM(K90:K110) -> 0 | M111: =SUM(M90:M110) -> 0 | N111: =IFERROR(H111-Wk4!H111,"") -> 0 | O111: =IFERROR(D111-Wk4!D111,"") -> 0 | P111: =SUM(P90:P110) -> 0 | Q111: =SUM(Q90:Q110) -> 0 | R111: =IFERROR(INDEX('Last Year'!$C$6:$C$369,MATCH(B111-364,'Last Year'!$B$6:$B$369,0)),"") -> 0 | S111: =IFERROR(H111/R111-1,"")
A112: =TEXT(Setup!$C$5+33,"dddd") -> Saturday | B112: =Setup!$C$5+33 -> 46060 | C112: 9.00 - 9.30 | P112: =IFERROR(H112/Setup!$C$6,"") -> 0 | Q112: =IFERROR(H112-P112,"") -> 0
A113: =TEXT(Setup!$C$5+33,"dddd") -> Saturday | B113: =Setup!$C$5+33 -> 46060 | C113: 9.30 - 10.00 | P113: =IFERROR(H113/Setup!$C$6,"") -> 0 | Q113: =IFERROR(H113-P113,"") -> 0
A114: =TEXT(Setup!$C$5+33,"dddd") -> Saturday | B114: =Setup!$C$5+33 -> 46060 | C114: 10.00 - 10.30 | P114: =IFERROR(H114/Setup!$C$6,"") -> 0 | Q114: =IFERROR(H114-P114,"") -> 0
A115: =TEXT(Setup!$C$5+33,"dddd") -> Saturday | B115: =Setup!$C$5+33 -> 46060 | C115: 10.30 - 11.00 | P115: =IFERROR(H115/Setup!$C$6,"") -> 0 | Q115: =IFERROR(H115-P115,"") -> 0
A116: =TEXT(Setup!$C$5+33,"dddd") -> Saturday | B116: =Setup!$C$5+33 -> 46060 | C116: 11.00 - 11.30 | P116: =IFERROR(H116/Setup!$C$6,"") -> 0 | Q116: =IFERROR(H116-P116,"") -> 0
A117: =TEXT(Setup!$C$5+33,"dddd") -> Saturday | B117: =Setup!$C$5+33 -> 46060 | C117: 11.30 - 12.00 | P117: =IFERROR(H117/Setup!$C$6,"") -> 0 | Q117: =IFERROR(H117-P117,"") -> 0
A118: =TEXT(Setup!$C$5+33,"dddd") -> Saturday | B118: =Setup!$C$5+33 -> 46060 | C118: 12.00 - 12.30 | P118: =IFERROR(H118/Setup!$C$6,"") -> 0 | Q118: =IFERROR(H118-P118,"") -> 0
A119: =TEXT(Setup!$C$5+33,"dddd") -> Saturday | B119: =Setup!$C$5+33 -> 46060 | C119: 12.30 - 13.00 | P119: =IFERROR(H119/Setup!$C$6,"") -> 0 | Q119: =IFERROR(H119-P119,"") -> 0
A120: =TEXT(Setup!$C$5+33,"dddd") -> Saturday | B120: =Setup!$C$5+33 -> 46060 | C120: 13.00 - 13.30 | P120: =IFERROR(H120/Setup!$C$6,"") -> 0 | Q120: =IFERROR(H120-P120,"") -> 0
A121: =TEXT(Setup!$C$5+33,"dddd") -> Saturday | B121: =Setup!$C$5+33 -> 46060 | C121: 13.30 - 14.00 | P121: =IFERROR(H121/Setup!$C$6,"") -> 0 | Q121: =IFERROR(H121-P121,"") -> 0
A122: =TEXT(Setup!$C$5+33,"dddd") -> Saturday | B122: =Setup!$C$5+33 -> 46060 | C122: 14.00 - 14.30 | P122: =IFERROR(H122/Setup!$C$6,"") -> 0 | Q122: =IFERROR(H122-P122,"") -> 0
A123: =TEXT(Setup!$C$5+33,"dddd") -> Saturday | B123: =Setup!$C$5+33 -> 46060 | C123: 14.30 - 15.00 | P123: =IFERROR(H123/Setup!$C$6,"") -> 0 | Q123: =IFERROR(H123-P123,"") -> 0
... A132: =TEXT(Setup!$C$5+33,"dddd") -> Saturday | B132: =Setup!$C$5+33 -> 46060 | C132: ONLINE | P132: =IFERROR(H132/Setup!$C$6,"") -> 0 | Q132: =IFERROR(H132-P132,"") -> 0
A133: =TEXT(Setup!$C$5+33,"dddd") -> Saturday | B133: =Setup!$C$5+33 -> 46060 | C133: TOTAL | D133: =SUM(D112:D132) -> 0 | E133: =SUM(E112:E132) -> 0 | F133: =SUM(F112:F132) -> 0 | G133: =SUM(G112:G132) -> 0 | H133: =SUM(H112:H132) -> 0 | I133: =IFERROR(E133/D133,"") | J133: =IFERROR(H133/E133,"") | K133: =SUM(K112:K132) -> 0 | M133: =SUM(M112:M132) -> 0 | N133: =IFERROR(H133-Wk4!H133,"") -> 0 | O133: =IFERROR(D133-Wk4!D133,"") -> 0 | P133: =SUM(P112:P132) -> 0 | Q133: =SUM(Q112:Q132) -> 0 | R133: =IFERROR(INDEX('Last Year'!$C$6:$C$369,MATCH(B133-364,'Last Year'!$B$6:$B$369,0)),"") -> 0 | S133: =IFERROR(H133/R133-1,"")
A134: =TEXT(Setup!$C$5+34,"dddd") -> Sunday | B134: =Setup!$C$5+34 -> 46061 | C134: 9.00 - 9.30 | P134: =IFERROR(H134/Setup!$C$6,"") -> 0 | Q134: =IFERROR(H134-P134,"") -> 0
A135: =TEXT(Setup!$C$5+34,"dddd") -> Sunday | B135: =Setup!$C$5+34 -> 46061 | C135: 9.30 - 10.00 | P135: =IFERROR(H135/Setup!$C$6,"") -> 0 | Q135: =IFERROR(H135-P135,"") -> 0
A136: =TEXT(Setup!$C$5+34,"dddd") -> Sunday | B136: =Setup!$C$5+34 -> 46061 | C136: 10.00 - 10.30 | P136: =IFERROR(H136/Setup!$C$6,"") -> 0 | Q136: =IFERROR(H136-P136,"") -> 0
A137: =TEXT(Setup!$C$5+34,"dddd") -> Sunday | B137: =Setup!$C$5+34 -> 46061 | C137: 10.30 - 11.00 | P137: =IFERROR(H137/Setup!$C$6,"") -> 0 | Q137: =IFERROR(H137-P137,"") -> 0
A138: =TEXT(Setup!$C$5+34,"dddd") -> Sunday | B138: =Setup!$C$5+34 -> 46061 | C138: 11.00 - 11.30 | P138: =IFERROR(H138/Setup!$C$6,"") -> 0 | Q138: =IFERROR(H138-P138,"") -> 0
A139: =TEXT(Setup!$C$5+34,"dddd") -> Sunday | B139: =Setup!$C$5+34 -> 46061 | C139: 11.30 - 12.00 | P139: =IFERROR(H139/Setup!$C$6,"") -> 0 | Q139: =IFERROR(H139-P139,"") -> 0
A140: =TEXT(Setup!$C$5+34,"dddd") -> Sunday | B140: =Setup!$C$5+34 -> 46061 | C140: 12.00 - 12.30 | P140: =IFERROR(H140/Setup!$C$6,"") -> 0 | Q140: =IFERROR(H140-P140,"") -> 0
A141: =TEXT(Setup!$C$5+34,"dddd") -> Sunday | B141: =Setup!$C$5+34 -> 46061 | C141: 12.30 - 13.00 | P141: =IFERROR(H141/Setup!$C$6,"") -> 0 | Q141: =IFERROR(H141-P141,"") -> 0
A142: =TEXT(Setup!$C$5+34,"dddd") -> Sunday | B142: =Setup!$C$5+34 -> 46061 | C142: 13.00 - 13.30 | P142: =IFERROR(H142/Setup!$C$6,"") -> 0 | Q142: =IFERROR(H142-P142,"") -> 0
A143: =TEXT(Setup!$C$5+34,"dddd") -> Sunday | B143: =Setup!$C$5+34 -> 46061 | C143: 13.30 - 14.00 | P143: =IFERROR(H143/Setup!$C$6,"") -> 0 | Q143: =IFERROR(H143-P143,"") -> 0
A144: =TEXT(Setup!$C$5+34,"dddd") -> Sunday | B144: =Setup!$C$5+34 -> 46061 | C144: 14.00 - 14.30 | P144: =IFERROR(H144/Setup!$C$6,"") -> 0 | Q144: =IFERROR(H144-P144,"") -> 0
A145: =TEXT(Setup!$C$5+34,"dddd") -> Sunday | B145: =Setup!$C$5+34 -> 46061 | C145: 14.30 - 15.00 | P145: =IFERROR(H145/Setup!$C$6,"") -> 0 | Q145: =IFERROR(H145-P145,"") -> 0
... A154: =TEXT(Setup!$C$5+34,"dddd") -> Sunday | B154: =Setup!$C$5+34 -> 46061 | C154: ONLINE | P154: =IFERROR(H154/Setup!$C$6,"") -> 0 | Q154: =IFERROR(H154-P154,"") -> 0
A155: =TEXT(Setup!$C$5+34,"dddd") -> Sunday | B155: =Setup!$C$5+34 -> 46061 | C155: TOTAL | D155: =SUM(D134:D154) -> 0 | E155: =SUM(E134:E154) -> 0 | F155: =SUM(F134:F154) -> 0 | G155: =SUM(G134:G154) -> 0 | H155: =SUM(H134:H154) -> 0 | I155: =IFERROR(E155/D155,"") | J155: =IFERROR(H155/E155,"") | K155: =SUM(K134:K154) -> 0 | M155: =SUM(M134:M154) -> 0 | N155: =IFERROR(H155-Wk4!H155,"") -> 0 | O155: =IFERROR(D155-Wk4!D155,"") -> 0 | P155: =SUM(P134:P154) -> 0 | Q155: =SUM(Q134:Q154) -> 0 | R155: =IFERROR(INDEX('Last Year'!$C$6:$C$369,MATCH(B155-364,'Last Year'!$B$6:$B$369,0)),"") -> 0 | S155: =IFERROR(H155/R155-1,"")
C156: FULL WEEK | D156: =D23+D45+D67+D89+D111+D133+D155 -> 0 | E156: =E23+E45+E67+E89+E111+E133+E155 -> 0 | F156: =F23+F45+F67+F89+F111+F133+F155 -> 0 | G156: =G23+G45+G67+G89+G111+G133+G155 -> 0 | H156: =H23+H45+H67+H89+H111+H133+H155 -> 0 | I156: =IFERROR(E156/D156,"") | J156: =IFERROR(H156/E156,"") | K156: =K23+K45+K67+K89+K111+K133+K155 -> 0 | M156: =M23+M45+M67+M89+M111+M133+M155 -> 0 | P156: =P23+P45+P67+P89+P111+P133+P155 -> 0 | Q156: =Q23+Q45+Q67+Q89+Q111+Q133+Q155 -> 0 | R156: =R23+R45+R67+R89+R111+R133+R155 -> 0 | S156: =IFERROR(H156/R156-1,"")
...

Sheet Wk6
A1: Day | B1: Date | C1: Time | D1: Customers In | E1: Sales | F1: Vouchers Used | G1: Walk In/Out | H1: Sale Amount | I1: Conversion | J1: Avg Sale | K1: Tracked Category | L1: Notes | M1: Cash | N1: vs Last Wk € | O1: vs Last Wk Cust | P1: Est. Cost | Q1: Est. Profit | R1: Last Year Day | S1: vs Last Year
A2: =TEXT(Setup!$C$5+35,"dddd") -> Monday | B2: =Setup!$C$5+35 -> 46062 | C2: 9.00 - 9.30 | P2: =IFERROR(H2/Setup!$C$6,"") -> 0 | Q2: =IFERROR(H2-P2,"") -> 0
A3: =TEXT(Setup!$C$5+35,"dddd") -> Monday | B3: =Setup!$C$5+35 -> 46062 | C3: 9.30 - 10.00 | P3: =IFERROR(H3/Setup!$C$6,"") -> 0 | Q3: =IFERROR(H3-P3,"") -> 0
A4: =TEXT(Setup!$C$5+35,"dddd") -> Monday | B4: =Setup!$C$5+35 -> 46062 | C4: 10.00 - 10.30 | P4: =IFERROR(H4/Setup!$C$6,"") -> 0 | Q4: =IFERROR(H4-P4,"") -> 0
A5: =TEXT(Setup!$C$5+35,"dddd") -> Monday | B5: =Setup!$C$5+35 -> 46062 | C5: 10.30 - 11.00 | P5: =IFERROR(H5/Setup!$C$6,"") -> 0 | Q5: =IFERROR(H5-P5,"") -> 0
A6: =TEXT(Setup!$C$5+35,"dddd") -> Monday | B6: =Setup!$C$5+35 -> 46062 | C6: 11.00 - 11.30 | P6: =IFERROR(H6/Setup!$C$6,"") -> 0 | Q6: =IFERROR(H6-P6,"") -> 0
A7: =TEXT(Setup!$C$5+35,"dddd") -> Monday | B7: =Setup!$C$5+35 -> 46062 | C7: 11.30 - 12.00 | P7: =IFERROR(H7/Setup!$C$6,"") -> 0 | Q7: =IFERROR(H7-P7,"") -> 0
A8: =TEXT(Setup!$C$5+35,"dddd") -> Monday | B8: =Setup!$C$5+35 -> 46062 | C8: 12.00 - 12.30 | P8: =IFERROR(H8/Setup!$C$6,"") -> 0 | Q8: =IFERROR(H8-P8,"") -> 0
A9: =TEXT(Setup!$C$5+35,"dddd") -> Monday | B9: =Setup!$C$5+35 -> 46062 | C9: 12.30 - 13.00 | P9: =IFERROR(H9/Setup!$C$6,"") -> 0 | Q9: =IFERROR(H9-P9,"") -> 0
A10: =TEXT(Setup!$C$5+35,"dddd") -> Monday | B10: =Setup!$C$5+35 -> 46062 | C10: 13.00 - 13.30 | P10: =IFERROR(H10/Setup!$C$6,"") -> 0 | Q10: =IFERROR(H10-P10,"") -> 0
A11: =TEXT(Setup!$C$5+35,"dddd") -> Monday | B11: =Setup!$C$5+35 -> 46062 | C11: 13.30 - 14.00 | P11: =IFERROR(H11/Setup!$C$6,"") -> 0 | Q11: =IFERROR(H11-P11,"") -> 0
A12: =TEXT(Setup!$C$5+35,"dddd") -> Monday | B12: =Setup!$C$5+35 -> 46062 | C12: 14.00 - 14.30 | P12: =IFERROR(H12/Setup!$C$6,"") -> 0 | Q12: =IFERROR(H12-P12,"") -> 0
A13: =TEXT(Setup!$C$5+35,"dddd") -> Monday | B13: =Setup!$C$5+35 -> 46062 | C13: 14.30 - 15.00 | P13: =IFERROR(H13/Setup!$C$6,"") -> 0 | Q13: =IFERROR(H13-P13,"") -> 0
... A22: =TEXT(Setup!$C$5+35,"dddd") -> Monday | B22: =Setup!$C$5+35 -> 46062 | C22: ONLINE | P22: =IFERROR(H22/Setup!$C$6,"") -> 0 | Q22: =IFERROR(H22-P22,"") -> 0
A23: =TEXT(Setup!$C$5+35,"dddd") -> Monday | B23: =Setup!$C$5+35 -> 46062 | C23: TOTAL | D23: =SUM(D2:D22) -> 0 | E23: =SUM(E2:E22) -> 0 | F23: =SUM(F2:F22) -> 0 | G23: =SUM(G2:G22) -> 0 | H23: =SUM(H2:H22) -> 0 | I23: =IFERROR(E23/D23,"") | J23: =IFERROR(H23/E23,"") | K23: =SUM(K2:K22) -> 0 | M23: =SUM(M2:M22) -> 0 | N23: =IFERROR(H23-Wk5!H23,"") -> 0 | O23: =IFERROR(D23-Wk5!D23,"") -> 0 | P23: =SUM(P2:P22) -> 0 | Q23: =SUM(Q2:Q22) -> 0 | R23: =IFERROR(INDEX('Last Year'!$C$6:$C$369,MATCH(B23-364,'Last Year'!$B$6:$B$369,0)),"") -> 0 | S23: =IFERROR(H23/R23-1,"")
A24: =TEXT(Setup!$C$5+36,"dddd") -> Tuesday | B24: =Setup!$C$5+36 -> 46063 | C24: 9.00 - 9.30 | P24: =IFERROR(H24/Setup!$C$6,"") -> 0 | Q24: =IFERROR(H24-P24,"") -> 0
A25: =TEXT(Setup!$C$5+36,"dddd") -> Tuesday | B25: =Setup!$C$5+36 -> 46063 | C25: 9.30 - 10.00 | P25: =IFERROR(H25/Setup!$C$6,"") -> 0 | Q25: =IFERROR(H25-P25,"") -> 0
A26: =TEXT(Setup!$C$5+36,"dddd") -> Tuesday | B26: =Setup!$C$5+36 -> 46063 | C26: 10.00 - 10.30 | P26: =IFERROR(H26/Setup!$C$6,"") -> 0 | Q26: =IFERROR(H26-P26,"") -> 0
A27: =TEXT(Setup!$C$5+36,"dddd") -> Tuesday | B27: =Setup!$C$5+36 -> 46063 | C27: 10.30 - 11.00 | P27: =IFERROR(H27/Setup!$C$6,"") -> 0 | Q27: =IFERROR(H27-P27,"") -> 0
A28: =TEXT(Setup!$C$5+36,"dddd") -> Tuesday | B28: =Setup!$C$5+36 -> 46063 | C28: 11.00 - 11.30 | P28: =IFERROR(H28/Setup!$C$6,"") -> 0 | Q28: =IFERROR(H28-P28,"") -> 0
A29: =TEXT(Setup!$C$5+36,"dddd") -> Tuesday | B29: =Setup!$C$5+36 -> 46063 | C29: 11.30 - 12.00 | P29: =IFERROR(H29/Setup!$C$6,"") -> 0 | Q29: =IFERROR(H29-P29,"") -> 0
A30: =TEXT(Setup!$C$5+36,"dddd") -> Tuesday | B30: =Setup!$C$5+36 -> 46063 | C30: 12.00 - 12.30 | P30: =IFERROR(H30/Setup!$C$6,"") -> 0 | Q30: =IFERROR(H30-P30,"") -> 0
A31: =TEXT(Setup!$C$5+36,"dddd") -> Tuesday | B31: =Setup!$C$5+36 -> 46063 | C31: 12.30 - 13.00 | P31: =IFERROR(H31/Setup!$C$6,"") -> 0 | Q31: =IFERROR(H31-P31,"") -> 0
A32: =TEXT(Setup!$C$5+36,"dddd") -> Tuesday | B32: =Setup!$C$5+36 -> 46063 | C32: 13.00 - 13.30 | P32: =IFERROR(H32/Setup!$C$6,"") -> 0 | Q32: =IFERROR(H32-P32,"") -> 0
A33: =TEXT(Setup!$C$5+36,"dddd") -> Tuesday | B33: =Setup!$C$5+36 -> 46063 | C33: 13.30 - 14.00 | P33: =IFERROR(H33/Setup!$C$6,"") -> 0 | Q33: =IFERROR(H33-P33,"") -> 0
A34: =TEXT(Setup!$C$5+36,"dddd") -> Tuesday | B34: =Setup!$C$5+36 -> 46063 | C34: 14.00 - 14.30 | P34: =IFERROR(H34/Setup!$C$6,"") -> 0 | Q34: =IFERROR(H34-P34,"") -> 0
A35: =TEXT(Setup!$C$5+36,"dddd") -> Tuesday | B35: =Setup!$C$5+36 -> 46063 | C35: 14.30 - 15.00 | P35: =IFERROR(H35/Setup!$C$6,"") -> 0 | Q35: =IFERROR(H35-P35,"") -> 0
... A44: =TEXT(Setup!$C$5+36,"dddd") -> Tuesday | B44: =Setup!$C$5+36 -> 46063 | C44: ONLINE | P44: =IFERROR(H44/Setup!$C$6,"") -> 0 | Q44: =IFERROR(H44-P44,"") -> 0
A45: =TEXT(Setup!$C$5+36,"dddd") -> Tuesday | B45: =Setup!$C$5+36 -> 46063 | C45: TOTAL | D45: =SUM(D24:D44) -> 0 | E45: =SUM(E24:E44) -> 0 | F45: =SUM(F24:F44) -> 0 | G45: =SUM(G24:G44) -> 0 | H45: =SUM(H24:H44) -> 0 | I45: =IFERROR(E45/D45,"") | J45: =IFERROR(H45/E45,"") | K45: =SUM(K24:K44) -> 0 | M45: =SUM(M24:M44) -> 0 | N45: =IFERROR(H45-Wk5!H45,"") -> 0 | O45: =IFERROR(D45-Wk5!D45,"") -> 0 | P45: =SUM(P24:P44) -> 0 | Q45: =SUM(Q24:Q44) -> 0 | R45: =IFERROR(INDEX('Last Year'!$C$6:$C$369,MATCH(B45-364,'Last Year'!$B$6:$B$369,0)),"") -> 0 | S45: =IFERROR(H45/R45-1,"")
A46: =TEXT(Setup!$C$5+37,"dddd") -> Wednesday | B46: =Setup!$C$5+37 -> 46064 | C46: 9.00 - 9.30 | P46: =IFERROR(H46/Setup!$C$6,"") -> 0 | Q46: =IFERROR(H46-P46,"") -> 0
A47: =TEXT(Setup!$C$5+37,"dddd") -> Wednesday | B47: =Setup!$C$5+37 -> 46064 | C47: 9.30 - 10.00 | P47: =IFERROR(H47/Setup!$C$6,"") -> 0 | Q47: =IFERROR(H47-P47,"") -> 0
A48: =TEXT(Setup!$C$5+37,"dddd") -> Wednesday | B48: =Setup!$C$5+37 -> 46064 | C48: 10.00 - 10.30 | P48: =IFERROR(H48/Setup!$C$6,"") -> 0 | Q48: =IFERROR(H48-P48,"") -> 0
A49: =TEXT(Setup!$C$5+37,"dddd") -> Wednesday | B49: =Setup!$C$5+37 -> 46064 | C49: 10.30 - 11.00 | P49: =IFERROR(H49/Setup!$C$6,"") -> 0 | Q49: =IFERROR(H49-P49,"") -> 0
A50: =TEXT(Setup!$C$5+37,"dddd") -> Wednesday | B50: =Setup!$C$5+37 -> 46064 | C50: 11.00 - 11.30 | P50: =IFERROR(H50/Setup!$C$6,"") -> 0 | Q50: =IFERROR(H50-P50,"") -> 0
A51: =TEXT(Setup!$C$5+37,"dddd") -> Wednesday | B51: =Setup!$C$5+37 -> 46064 | C51: 11.30 - 12.00 | P51: =IFERROR(H51/Setup!$C$6,"") -> 0 | Q51: =IFERROR(H51-P51,"") -> 0
A52: =TEXT(Setup!$C$5+37,"dddd") -> Wednesday | B52: =Setup!$C$5+37 -> 46064 | C52: 12.00 - 12.30 | P52: =IFERROR(H52/Setup!$C$6,"") -> 0 | Q52: =IFERROR(H52-P52,"") -> 0
A53: =TEXT(Setup!$C$5+37,"dddd") -> Wednesday | B53: =Setup!$C$5+37 -> 46064 | C53: 12.30 - 13.00 | P53: =IFERROR(H53/Setup!$C$6,"") -> 0 | Q53: =IFERROR(H53-P53,"") -> 0
A54: =TEXT(Setup!$C$5+37,"dddd") -> Wednesday | B54: =Setup!$C$5+37 -> 46064 | C54: 13.00 - 13.30 | P54: =IFERROR(H54/Setup!$C$6,"") -> 0 | Q54: =IFERROR(H54-P54,"") -> 0
A55: =TEXT(Setup!$C$5+37,"dddd") -> Wednesday | B55: =Setup!$C$5+37 -> 46064 | C55: 13.30 - 14.00 | P55: =IFERROR(H55/Setup!$C$6,"") -> 0 | Q55: =IFERROR(H55-P55,"") -> 0
A56: =TEXT(Setup!$C$5+37,"dddd") -> Wednesday | B56: =Setup!$C$5+37 -> 46064 | C56: 14.00 - 14.30 | P56: =IFERROR(H56/Setup!$C$6,"") -> 0 | Q56: =IFERROR(H56-P56,"") -> 0
A57: =TEXT(Setup!$C$5+37,"dddd") -> Wednesday | B57: =Setup!$C$5+37 -> 46064 | C57: 14.30 - 15.00 | P57: =IFERROR(H57/Setup!$C$6,"") -> 0 | Q57: =IFERROR(H57-P57,"") -> 0
... A66: =TEXT(Setup!$C$5+37,"dddd") -> Wednesday | B66: =Setup!$C$5+37 -> 46064 | C66: ONLINE | P66: =IFERROR(H66/Setup!$C$6,"") -> 0 | Q66: =IFERROR(H66-P66,"") -> 0
A67: =TEXT(Setup!$C$5+37,"dddd") -> Wednesday | B67: =Setup!$C$5+37 -> 46064 | C67: TOTAL | D67: =SUM(D46:D66) -> 0 | E67: =SUM(E46:E66) -> 0 | F67: =SUM(F46:F66) -> 0 | G67: =SUM(G46:G66) -> 0 | H67: =SUM(H46:H66) -> 0 | I67: =IFERROR(E67/D67,"") | J67: =IFERROR(H67/E67,"") | K67: =SUM(K46:K66) -> 0 | M67: =SUM(M46:M66) -> 0 | N67: =IFERROR(H67-Wk5!H67,"") -> 0 | O67: =IFERROR(D67-Wk5!D67,"") -> 0 | P67: =SUM(P46:P66) -> 0 | Q67: =SUM(Q46:Q66) -> 0 | R67: =IFERROR(INDEX('Last Year'!$C$6:$C$369,MATCH(B67-364,'Last Year'!$B$6:$B$369,0)),"") -> 0 | S67: =IFERROR(H67/R67-1,"")
A68: =TEXT(Setup!$C$5+38,"dddd") -> Thursday | B68: =Setup!$C$5+38 -> 46065 | C68: 9.00 - 9.30 | P68: =IFERROR(H68/Setup!$C$6,"") -> 0 | Q68: =IFERROR(H68-P68,"") -> 0
A69: =TEXT(Setup!$C$5+38,"dddd") -> Thursday | B69: =Setup!$C$5+38 -> 46065 | C69: 9.30 - 10.00 | P69: =IFERROR(H69/Setup!$C$6,"") -> 0 | Q69: =IFERROR(H69-P69,"") -> 0
A70: =TEXT(Setup!$C$5+38,"dddd") -> Thursday | B70: =Setup!$C$5+38 -> 46065 | C70: 10.00 - 10.30 | P70: =IFERROR(H70/Setup!$C$6,"") -> 0 | Q70: =IFERROR(H70-P70,"") -> 0
A71: =TEXT(Setup!$C$5+38,"dddd") -> Thursday | B71: =Setup!$C$5+38 -> 46065 | C71: 10.30 - 11.00 | P71: =IFERROR(H71/Setup!$C$6,"") -> 0 | Q71: =IFERROR(H71-P71,"") -> 0
A72: =TEXT(Setup!$C$5+38,"dddd") -> Thursday | B72: =Setup!$C$5+38 -> 46065 | C72: 11.00 - 11.30 | P72: =IFERROR(H72/Setup!$C$6,"") -> 0 | Q72: =IFERROR(H72-P72,"") -> 0
A73: =TEXT(Setup!$C$5+38,"dddd") -> Thursday | B73: =Setup!$C$5+38 -> 46065 | C73: 11.30 - 12.00 | P73: =IFERROR(H73/Setup!$C$6,"") -> 0 | Q73: =IFERROR(H73-P73,"") -> 0
A74: =TEXT(Setup!$C$5+38,"dddd") -> Thursday | B74: =Setup!$C$5+38 -> 46065 | C74: 12.00 - 12.30 | P74: =IFERROR(H74/Setup!$C$6,"") -> 0 | Q74: =IFERROR(H74-P74,"") -> 0
A75: =TEXT(Setup!$C$5+38,"dddd") -> Thursday | B75: =Setup!$C$5+38 -> 46065 | C75: 12.30 - 13.00 | P75: =IFERROR(H75/Setup!$C$6,"") -> 0 | Q75: =IFERROR(H75-P75,"") -> 0
A76: =TEXT(Setup!$C$5+38,"dddd") -> Thursday | B76: =Setup!$C$5+38 -> 46065 | C76: 13.00 - 13.30 | P76: =IFERROR(H76/Setup!$C$6,"") -> 0 | Q76: =IFERROR(H76-P76,"") -> 0
A77: =TEXT(Setup!$C$5+38,"dddd") -> Thursday | B77: =Setup!$C$5+38 -> 46065 | C77: 13.30 - 14.00 | P77: =IFERROR(H77/Setup!$C$6,"") -> 0 | Q77: =IFERROR(H77-P77,"") -> 0
A78: =TEXT(Setup!$C$5+38,"dddd") -> Thursday | B78: =Setup!$C$5+38 -> 46065 | C78: 14.00 - 14.30 | P78: =IFERROR(H78/Setup!$C$6,"") -> 0 | Q78: =IFERROR(H78-P78,"") -> 0
A79: =TEXT(Setup!$C$5+38,"dddd") -> Thursday | B79: =Setup!$C$5+38 -> 46065 | C79: 14.30 - 15.00 | P79: =IFERROR(H79/Setup!$C$6,"") -> 0 | Q79: =IFERROR(H79-P79,"") -> 0
... A88: =TEXT(Setup!$C$5+38,"dddd") -> Thursday | B88: =Setup!$C$5+38 -> 46065 | C88: ONLINE | P88: =IFERROR(H88/Setup!$C$6,"") -> 0 | Q88: =IFERROR(H88-P88,"") -> 0
A89: =TEXT(Setup!$C$5+38,"dddd") -> Thursday | B89: =Setup!$C$5+38 -> 46065 | C89: TOTAL | D89: =SUM(D68:D88) -> 0 | E89: =SUM(E68:E88) -> 0 | F89: =SUM(F68:F88) -> 0 | G89: =SUM(G68:G88) -> 0 | H89: =SUM(H68:H88) -> 0 | I89: =IFERROR(E89/D89,"") | J89: =IFERROR(H89/E89,"") | K89: =SUM(K68:K88) -> 0 | M89: =SUM(M68:M88) -> 0 | N89: =IFERROR(H89-Wk5!H89,"") -> 0 | O89: =IFERROR(D89-Wk5!D89,"") -> 0 | P89: =SUM(P68:P88) -> 0 | Q89: =SUM(Q68:Q88) -> 0 | R89: =IFERROR(INDEX('Last Year'!$C$6:$C$369,MATCH(B89-364,'Last Year'!$B$6:$B$369,0)),"") -> 0 | S89: =IFERROR(H89/R89-1,"")
A90: =TEXT(Setup!$C$5+39,"dddd") -> Friday | B90: =Setup!$C$5+39 -> 46066 | C90: 9.00 - 9.30 | P90: =IFERROR(H90/Setup!$C$6,"") -> 0 | Q90: =IFERROR(H90-P90,"") -> 0
A91: =TEXT(Setup!$C$5+39,"dddd") -> Friday | B91: =Setup!$C$5+39 -> 46066 | C91: 9.30 - 10.00 | P91: =IFERROR(H91/Setup!$C$6,"") -> 0 | Q91: =IFERROR(H91-P91,"") -> 0
A92: =TEXT(Setup!$C$5+39,"dddd") -> Friday | B92: =Setup!$C$5+39 -> 46066 | C92: 10.00 - 10.30 | P92: =IFERROR(H92/Setup!$C$6,"") -> 0 | Q92: =IFERROR(H92-P92,"") -> 0
A93: =TEXT(Setup!$C$5+39,"dddd") -> Friday | B93: =Setup!$C$5+39 -> 46066 | C93: 10.30 - 11.00 | P93: =IFERROR(H93/Setup!$C$6,"") -> 0 | Q93: =IFERROR(H93-P93,"") -> 0
A94: =TEXT(Setup!$C$5+39,"dddd") -> Friday | B94: =Setup!$C$5+39 -> 46066 | C94: 11.00 - 11.30 | P94: =IFERROR(H94/Setup!$C$6,"") -> 0 | Q94: =IFERROR(H94-P94,"") -> 0
A95: =TEXT(Setup!$C$5+39,"dddd") -> Friday | B95: =Setup!$C$5+39 -> 46066 | C95: 11.30 - 12.00 | P95: =IFERROR(H95/Setup!$C$6,"") -> 0 | Q95: =IFERROR(H95-P95,"") -> 0
A96: =TEXT(Setup!$C$5+39,"dddd") -> Friday | B96: =Setup!$C$5+39 -> 46066 | C96: 12.00 - 12.30 | P96: =IFERROR(H96/Setup!$C$6,"") -> 0 | Q96: =IFERROR(H96-P96,"") -> 0
A97: =TEXT(Setup!$C$5+39,"dddd") -> Friday | B97: =Setup!$C$5+39 -> 46066 | C97: 12.30 - 13.00 | P97: =IFERROR(H97/Setup!$C$6,"") -> 0 | Q97: =IFERROR(H97-P97,"") -> 0
A98: =TEXT(Setup!$C$5+39,"dddd") -> Friday | B98: =Setup!$C$5+39 -> 46066 | C98: 13.00 - 13.30 | P98: =IFERROR(H98/Setup!$C$6,"") -> 0 | Q98: =IFERROR(H98-P98,"") -> 0
A99: =TEXT(Setup!$C$5+39,"dddd") -> Friday | B99: =Setup!$C$5+39 -> 46066 | C99: 13.30 - 14.00 | P99: =IFERROR(H99/Setup!$C$6,"") -> 0 | Q99: =IFERROR(H99-P99,"") -> 0
A100: =TEXT(Setup!$C$5+39,"dddd") -> Friday | B100: =Setup!$C$5+39 -> 46066 | C100: 14.00 - 14.30 | P100: =IFERROR(H100/Setup!$C$6,"") -> 0 | Q100: =IFERROR(H100-P100,"") -> 0
A101: =TEXT(Setup!$C$5+39,"dddd") -> Friday | B101: =Setup!$C$5+39 -> 46066 | C101: 14.30 - 15.00 | P101: =IFERROR(H101/Setup!$C$6,"") -> 0 | Q101: =IFERROR(H101-P101,"") -> 0
... A110: =TEXT(Setup!$C$5+39,"dddd") -> Friday | B110: =Setup!$C$5+39 -> 46066 | C110: ONLINE | P110: =IFERROR(H110/Setup!$C$6,"") -> 0 | Q110: =IFERROR(H110-P110,"") -> 0
A111: =TEXT(Setup!$C$5+39,"dddd") -> Friday | B111: =Setup!$C$5+39 -> 46066 | C111: TOTAL | D111: =SUM(D90:D110) -> 0 | E111: =SUM(E90:E110) -> 0 | F111: =SUM(F90:F110) -> 0 | G111: =SUM(G90:G110) -> 0 | H111: =SUM(H90:H110) -> 0 | I111: =IFERROR(E111/D111,"") | J111: =IFERROR(H111/E111,"") | K111: =SUM(K90:K110) -> 0 | M111: =SUM(M90:M110) -> 0 | N111: =IFERROR(H111-Wk5!H111,"") -> 0 | O111: =IFERROR(D111-Wk5!D111,"") -> 0 | P111: =SUM(P90:P110) -> 0 | Q111: =SUM(Q90:Q110) -> 0 | R111: =IFERROR(INDEX('Last Year'!$C$6:$C$369,MATCH(B111-364,'Last Year'!$B$6:$B$369,0)),"") -> 0 | S111: =IFERROR(H111/R111-1,"")
A112: =TEXT(Setup!$C$5+40,"dddd") -> Saturday | B112: =Setup!$C$5+40 -> 46067 | C112: 9.00 - 9.30 | P112: =IFERROR(H112/Setup!$C$6,"") -> 0 | Q112: =IFERROR(H112-P112,"") -> 0
A113: =TEXT(Setup!$C$5+40,"dddd") -> Saturday | B113: =Setup!$C$5+40 -> 46067 | C113: 9.30 - 10.00 | P113: =IFERROR(H113/Setup!$C$6,"") -> 0 | Q113: =IFERROR(H113-P113,"") -> 0
A114: =TEXT(Setup!$C$5+40,"dddd") -> Saturday | B114: =Setup!$C$5+40 -> 46067 | C114: 10.00 - 10.30 | P114: =IFERROR(H114/Setup!$C$6,"") -> 0 | Q114: =IFERROR(H114-P114,"") -> 0
A115: =TEXT(Setup!$C$5+40,"dddd") -> Saturday | B115: =Setup!$C$5+40 -> 46067 | C115: 10.30 - 11.00 | P115: =IFERROR(H115/Setup!$C$6,"") -> 0 | Q115: =IFERROR(H115-P115,"") -> 0
A116: =TEXT(Setup!$C$5+40,"dddd") -> Saturday | B116: =Setup!$C$5+40 -> 46067 | C116: 11.00 - 11.30 | P116: =IFERROR(H116/Setup!$C$6,"") -> 0 | Q116: =IFERROR(H116-P116,"") -> 0
A117: =TEXT(Setup!$C$5+40,"dddd") -> Saturday | B117: =Setup!$C$5+40 -> 46067 | C117: 11.30 - 12.00 | P117: =IFERROR(H117/Setup!$C$6,"") -> 0 | Q117: =IFERROR(H117-P117,"") -> 0
A118: =TEXT(Setup!$C$5+40,"dddd") -> Saturday | B118: =Setup!$C$5+40 -> 46067 | C118: 12.00 - 12.30 | P118: =IFERROR(H118/Setup!$C$6,"") -> 0 | Q118: =IFERROR(H118-P118,"") -> 0
A119: =TEXT(Setup!$C$5+40,"dddd") -> Saturday | B119: =Setup!$C$5+40 -> 46067 | C119: 12.30 - 13.00 | P119: =IFERROR(H119/Setup!$C$6,"") -> 0 | Q119: =IFERROR(H119-P119,"") -> 0
A120: =TEXT(Setup!$C$5+40,"dddd") -> Saturday | B120: =Setup!$C$5+40 -> 46067 | C120: 13.00 - 13.30 | P120: =IFERROR(H120/Setup!$C$6,"") -> 0 | Q120: =IFERROR(H120-P120,"") -> 0
A121: =TEXT(Setup!$C$5+40,"dddd") -> Saturday | B121: =Setup!$C$5+40 -> 46067 | C121: 13.30 - 14.00 | P121: =IFERROR(H121/Setup!$C$6,"") -> 0 | Q121: =IFERROR(H121-P121,"") -> 0
A122: =TEXT(Setup!$C$5+40,"dddd") -> Saturday | B122: =Setup!$C$5+40 -> 46067 | C122: 14.00 - 14.30 | P122: =IFERROR(H122/Setup!$C$6,"") -> 0 | Q122: =IFERROR(H122-P122,"") -> 0
A123: =TEXT(Setup!$C$5+40,"dddd") -> Saturday | B123: =Setup!$C$5+40 -> 46067 | C123: 14.30 - 15.00 | P123: =IFERROR(H123/Setup!$C$6,"") -> 0 | Q123: =IFERROR(H123-P123,"") -> 0
... A132: =TEXT(Setup!$C$5+40,"dddd") -> Saturday | B132: =Setup!$C$5+40 -> 46067 | C132: ONLINE | P132: =IFERROR(H132/Setup!$C$6,"") -> 0 | Q132: =IFERROR(H132-P132,"") -> 0
A133: =TEXT(Setup!$C$5+40,"dddd") -> Saturday | B133: =Setup!$C$5+40 -> 46067 | C133: TOTAL | D133: =SUM(D112:D132) -> 0 | E133: =SUM(E112:E132) -> 0 | F133: =SUM(F112:F132) -> 0 | G133: =SUM(G112:G132) -> 0 | H133: =SUM(H112:H132) -> 0 | I133: =IFERROR(E133/D133,"") | J133: =IFERROR(H133/E133,"") | K133: =SUM(K112:K132) -> 0 | M133: =SUM(M112:M132) -> 0 | N133: =IFERROR(H133-Wk5!H133,"") -> 0 | O133: =IFERROR(D133-Wk5!D133,"") -> 0 | P133: =SUM(P112:P132) -> 0 | Q133: =SUM(Q112:Q132) -> 0 | R133: =IFERROR(INDEX('Last Year'!$C$6:$C$369,MATCH(B133-364,'Last Year'!$B$6:$B$369,0)),"") -> 0 | S133: =IFERROR(H133/R133-1,"")
A134: =TEXT(Setup!$C$5+41,"dddd") -> Sunday | B134: =Setup!$C$5+41 -> 46068 | C134: 9.00 - 9.30 | P134: =IFERROR(H134/Setup!$C$6,"") -> 0 | Q134: =IFERROR(H134-P134,"") -> 0
A135: =TEXT(Setup!$C$5+41,"dddd") -> Sunday | B135: =Setup!$C$5+41 -> 46068 | C135: 9.30 - 10.00 | P135: =IFERROR(H135/Setup!$C$6,"") -> 0 | Q135: =IFERROR(H135-P135,"") -> 0
A136: =TEXT(Setup!$C$5+41,"dddd") -> Sunday | B136: =Setup!$C$5+41 -> 46068 | C136: 10.00 - 10.30 | P136: =IFERROR(H136/Setup!$C$6,"") -> 0 | Q136: =IFERROR(H136-P136,"") -> 0
A137: =TEXT(Setup!$C$5+41,"dddd") -> Sunday | B137: =Setup!$C$5+41 -> 46068 | C137: 10.30 - 11.00 | P137: =IFERROR(H137/Setup!$C$6,"") -> 0 | Q137: =IFERROR(H137-P137,"") -> 0
A138: =TEXT(Setup!$C$5+41,"dddd") -> Sunday | B138: =Setup!$C$5+41 -> 46068 | C138: 11.00 - 11.30 | P138: =IFERROR(H138/Setup!$C$6,"") -> 0 | Q138: =IFERROR(H138-P138,"") -> 0
A139: =TEXT(Setup!$C$5+41,"dddd") -> Sunday | B139: =Setup!$C$5+41 -> 46068 | C139: 11.30 - 12.00 | P139: =IFERROR(H139/Setup!$C$6,"") -> 0 | Q139: =IFERROR(H139-P139,"") -> 0
A140: =TEXT(Setup!$C$5+41,"dddd") -> Sunday | B140: =Setup!$C$5+41 -> 46068 | C140: 12.00 - 12.30 | P140: =IFERROR(H140/Setup!$C$6,"") -> 0 | Q140: =IFERROR(H140-P140,"") -> 0
A141: =TEXT(Setup!$C$5+41,"dddd") -> Sunday | B141: =Setup!$C$5+41 -> 46068 | C141: 12.30 - 13.00 | P141: =IFERROR(H141/Setup!$C$6,"") -> 0 | Q141: =IFERROR(H141-P141,"") -> 0
A142: =TEXT(Setup!$C$5+41,"dddd") -> Sunday | B142: =Setup!$C$5+41 -> 46068 | C142: 13.00 - 13.30 | P142: =IFERROR(H142/Setup!$C$6,"") -> 0 | Q142: =IFERROR(H142-P142,"") -> 0
A143: =TEXT(Setup!$C$5+41,"dddd") -> Sunday | B143: =Setup!$C$5+41 -> 46068 | C143: 13.30 - 14.00 | P143: =IFERROR(H143/Setup!$C$6,"") -> 0 | Q143: =IFERROR(H143-P143,"") -> 0
A144: =TEXT(Setup!$C$5+41,"dddd") -> Sunday | B144: =Setup!$C$5+41 -> 46068 | C144: 14.00 - 14.30 | P144: =IFERROR(H144/Setup!$C$6,"") -> 0 | Q144: =IFERROR(H144-P144,"") -> 0
A145: =TEXT(Setup!$C$5+41,"dddd") -> Sunday | B145: =Setup!$C$5+41 -> 46068 | C145: 14.30 - 15.00 | P145: =IFERROR(H145/Setup!$C$6,"") -> 0 | Q145: =IFERROR(H145-P145,"") -> 0
... A154: =TEXT(Setup!$C$5+41,"dddd") -> Sunday | B154: =Setup!$C$5+41 -> 46068 | C154: ONLINE | P154: =IFERROR(H154/Setup!$C$6,"") -> 0 | Q154: =IFERROR(H154-P154,"") -> 0
A155: =TEXT(Setup!$C$5+41,"dddd") -> Sunday | B155: =Setup!$C$5+41 -> 46068 | C155: TOTAL | D155: =SUM(D134:D154) -> 0 | E155: =SUM(E134:E154) -> 0 | F155: =SUM(F134:F154) -> 0 | G155: =SUM(G134:G154) -> 0 | H155: =SUM(H134:H154) -> 0 | I155: =IFERROR(E155/D155,"") | J155: =IFERROR(H155/E155,"") | K155: =SUM(K134:K154) -> 0 | M155: =SUM(M134:M154) -> 0 | N155: =IFERROR(H155-Wk5!H155,"") -> 0 | O155: =IFERROR(D155-Wk5!D155,"") -> 0 | P155: =SUM(P134:P154) -> 0 | Q155: =SUM(Q134:Q154) -> 0 | R155: =IFERROR(INDEX('Last Year'!$C$6:$C$369,MATCH(B155-364,'Last Year'!$B$6:$B$369,0)),"") -> 0 | S155: =IFERROR(H155/R155-1,"")
C156: FULL WEEK | D156: =D23+D45+D67+D89+D111+D133+D155 -> 0 | E156: =E23+E45+E67+E89+E111+E133+E155 -> 0 | F156: =F23+F45+F67+F89+F111+F133+F155 -> 0 | G156: =G23+G45+G67+G89+G111+G133+G155 -> 0 | H156: =H23+H45+H67+H89+H111+H133+H155 -> 0 | I156: =IFERROR(E156/D156,"") | J156: =IFERROR(H156/E156,"") | K156: =K23+K45+K67+K89+K111+K133+K155 -> 0 | M156: =M23+M45+M67+M89+M111+M133+M155 -> 0 | P156: =P23+P45+P67+P89+P111+P133+P155 -> 0 | Q156: =Q23+Q45+Q67+Q89+Q111+Q133+Q155 -> 0 | R156: =R23+R45+R67+R89+R111+R133+R155 -> 0 | S156: =IFERROR(H156/R156-1,"")
...

Sheet Wk7
A1: Day | B1: Date | C1: Time | D1: Customers In | E1: Sales | F1: Vouchers Used | G1: Walk In/Out | H1: Sale Amount | I1: Conversion | J1: Avg Sale | K1: Tracked Category | L1: Notes | M1: Cash | N1: vs Last Wk € | O1: vs Last Wk Cust | P1: Est. Cost | Q1: Est. Profit | R1: Last Year Day | S1: vs Last Year
A2: =TEXT(Setup!$C$5+42,"dddd") -> Monday | B2: =Setup!$C$5+42 -> 46069 | C2: 9.00 - 9.30 | P2: =IFERROR(H2/Setup!$C$6,"") -> 0 | Q2: =IFERROR(H2-P2,"") -> 0
A3: =TEXT(Setup!$C$5+42,"dddd") -> Monday | B3: =Setup!$C$5+42 -> 46069 | C3: 9.30 - 10.00 | P3: =IFERROR(H3/Setup!$C$6,"") -> 0 | Q3: =IFERROR(H3-P3,"") -> 0
A4: =TEXT(Setup!$C$5+42,"dddd") -> Monday | B4: =Setup!$C$5+42 -> 46069 | C4: 10.00 - 10.30 | P4: =IFERROR(H4/Setup!$C$6,"") -> 0 | Q4: =IFERROR(H4-P4,"") -> 0
A5: =TEXT(Setup!$C$5+42,"dddd") -> Monday | B5: =Setup!$C$5+42 -> 46069 | C5: 10.30 - 11.00 | P5: =IFERROR(H5/Setup!$C$6,"") -> 0 | Q5: =IFERROR(H5-P5,"") -> 0
A6: =TEXT(Setup!$C$5+42,"dddd") -> Monday | B6: =Setup!$C$5+42 -> 46069 | C6: 11.00 - 11.30 | P6: =IFERROR(H6/Setup!$C$6,"") -> 0 | Q6: =IFERROR(H6-P6,"") -> 0
A7: =TEXT(Setup!$C$5+42,"dddd") -> Monday | B7: =Setup!$C$5+42 -> 46069 | C7: 11.30 - 12.00 | P7: =IFERROR(H7/Setup!$C$6,"") -> 0 | Q7: =IFERROR(H7-P7,"") -> 0
A8: =TEXT(Setup!$C$5+42,"dddd") -> Monday | B8: =Setup!$C$5+42 -> 46069 | C8: 12.00 - 12.30 | P8: =IFERROR(H8/Setup!$C$6,"") -> 0 | Q8: =IFERROR(H8-P8,"") -> 0
A9: =TEXT(Setup!$C$5+42,"dddd") -> Monday | B9: =Setup!$C$5+42 -> 46069 | C9: 12.30 - 13.00 | P9: =IFERROR(H9/Setup!$C$6,"") -> 0 | Q9: =IFERROR(H9-P9,"") -> 0
A10: =TEXT(Setup!$C$5+42,"dddd") -> Monday | B10: =Setup!$C$5+42 -> 46069 | C10: 13.00 - 13.30 | P10: =IFERROR(H10/Setup!$C$6,"") -> 0 | Q10: =IFERROR(H10-P10,"") -> 0
A11: =TEXT(Setup!$C$5+42,"dddd") -> Monday | B11: =Setup!$C$5+42 -> 46069 | C11: 13.30 - 14.00 | P11: =IFERROR(H11/Setup!$C$6,"") -> 0 | Q11: =IFERROR(H11-P11,"") -> 0
A12: =TEXT(Setup!$C$5+42,"dddd") -> Monday | B12: =Setup!$C$5+42 -> 46069 | C12: 14.00 - 14.30 | P12: =IFERROR(H12/Setup!$C$6,"") -> 0 | Q12: =IFERROR(H12-P12,"") -> 0
A13: =TEXT(Setup!$C$5+42,"dddd") -> Monday | B13: =Setup!$C$5+42 -> 46069 | C13: 14.30 - 15.00 | P13: =IFERROR(H13/Setup!$C$6,"") -> 0 | Q13: =IFERROR(H13-P13,"") -> 0
... A22: =TEXT(Setup!$C$5+42,"dddd") -> Monday | B22: =Setup!$C$5+42 -> 46069 | C22: ONLINE | P22: =IFERROR(H22/Setup!$C$6,"") -> 0 | Q22: =IFERROR(H22-P22,"") -> 0
A23: =TEXT(Setup!$C$5+42,"dddd") -> Monday | B23: =Setup!$C$5+42 -> 46069 | C23: TOTAL | D23: =SUM(D2:D22) -> 0 | E23: =SUM(E2:E22) -> 0 | F23: =SUM(F2:F22) -> 0 | G23: =SUM(G2:G22) -> 0 | H23: =SUM(H2:H22) -> 0 | I23: =IFERROR(E23/D23,"") | J23: =IFERROR(H23/E23,"") | K23: =SUM(K2:K22) -> 0 | M23: =SUM(M2:M22) -> 0 | N23: =IFERROR(H23-Wk6!H23,"") -> 0 | O23: =IFERROR(D23-Wk6!D23,"") -> 0 | P23: =SUM(P2:P22) -> 0 | Q23: =SUM(Q2:Q22) -> 0 | R23: =IFERROR(INDEX('Last Year'!$C$6:$C$369,MATCH(B23-364,'Last Year'!$B$6:$B$369,0)),"") -> 0 | S23: =IFERROR(H23/R23-1,"")
A24: =TEXT(Setup!$C$5+43,"dddd") -> Tuesday | B24: =Setup!$C$5+43 -> 46070 | C24: 9.00 - 9.30 | P24: =IFERROR(H24/Setup!$C$6,"") -> 0 | Q24: =IFERROR(H24-P24,"") -> 0
A25: =TEXT(Setup!$C$5+43,"dddd") -> Tuesday | B25: =Setup!$C$5+43 -> 46070 | C25: 9.30 - 10.00 | P25: =IFERROR(H25/Setup!$C$6,"") -> 0 | Q25: =IFERROR(H25-P25,"") -> 0
A26: =TEXT(Setup!$C$5+43,"dddd") -> Tuesday | B26: =Setup!$C$5+43 -> 46070 | C26: 10.00 - 10.30 | P26: =IFERROR(H26/Setup!$C$6,"") -> 0 | Q26: =IFERROR(H26-P26,"") -> 0
A27: =TEXT(Setup!$C$5+43,"dddd") -> Tuesday | B27: =Setup!$C$5+43 -> 46070 | C27: 10.30 - 11.00 | P27: =IFERROR(H27/Setup!$C$6,"") -> 0 | Q27: =IFERROR(H27-P27,"") -> 0
A28: =TEXT(Setup!$C$5+43,"dddd") -> Tuesday | B28: =Setup!$C$5+43 -> 46070 | C28: 11.00 - 11.30 | P28: =IFERROR(H28/Setup!$C$6,"") -> 0 | Q28: =IFERROR(H28-P28,"") -> 0
A29: =TEXT(Setup!$C$5+43,"dddd") -> Tuesday | B29: =Setup!$C$5+43 -> 46070 | C29: 11.30 - 12.00 | P29: =IFERROR(H29/Setup!$C$6,"") -> 0 | Q29: =IFERROR(H29-P29,"") -> 0
A30: =TEXT(Setup!$C$5+43,"dddd") -> Tuesday | B30: =Setup!$C$5+43 -> 46070 | C30: 12.00 - 12.30 | P30: =IFERROR(H30/Setup!$C$6,"") -> 0 | Q30: =IFERROR(H30-P30,"") -> 0
A31: =TEXT(Setup!$C$5+43,"dddd") -> Tuesday | B31: =Setup!$C$5+43 -> 46070 | C31: 12.30 - 13.00 | P31: =IFERROR(H31/Setup!$C$6,"") -> 0 | Q31: =IFERROR(H31-P31,"") -> 0
A32: =TEXT(Setup!$C$5+43,"dddd") -> Tuesday | B32: =Setup!$C$5+43 -> 46070 | C32: 13.00 - 13.30 | P32: =IFERROR(H32/Setup!$C$6,"") -> 0 | Q32: =IFERROR(H32-P32,"") -> 0
A33: =TEXT(Setup!$C$5+43,"dddd") -> Tuesday | B33: =Setup!$C$5+43 -> 46070 | C33: 13.30 - 14.00 | P33: =IFERROR(H33/Setup!$C$6,"") -> 0 | Q33: =IFERROR(H33-P33,"") -> 0
A34: =TEXT(Setup!$C$5+43,"dddd") -> Tuesday | B34: =Setup!$C$5+43 -> 46070 | C34: 14.00 - 14.30 | P34: =IFERROR(H34/Setup!$C$6,"") -> 0 | Q34: =IFERROR(H34-P34,"") -> 0
A35: =TEXT(Setup!$C$5+43,"dddd") -> Tuesday | B35: =Setup!$C$5+43 -> 46070 | C35: 14.30 - 15.00 | P35: =IFERROR(H35/Setup!$C$6,"") -> 0 | Q35: =IFERROR(H35-P35,"") -> 0
... A44: =TEXT(Setup!$C$5+43,"dddd") -> Tuesday | B44: =Setup!$C$5+43 -> 46070 | C44: ONLINE | P44: =IFERROR(H44/Setup!$C$6,"") -> 0 | Q44: =IFERROR(H44-P44,"") -> 0
A45: =TEXT(Setup!$C$5+43,"dddd") -> Tuesday | B45: =Setup!$C$5+43 -> 46070 | C45: TOTAL | D45: =SUM(D24:D44) -> 0 | E45: =SUM(E24:E44) -> 0 | F45: =SUM(F24:F44) -> 0 | G45: =SUM(G24:G44) -> 0 | H45: =SUM(H24:H44) -> 0 | I45: =IFERROR(E45/D45,"") | J45: =IFERROR(H45/E45,"") | K45: =SUM(K24:K44) -> 0 | M45: =SUM(M24:M44) -> 0 | N45: =IFERROR(H45-Wk6!H45,"") -> 0 | O45: =IFERROR(D45-Wk6!D45,"") -> 0 | P45: =SUM(P24:P44) -> 0 | Q45: =SUM(Q24:Q44) -> 0 | R45: =IFERROR(INDEX('Last Year'!$C$6:$C$369,MATCH(B45-364,'Last Year'!$B$6:$B$369,0)),"") -> 0 | S45: =IFERROR(H45/R45-1,"")
A46: =TEXT(Setup!$C$5+44,"dddd") -> Wednesday | B46: =Setup!$C$5+44 -> 46071 | C46: 9.00 - 9.30 | P46: =IFERROR(H46/Setup!$C$6,"") -> 0 | Q46: =IFERROR(H46-P46,"") -> 0
A47: =TEXT(Setup!$C$5+44,"dddd") -> Wednesday | B47: =Setup!$C$5+44 -> 46071 | C47: 9.30 - 10.00 | P47: =IFERROR(H47/Setup!$C$6,"") -> 0 | Q47: =IFERROR(H47-P47,"") -> 0
A48: =TEXT(Setup!$C$5+44,"dddd") -> Wednesday | B48: =Setup!$C$5+44 -> 46071 | C48: 10.00 - 10.30 | P48: =IFERROR(H48/Setup!$C$6,"") -> 0 | Q48: =IFERROR(H48-P48,"") -> 0
A49: =TEXT(Setup!$C$5+44,"dddd") -> Wednesday | B49: =Setup!$C$5+44 -> 46071 | C49: 10.30 - 11.00 | P49: =IFERROR(H49/Setup!$C$6,"") -> 0 | Q49: =IFERROR(H49-P49,"") -> 0
A50: =TEXT(Setup!$C$5+44,"dddd") -> Wednesday | B50: =Setup!$C$5+44 -> 46071 | C50: 11.00 - 11.30 | P50: =IFERROR(H50/Setup!$C$6,"") -> 0 | Q50: =IFERROR(H50-P50,"") -> 0
A51: =TEXT(Setup!$C$5+44,"dddd") -> Wednesday | B51: =Setup!$C$5+44 -> 46071 | C51: 11.30 - 12.00 | P51: =IFERROR(H51/Setup!$C$6,"") -> 0 | Q51: =IFERROR(H51-P51,"") -> 0
A52: =TEXT(Setup!$C$5+44,"dddd") -> Wednesday | B52: =Setup!$C$5+44 -> 46071 | C52: 12.00 - 12.30 | P52: =IFERROR(H52/Setup!$C$6,"") -> 0 | Q52: =IFERROR(H52-P52,"") -> 0
A53: =TEXT(Setup!$C$5+44,"dddd") -> Wednesday | B53: =Setup!$C$5+44 -> 46071 | C53: 12.30 - 13.00 | P53: =IFERROR(H53/Setup!$C$6,"") -> 0 | Q53: =IFERROR(H53-P53,"") -> 0
A54: =TEXT(Setup!$C$5+44,"dddd") -> Wednesday | B54: =Setup!$C$5+44 -> 46071 | C54: 13.00 - 13.30 | P54: =IFERROR(H54/Setup!$C$6,"") -> 0 | Q54: =IFERROR(H54-P54,"") -> 0
A55: =TEXT(Setup!$C$5+44,"dddd") -> Wednesday | B55: =Setup!$C$5+44 -> 46071 | C55: 13.30 - 14.00 | P55: =IFERROR(H55/Setup!$C$6,"") -> 0 | Q55: =IFERROR(H55-P55,"") -> 0
A56: =TEXT(Setup!$C$5+44,"dddd") -> Wednesday | B56: =Setup!$C$5+44 -> 46071 | C56: 14.00 - 14.30 | P56: =IFERROR(H56/Setup!$C$6,"") -> 0 | Q56: =IFERROR(H56-P56,"") -> 0
A57: =TEXT(Setup!$C$5+44,"dddd") -> Wednesday | B57: =Setup!$C$5+44 -> 46071 | C57: 14.30 - 15.00 | P57: =IFERROR(H57/Setup!$C$6,"") -> 0 | Q57: =IFERROR(H57-P57,"") -> 0
... A66: =TEXT(Setup!$C$5+44,"dddd") -> Wednesday | B66: =Setup!$C$5+44 -> 46071 | C66: ONLINE | P66: =IFERROR(H66/Setup!$C$6,"") -> 0 | Q66: =IFERROR(H66-P66,"") -> 0
A67: =TEXT(Setup!$C$5+44,"dddd") -> Wednesday | B67: =Setup!$C$5+44 -> 46071 | C67: TOTAL | D67: =SUM(D46:D66) -> 0 | E67: =SUM(E46:E66) -> 0 | F67: =SUM(F46:F66) -> 0 | G67: =SUM(G46:G66) -> 0 | H67: =SUM(H46:H66) -> 0 | I67: =IFERROR(E67/D67,"") | J67: =IFERROR(H67/E67,"") | K67: =SUM(K46:K66) -> 0 | M67: =SUM(M46:M66) -> 0 | N67: =IFERROR(H67-Wk6!H67,"") -> 0 | O67: =IFERROR(D67-Wk6!D67,"") -> 0 | P67: =SUM(P46:P66) -> 0 | Q67: =SUM(Q46:Q66) -> 0 | R67: =IFERROR(INDEX('Last Year'!$C$6:$C$369,MATCH(B67-364,'Last Year'!$B$6:$B$369,0)),"") -> 0 | S67: =IFERROR(H67/R67-1,"")
A68: =TEXT(Setup!$C$5+45,"dddd") -> Thursday | B68: =Setup!$C$5+45 -> 46072 | C68: 9.00 - 9.30 | P68: =IFERROR(H68/Setup!$C$6,"") -> 0 | Q68: =IFERROR(H68-P68,"") -> 0
A69: =TEXT(Setup!$C$5+45,"dddd") -> Thursday | B69: =Setup!$C$5+45 -> 46072 | C69: 9.30 - 10.00 | P69: =IFERROR(H69/Setup!$C$6,"") -> 0 | Q69: =IFERROR(H69-P69,"") -> 0
A70: =TEXT(Setup!$C$5+45,"dddd") -> Thursday | B70: =Setup!$C$5+45 -> 46072 | C70: 10.00 - 10.30 | P70: =IFERROR(H70/Setup!$C$6,"") -> 0 | Q70: =IFERROR(H70-P70,"") -> 0
A71: =TEXT(Setup!$C$5+45,"dddd") -> Thursday | B71: =Setup!$C$5+45 -> 46072 | C71: 10.30 - 11.00 | P71: =IFERROR(H71/Setup!$C$6,"") -> 0 | Q71: =IFERROR(H71-P71,"") -> 0
A72: =TEXT(Setup!$C$5+45,"dddd") -> Thursday | B72: =Setup!$C$5+45 -> 46072 | C72: 11.00 - 11.30 | P72: =IFERROR(H72/Setup!$C$6,"") -> 0 | Q72: =IFERROR(H72-P72,"") -> 0
A73: =TEXT(Setup!$C$5+45,"dddd") -> Thursday | B73: =Setup!$C$5+45 -> 46072 | C73: 11.30 - 12.00 | P73: =IFERROR(H73/Setup!$C$6,"") -> 0 | Q73: =IFERROR(H73-P73,"") -> 0
A74: =TEXT(Setup!$C$5+45,"dddd") -> Thursday | B74: =Setup!$C$5+45 -> 46072 | C74: 12.00 - 12.30 | P74: =IFERROR(H74/Setup!$C$6,"") -> 0 | Q74: =IFERROR(H74-P74,"") -> 0
A75: =TEXT(Setup!$C$5+45,"dddd") -> Thursday | B75: =Setup!$C$5+45 -> 46072 | C75: 12.30 - 13.00 | P75: =IFERROR(H75/Setup!$C$6,"") -> 0 | Q75: =IFERROR(H75-P75,"") -> 0
A76: =TEXT(Setup!$C$5+45,"dddd") -> Thursday | B76: =Setup!$C$5+45 -> 46072 | C76: 13.00 - 13.30 | P76: =IFERROR(H76/Setup!$C$6,"") -> 0 | Q76: =IFERROR(H76-P76,"") -> 0
A77: =TEXT(Setup!$C$5+45,"dddd") -> Thursday | B77: =Setup!$C$5+45 -> 46072 | C77: 13.30 - 14.00 | P77: =IFERROR(H77/Setup!$C$6,"") -> 0 | Q77: =IFERROR(H77-P77,"") -> 0
A78: =TEXT(Setup!$C$5+45,"dddd") -> Thursday | B78: =Setup!$C$5+45 -> 46072 | C78: 14.00 - 14.30 | P78: =IFERROR(H78/Setup!$C$6,"") -> 0 | Q78: =IFERROR(H78-P78,"") -> 0
A79: =TEXT(Setup!$C$5+45,"dddd") -> Thursday | B79: =Setup!$C$5+45 -> 46072 | C79: 14.30 - 15.00 | P79: =IFERROR(H79/Setup!$C$6,"") -> 0 | Q79: =IFERROR(H79-P79,"") -> 0
... A88: =TEXT(Setup!$C$5+45,"dddd") -> Thursday | B88: =Setup!$C$5+45 -> 46072 | C88: ONLINE | P88: =IFERROR(H88/Setup!$C$6,"") -> 0 | Q88: =IFERROR(H88-P88,"") -> 0
A89: =TEXT(Setup!$C$5+45,"dddd") -> Thursday | B89: =Setup!$C$5+45 -> 46072 | C89: TOTAL | D89: =SUM(D68:D88) -> 0 | E89: =SUM(E68:E88) -> 0 | F89: =SUM(F68:F88) -> 0 | G89: =SUM(G68:G88) -> 0 | H89: =SUM(H68:H88) -> 0 | I89: =IFERROR(E89/D89,"") | J89: =IFERROR(H89/E89,"") | K89: =SUM(K68:K88) -> 0 | M89: =SUM(M68:M88) -> 0 | N89: =IFERROR(H89-Wk6!H89,"") -> 0 | O89: =IFERROR(D89-Wk6!D89,"") -> 0 | P89: =SUM(P68:P88) -> 0 | Q89: =SUM(Q68:Q88) -> 0 | R89: =IFERROR(INDEX('Last Year'!$C$6:$C$369,MATCH(B89-364,'Last Year'!$B$6:$B$369,0)),"") -> 0 | S89: =IFERROR(H89/R89-1,"")
A90: =TEXT(Setup!$C$5+46,"dddd") -> Friday | B90: =Setup!$C$5+46 -> 46073 | C90: 9.00 - 9.30 | P90: =IFERROR(H90/Setup!$C$6,"") -> 0 | Q90: =IFERROR(H90-P90,"") -> 0
A91: =TEXT(Setup!$C$5+46,"dddd") -> Friday | B91: =Setup!$C$5+46 -> 46073 | C91: 9.30 - 10.00 | P91: =IFERROR(H91/Setup!$C$6,"") -> 0 | Q91: =IFERROR(H91-P91,"") -> 0
A92: =TEXT(Setup!$C$5+46,"dddd") -> Friday | B92: =Setup!$C$5+46 -> 46073 | C92: 10.00 - 10.30 | P92: =IFERROR(H92/Setup!$C$6,"") -> 0 | Q92: =IFERROR(H92-P92,"") -> 0
A93: =TEXT(Setup!$C$5+46,"dddd") -> Friday | B93: =Setup!$C$5+46 -> 46073 | C93: 10.30 - 11.00 | P93: =IFERROR(H93/Setup!$C$6,"") -> 0 | Q93: =IFERROR(H93-P93,"") -> 0
A94: =TEXT(Setup!$C$5+46,"dddd") -> Friday | B94: =Setup!$C$5+46 -> 46073 | C94: 11.00 - 11.30 | P94: =IFERROR(H94/Setup!$C$6,"") -> 0 | Q94: =IFERROR(H94-P94,"") -> 0
A95: =TEXT(Setup!$C$5+46,"dddd") -> Friday | B95: =Setup!$C$5+46 -> 46073 | C95: 11.30 - 12.00 | P95: =IFERROR(H95/Setup!$C$6,"") -> 0 | Q95: =IFERROR(H95-P95,"") -> 0
A96: =TEXT(Setup!$C$5+46,"dddd") -> Friday | B96: =Setup!$C$5+46 -> 46073 | C96: 12.00 - 12.30 | P96: =IFERROR(H96/Setup!$C$6,"") -> 0 | Q96: =IFERROR(H96-P96,"") -> 0
A97: =TEXT(Setup!$C$5+46,"dddd") -> Friday | B97: =Setup!$C$5+46 -> 46073 | C97: 12.30 - 13.00 | P97: =IFERROR(H97/Setup!$C$6,"") -> 0 | Q97: =IFERROR(H97-P97,"") -> 0
A98: =TEXT(Setup!$C$5+46,"dddd") -> Friday | B98: =Setup!$C$5+46 -> 46073 | C98: 13.00 - 13.30 | P98: =IFERROR(H98/Setup!$C$6,"") -> 0 | Q98: =IFERROR(H98-P98,"") -> 0
A99: =TEXT(Setup!$C$5+46,"dddd") -> Friday | B99: =Setup!$C$5+46 -> 46073 | C99: 13.30 - 14.00 | P99: =IFERROR(H99/Setup!$C$6,"") -> 0 | Q99: =IFERROR(H99-P99,"") -> 0
A100: =TEXT(Setup!$C$5+46,"dddd") -> Friday | B100: =Setup!$C$5+46 -> 46073 | C100: 14.00 - 14.30 | P100: =IFERROR(H100/Setup!$C$6,"") -> 0 | Q100: =IFERROR(H100-P100,"") -> 0
A101: =TEXT(Setup!$C$5+46,"dddd") -> Friday | B101: =Setup!$C$5+46 -> 46073 | C101: 14.30 - 15.00 | P101: =IFERROR(H101/Setup!$C$6,"") -> 0 | Q101: =IFERROR(H101-P101,"") -> 0
... A110: =TEXT(Setup!$C$5+46,"dddd") -> Friday | B110: =Setup!$C$5+46 -> 46073 | C110: ONLINE | P110: =IFERROR(H110/Setup!$C$6,"") -> 0 | Q110: =IFERROR(H110-P110,"") -> 0
A111: =TEXT(Setup!$C$5+46,"dddd") -> Friday | B111: =Setup!$C$5+46 -> 46073 | C111: TOTAL | D111: =SUM(D90:D110) -> 0 | E111: =SUM(E90:E110) -> 0 | F111: =SUM(F90:F110) -> 0 | G111: =SUM(G90:G110) -> 0 | H111: =SUM(H90:H110) -> 0 | I111: =IFERROR(E111/D111,"") | J111: =IFERROR(H111/E111,"") | K111: =SUM(K90:K110) -> 0 | M111: =SUM(M90:M110) -> 0 | N111: =IFERROR(H111-Wk6!H111,"") -> 0 | O111: =IFERROR(D111-Wk6!D111,"") -> 0 | P111: =SUM(P90:P110) -> 0 | Q111: =SUM(Q90:Q110) -> 0 | R111: =IFERROR(INDEX('Last Year'!$C$6:$C$369,MATCH(B111-364,'Last Year'!$B$6:$B$369,0)),"") -> 0 | S111: =IFERROR(H111/R111-1,"")
A112: =TEXT(Setup!$C$5+47,"dddd") -> Saturday | B112: =Setup!$C$5+47 -> 46074 | C112: 9.00 - 9.30 | P112: =IFERROR(H112/Setup!$C$6,"") -> 0 | Q112: =IFERROR(H112-P112,"") -> 0
A113: =TEXT(Setup!$C$5+47,"dddd") -> Saturday | B113: =Setup!$C$5+47 -> 46074 | C113: 9.30 - 10.00 | P113: =IFERROR(H113/Setup!$C$6,"") -> 0 | Q113: =IFERROR(H113-P113,"") -> 0
A114: =TEXT(Setup!$C$5+47,"dddd") -> Saturday | B114: =Setup!$C$5+47 -> 46074 | C114: 10.00 - 10.30 | P114: =IFERROR(H114/Setup!$C$6,"") -> 0 | Q114: =IFERROR(H114-P114,"") -> 0
A115: =TEXT(Setup!$C$5+47,"dddd") -> Saturday | B115: =Setup!$C$5+47 -> 46074 | C115: 10.30 - 11.00 | P115: =IFERROR(H115/Setup!$C$6,"") -> 0 | Q115: =IFERROR(H115-P115,"") -> 0
A116: =TEXT(Setup!$C$5+47,"dddd") -> Saturday | B116: =Setup!$C$5+47 -> 46074 | C116: 11.00 - 11.30 | P116: =IFERROR(H116/Setup!$C$6,"") -> 0 | Q116: =IFERROR(H116-P116,"") -> 0
A117: =TEXT(Setup!$C$5+47,"dddd") -> Saturday | B117: =Setup!$C$5+47 -> 46074 | C117: 11.30 - 12.00 | P117: =IFERROR(H117/Setup!$C$6,"") -> 0 | Q117: =IFERROR(H117-P117,"") -> 0
A118: =TEXT(Setup!$C$5+47,"dddd") -> Saturday | B118: =Setup!$C$5+47 -> 46074 | C118: 12.00 - 12.30 | P118: =IFERROR(H118/Setup!$C$6,"") -> 0 | Q118: =IFERROR(H118-P118,"") -> 0
A119: =TEXT(Setup!$C$5+47,"dddd") -> Saturday | B119: =Setup!$C$5+47 -> 46074 | C119: 12.30 - 13.00 | P119: =IFERROR(H119/Setup!$C$6,"") -> 0 | Q119: =IFERROR(H119-P119,"") -> 0
A120: =TEXT(Setup!$C$5+47,"dddd") -> Saturday | B120: =Setup!$C$5+47 -> 46074 | C120: 13.00 - 13.30 | P120: =IFERROR(H120/Setup!$C$6,"") -> 0 | Q120: =IFERROR(H120-P120,"") -> 0
A121: =TEXT(Setup!$C$5+47,"dddd") -> Saturday | B121: =Setup!$C$5+47 -> 46074 | C121: 13.30 - 14.00 | P121: =IFERROR(H121/Setup!$C$6,"") -> 0 | Q121: =IFERROR(H121-P121,"") -> 0
A122: =TEXT(Setup!$C$5+47,"dddd") -> Saturday | B122: =Setup!$C$5+47 -> 46074 | C122: 14.00 - 14.30 | P122: =IFERROR(H122/Setup!$C$6,"") -> 0 | Q122: =IFERROR(H122-P122,"") -> 0
A123: =TEXT(Setup!$C$5+47,"dddd") -> Saturday | B123: =Setup!$C$5+47 -> 46074 | C123: 14.30 - 15.00 | P123: =IFERROR(H123/Setup!$C$6,"") -> 0 | Q123: =IFERROR(H123-P123,"") -> 0
... A132: =TEXT(Setup!$C$5+47,"dddd") -> Saturday | B132: =Setup!$C$5+47 -> 46074 | C132: ONLINE | P132: =IFERROR(H132/Setup!$C$6,"") -> 0 | Q132: =IFERROR(H132-P132,"") -> 0
A133: =TEXT(Setup!$C$5+47,"dddd") -> Saturday | B133: =Setup!$C$5+47 -> 46074 | C133: TOTAL | D133: =SUM(D112:D132) -> 0 | E133: =SUM(E112:E132) -> 0 | F133: =SUM(F112:F132) -> 0 | G133: =SUM(G112:G132) -> 0 | H133: =SUM(H112:H132) -> 0 | I133: =IFERROR(E133/D133,"") | J133: =IFERROR(H133/E133,"") | K133: =SUM(K112:K132) -> 0 | M133: =SUM(M112:M132) -> 0 | N133: =IFERROR(H133-Wk6!H133,"") -> 0 | O133: =IFERROR(D133-Wk6!D133,"") -> 0 | P133: =SUM(P112:P132) -> 0 | Q133: =SUM(Q112:Q132) -> 0 | R133: =IFERROR(INDEX('Last Year'!$C$6:$C$369,MATCH(B133-364,'Last Year'!$B$6:$B$369,0)),"") -> 0 | S133: =IFERROR(H133/R133-1,"")
A134: =TEXT(Setup!$C$5+48,"dddd") -> Sunday | B134: =Setup!$C$5+48 -> 46075 | C134: 9.00 - 9.30 | P134: =IFERROR(H134/Setup!$C$6,"") -> 0 | Q134: =IFERROR(H134-P134,"") -> 0
A135: =TEXT(Setup!$C$5+48,"dddd") -> Sunday | B135: =Setup!$C$5+48 -> 46075 | C135: 9.30 - 10.00 | P135: =IFERROR(H135/Setup!$C$6,"") -> 0 | Q135: =IFERROR(H135-P135,"") -> 0
A136: =TEXT(Setup!$C$5+48,"dddd") -> Sunday | B136: =Setup!$C$5+48 -> 46075 | C136: 10.00 - 10.30 | P136: =IFERROR(H136/Setup!$C$6,"") -> 0 | Q136: =IFERROR(H136-P136,"") -> 0
A137: =TEXT(Setup!$C$5+48,"dddd") -> Sunday | B137: =Setup!$C$5+48 -> 46075 | C137: 10.30 - 11.00 | P137: =IFERROR(H137/Setup!$C$6,"") -> 0 | Q137: =IFERROR(H137-P137,"") -> 0
A138: =TEXT(Setup!$C$5+48,"dddd") -> Sunday | B138: =Setup!$C$5+48 -> 46075 | C138: 11.00 - 11.30 | P138: =IFERROR(H138/Setup!$C$6,"") -> 0 | Q138: =IFERROR(H138-P138,"") -> 0
A139: =TEXT(Setup!$C$5+48,"dddd") -> Sunday | B139: =Setup!$C$5+48 -> 46075 | C139: 11.30 - 12.00 | P139: =IFERROR(H139/Setup!$C$6,"") -> 0 | Q139: =IFERROR(H139-P139,"") -> 0
A140: =TEXT(Setup!$C$5+48,"dddd") -> Sunday | B140: =Setup!$C$5+48 -> 46075 | C140: 12.00 - 12.30 | P140: =IFERROR(H140/Setup!$C$6,"") -> 0 | Q140: =IFERROR(H140-P140,"") -> 0
A141: =TEXT(Setup!$C$5+48,"dddd") -> Sunday | B141: =Setup!$C$5+48 -> 46075 | C141: 12.30 - 13.00 | P141: =IFERROR(H141/Setup!$C$6,"") -> 0 | Q141: =IFERROR(H141-P141,"") -> 0
A142: =TEXT(Setup!$C$5+48,"dddd") -> Sunday | B142: =Setup!$C$5+48 -> 46075 | C142: 13.00 - 13.30 | P142: =IFERROR(H142/Setup!$C$6,"") -> 0 | Q142: =IFERROR(H142-P142,"") -> 0
A143: =TEXT(Setup!$C$5+48,"dddd") -> Sunday | B143: =Setup!$C$5+48 -> 46075 | C143: 13.30 - 14.00 | P143: =IFERROR(H143/Setup!$C$6,"") -> 0 | Q143: =IFERROR(H143-P143,"") -> 0
A144: =TEXT(Setup!$C$5+48,"dddd") -> Sunday | B144: =Setup!$C$5+48 -> 46075 | C144: 14.00 - 14.30 | P144: =IFERROR(H144/Setup!$C$6,"") -> 0 | Q144: =IFERROR(H144-P144,"") -> 0
A145: =TEXT(Setup!$C$5+48,"dddd") -> Sunday | B145: =Setup!$C$5+48 -> 46075 | C145: 14.30 - 15.00 | P145: =IFERROR(H145/Setup!$C$6,"") -> 0 | Q145: =IFERROR(H145-P145,"") -> 0
... A154: =TEXT(Setup!$C$5+48,"dddd") -> Sunday | B154: =Setup!$C$5+48 -> 46075 | C154: ONLINE | P154: =IFERROR(H154/Setup!$C$6,"") -> 0 | Q154: =IFERROR(H154-P154,"") -> 0
A155: =TEXT(Setup!$C$5+48,"dddd") -> Sunday | B155: =Setup!$C$5+48 -> 46075 | C155: TOTAL | D155: =SUM(D134:D154) -> 0 | E155: =SUM(E134:E154) -> 0 | F155: =SUM(F134:F154) -> 0 | G155: =SUM(G134:G154) -> 0 | H155: =SUM(H134:H154) -> 0 | I155: =IFERROR(E155/D155,"") | J155: =IFERROR(H155/E155,"") | K155: =SUM(K134:K154) -> 0 | M155: =SUM(M134:M154) -> 0 | N155: =IFERROR(H155-Wk6!H155,"") -> 0 | O155: =IFERROR(D155-Wk6!D155,"") -> 0 | P155: =SUM(P134:P154) -> 0 | Q155: =SUM(Q134:Q154) -> 0 | R155: =IFERROR(INDEX('Last Year'!$C$6:$C$369,MATCH(B155-364,'Last Year'!$B$6:$B$369,0)),"") -> 0 | S155: =IFERROR(H155/R155-1,"")
C156: FULL WEEK | D156: =D23+D45+D67+D89+D111+D133+D155 -> 0 | E156: =E23+E45+E67+E89+E111+E133+E155 -> 0 | F156: =F23+F45+F67+F89+F111+F133+F155 -> 0 | G156: =G23+G45+G67+G89+G111+G133+G155 -> 0 | H156: =H23+H45+H67+H89+H111+H133+H155 -> 0 | I156: =IFERROR(E156/D156,"") | J156: =IFERROR(H156/E156,"") | K156: =K23+K45+K67+K89+K111+K133+K155 -> 0 | M156: =M23+M45+M67+M89+M111+M133+M155 -> 0 | P156: =P23+P45+P67+P89+P111+P133+P155 -> 0 | Q156: =Q23+Q45+Q67+Q89+Q111+Q133+Q155 -> 0 | R156: =R23+R45+R67+R89+R111+R133+R155 -> 0 | S156: =IFERROR(H156/R156-1,"")
...

Sheet Wk8
A1: Day | B1: Date | C1: Time | D1: Customers In | E1: Sales | F1: Vouchers Used | G1: Walk In/Out | H1: Sale Amount | I1: Conversion | J1: Avg Sale | K1: Tracked Category | L1: Notes | M1: Cash | N1: vs Last Wk € | O1: vs Last Wk Cust | P1: Est. Cost | Q1: Est. Profit | R1: Last Year Day | S1: vs Last Year
A2: =TEXT(Setup!$C$5+49,"dddd") -> Monday | B2: =Setup!$C$5+49 -> 46076 | C2: 9.00 - 9.30 | P2: =IFERROR(H2/Setup!$C$6,"") -> 0 | Q2: =IFERROR(H2-P2,"") -> 0
A3: =TEXT(Setup!$C$5+49,"dddd") -> Monday | B3: =Setup!$C$5+49 -> 46076 | C3: 9.30 - 10.00 | P3: =IFERROR(H3/Setup!$C$6,"") -> 0 | Q3: =IFERROR(H3-P3,"") -> 0
A4: =TEXT(Setup!$C$5+49,"dddd") -> Monday | B4: =Setup!$C$5+49 -> 46076 | C4: 10.00 - 10.30 | P4: =IFERROR(H4/Setup!$C$6,"") -> 0 | Q4: =IFERROR(H4-P4,"") -> 0
A5: =TEXT(Setup!$C$5+49,"dddd") -> Monday | B5: =Setup!$C$5+49 -> 46076 | C5: 10.30 - 11.00 | P5: =IFERROR(H5/Setup!$C$6,"") -> 0 | Q5: =IFERROR(H5-P5,"") -> 0
A6: =TEXT(Setup!$C$5+49,"dddd") -> Monday | B6: =Setup!$C$5+49 -> 46076 | C6: 11.00 - 11.30 | P6: =IFERROR(H6/Setup!$C$6,"") -> 0 | Q6: =IFERROR(H6-P6,"") -> 0
A7: =TEXT(Setup!$C$5+49,"dddd") -> Monday | B7: =Setup!$C$5+49 -> 46076 | C7: 11.30 - 12.00 | P7: =IFERROR(H7/Setup!$C$6,"") -> 0 | Q7: =IFERROR(H7-P7,"") -> 0
A8: =TEXT(Setup!$C$5+49,"dddd") -> Monday | B8: =Setup!$C$5+49 -> 46076 | C8: 12.00 - 12.30 | P8: =IFERROR(H8/Setup!$C$6,"") -> 0 | Q8: =IFERROR(H8-P8,"") -> 0
A9: =TEXT(Setup!$C$5+49,"dddd") -> Monday | B9: =Setup!$C$5+49 -> 46076 | C9: 12.30 - 13.00 | P9: =IFERROR(H9/Setup!$C$6,"") -> 0 | Q9: =IFERROR(H9-P9,"") -> 0
A10: =TEXT(Setup!$C$5+49,"dddd") -> Monday | B10: =Setup!$C$5+49 -> 46076 | C10: 13.00 - 13.30 | P10: =IFERROR(H10/Setup!$C$6,"") -> 0 | Q10: =IFERROR(H10-P10,"") -> 0
A11: =TEXT(Setup!$C$5+49,"dddd") -> Monday | B11: =Setup!$C$5+49 -> 46076 | C11: 13.30 - 14.00 | P11: =IFERROR(H11/Setup!$C$6,"") -> 0 | Q11: =IFERROR(H11-P11,"") -> 0
A12: =TEXT(Setup!$C$5+49,"dddd") -> Monday | B12: =Setup!$C$5+49 -> 46076 | C12: 14.00 - 14.30 | P12: =IFERROR(H12/Setup!$C$6,"") -> 0 | Q12: =IFERROR(H12-P12,"") -> 0
A13: =TEXT(Setup!$C$5+49,"dddd") -> Monday | B13: =Setup!$C$5+49 -> 46076 | C13: 14.30 - 15.00 | P13: =IFERROR(H13/Setup!$C$6,"") -> 0 | Q13: =IFERROR(H13-P13,"") -> 0
... A22: =TEXT(Setup!$C$5+49,"dddd") -> Monday | B22: =Setup!$C$5+49 -> 46076 | C22: ONLINE | P22: =IFERROR(H22/Setup!$C$6,"") -> 0 | Q22: =IFERROR(H22-P22,"") -> 0
A23: =TEXT(Setup!$C$5+49,"dddd") -> Monday | B23: =Setup!$C$5+49 -> 46076 | C23: TOTAL | D23: =SUM(D2:D22) -> 0 | E23: =SUM(E2:E22) -> 0 | F23: =SUM(F2:F22) -> 0 | G23: =SUM(G2:G22) -> 0 | H23: =SUM(H2:H22) -> 0 | I23: =IFERROR(E23/D23,"") | J23: =IFERROR(H23/E23,"") | K23: =SUM(K2:K22) -> 0 | M23: =SUM(M2:M22) -> 0 | N23: =IFERROR(H23-Wk7!H23,"") -> 0 | O23: =IFERROR(D23-Wk7!D23,"") -> 0 | P23: =SUM(P2:P22) -> 0 | Q23: =SUM(Q2:Q22) -> 0 | R23: =IFERROR(INDEX('Last Year'!$C$6:$C$369,MATCH(B23-364,'Last Year'!$B$6:$B$369,0)),"") -> 0 | S23: =IFERROR(H23/R23-1,"")
A24: =TEXT(Setup!$C$5+50,"dddd") -> Tuesday | B24: =Setup!$C$5+50 -> 46077 | C24: 9.00 - 9.30 | P24: =IFERROR(H24/Setup!$C$6,"") -> 0 | Q24: =IFERROR(H24-P24,"") -> 0
A25: =TEXT(Setup!$C$5+50,"dddd") -> Tuesday | B25: =Setup!$C$5+50 -> 46077 | C25: 9.30 - 10.00 | P25: =IFERROR(H25/Setup!$C$6,"") -> 0 | Q25: =IFERROR(H25-P25,"") -> 0
A26: =TEXT(Setup!$C$5+50,"dddd") -> Tuesday | B26: =Setup!$C$5+50 -> 46077 | C26: 10.00 - 10.30 | P26: =IFERROR(H26/Setup!$C$6,"") -> 0 | Q26: =IFERROR(H26-P26,"") -> 0
A27: =TEXT(Setup!$C$5+50,"dddd") -> Tuesday | B27: =Setup!$C$5+50 -> 46077 | C27: 10.30 - 11.00 | P27: =IFERROR(H27/Setup!$C$6,"") -> 0 | Q27: =IFERROR(H27-P27,"") -> 0
A28: =TEXT(Setup!$C$5+50,"dddd") -> Tuesday | B28: =Setup!$C$5+50 -> 46077 | C28: 11.00 - 11.30 | P28: =IFERROR(H28/Setup!$C$6,"") -> 0 | Q28: =IFERROR(H28-P28,"") -> 0
A29: =TEXT(Setup!$C$5+50,"dddd") -> Tuesday | B29: =Setup!$C$5+50 -> 46077 | C29: 11.30 - 12.00 | P29: =IFERROR(H29/Setup!$C$6,"") -> 0 | Q29: =IFERROR(H29-P29,"") -> 0
A30: =TEXT(Setup!$C$5+50,"dddd") -> Tuesday | B30: =Setup!$C$5+50 -> 46077 | C30: 12.00 - 12.30 | P30: =IFERROR(H30/Setup!$C$6,"") -> 0 | Q30: =IFERROR(H30-P30,"") -> 0
A31: =TEXT(Setup!$C$5+50,"dddd") -> Tuesday | B31: =Setup!$C$5+50 -> 46077 | C31: 12.30 - 13.00 | P31: =IFERROR(H31/Setup!$C$6,"") -> 0 | Q31: =IFERROR(H31-P31,"") -> 0
A32: =TEXT(Setup!$C$5+50,"dddd") -> Tuesday | B32: =Setup!$C$5+50 -> 46077 | C32: 13.00 - 13.30 | P32: =IFERROR(H32/Setup!$C$6,"") -> 0 | Q32: =IFERROR(H32-P32,"") -> 0
A33: =TEXT(Setup!$C$5+50,"dddd") -> Tuesday | B33: =Setup!$C$5+50 -> 46077 | C33: 13.30 - 14.00 | P33: =IFERROR(H33/Setup!$C$6,"") -> 0 | Q33: =IFERROR(H33-P33,"") -> 0
A34: =TEXT(Setup!$C$5+50,"dddd") -> Tuesday | B34: =Setup!$C$5+50 -> 46077 | C34: 14.00 - 14.30 | P34: =IFERROR(H34/Setup!$C$6,"") -> 0 | Q34: =IFERROR(H34-P34,"") -> 0
A35: =TEXT(Setup!$C$5+50,"dddd") -> Tuesday | B35: =Setup!$C$5+50 -> 46077 | C35: 14.30 - 15.00 | P35: =IFERROR(H35/Setup!$C$6,"") -> 0 | Q35: =IFERROR(H35-P35,"") -> 0
... A44: =TEXT(Setup!$C$5+50,"dddd") -> Tuesday | B44: =Setup!$C$5+50 -> 46077 | C44: ONLINE | P44: =IFERROR(H44/Setup!$C$6,"") -> 0 | Q44: =IFERROR(H44-P44,"") -> 0
A45: =TEXT(Setup!$C$5+50,"dddd") -> Tuesday | B45: =Setup!$C$5+50 -> 46077 | C45: TOTAL | D45: =SUM(D24:D44) -> 0 | E45: =SUM(E24:E44) -> 0 | F45: =SUM(F24:F44) -> 0 | G45: =SUM(G24:G44) -> 0 | H45: =SUM(H24:H44) -> 0 | I45: =IFERROR(E45/D45,"") | J45: =IFERROR(H45/E45,"") | K45: =SUM(K24:K44) -> 0 | M45: =SUM(M24:M44) -> 0 | N45: =IFERROR(H45-Wk7!H45,"") -> 0 | O45: =IFERROR(D45-Wk7!D45,"") -> 0 | P45: =SUM(P24:P44) -> 0 | Q45: =SUM(Q24:Q44) -> 0 | R45: =IFERROR(INDEX('Last Year'!$C$6:$C$369,MATCH(B45-364,'Last Year'!$B$6:$B$369,0)),"") -> 0 | S45: =IFERROR(H45/R45-1,"")
A46: =TEXT(Setup!$C$5+51,"dddd") -> Wednesday | B46: =Setup!$C$5+51 -> 46078 | C46: 9.00 - 9.30 | P46: =IFERROR(H46/Setup!$C$6,"") -> 0 | Q46: =IFERROR(H46-P46,"") -> 0
A47: =TEXT(Setup!$C$5+51,"dddd") -> Wednesday | B47: =Setup!$C$5+51 -> 46078 | C47: 9.30 - 10.00 | P47: =IFERROR(H47/Setup!$C$6,"") -> 0 | Q47: =IFERROR(H47-P47,"") -> 0
A48: =TEXT(Setup!$C$5+51,"dddd") -> Wednesday | B48: =Setup!$C$5+51 -> 46078 | C48: 10.00 - 10.30 | P48: =IFERROR(H48/Setup!$C$6,"") -> 0 | Q48: =IFERROR(H48-P48,"") -> 0
A49: =TEXT(Setup!$C$5+51,"dddd") -> Wednesday | B49: =Setup!$C$5+51 -> 46078 | C49: 10.30 - 11.00 | P49: =IFERROR(H49/Setup!$C$6,"") -> 0 | Q49: =IFERROR(H49-P49,"") -> 0
A50: =TEXT(Setup!$C$5+51,"dddd") -> Wednesday | B50: =Setup!$C$5+51 -> 46078 | C50: 11.00 - 11.30 | P50: =IFERROR(H50/Setup!$C$6,"") -> 0 | Q50: =IFERROR(H50-P50,"") -> 0
A51: =TEXT(Setup!$C$5+51,"dddd") -> Wednesday | B51: =Setup!$C$5+51 -> 46078 | C51: 11.30 - 12.00 | P51: =IFERROR(H51/Setup!$C$6,"") -> 0 | Q51: =IFERROR(H51-P51,"") -> 0
A52: =TEXT(Setup!$C$5+51,"dddd") -> Wednesday | B52: =Setup!$C$5+51 -> 46078 | C52: 12.00 - 12.30 | P52: =IFERROR(H52/Setup!$C$6,"") -> 0 | Q52: =IFERROR(H52-P52,"") -> 0
A53: =TEXT(Setup!$C$5+51,"dddd") -> Wednesday | B53: =Setup!$C$5+51 -> 46078 | C53: 12.30 - 13.00 | P53: =IFERROR(H53/Setup!$C$6,"") -> 0 | Q53: =IFERROR(H53-P53,"") -> 0
A54: =TEXT(Setup!$C$5+51,"dddd") -> Wednesday | B54: =Setup!$C$5+51 -> 46078 | C54: 13.00 - 13.30 | P54: =IFERROR(H54/Setup!$C$6,"") -> 0 | Q54: =IFERROR(H54-P54,"") -> 0
A55: =TEXT(Setup!$C$5+51,"dddd") -> Wednesday | B55: =Setup!$C$5+51 -> 46078 | C55: 13.30 - 14.00 | P55: =IFERROR(H55/Setup!$C$6,"") -> 0 | Q55: =IFERROR(H55-P55,"") -> 0
A56: =TEXT(Setup!$C$5+51,"dddd") -> Wednesday | B56: =Setup!$C$5+51 -> 46078 | C56: 14.00 - 14.30 | P56: =IFERROR(H56/Setup!$C$6,"") -> 0 | Q56: =IFERROR(H56-P56,"") -> 0
A57: =TEXT(Setup!$C$5+51,"dddd") -> Wednesday | B57: =Setup!$C$5+51 -> 46078 | C57: 14.30 - 15.00 | P57: =IFERROR(H57/Setup!$C$6,"") -> 0 | Q57: =IFERROR(H57-P57,"") -> 0
... A66: =TEXT(Setup!$C$5+51,"dddd") -> Wednesday | B66: =Setup!$C$5+51 -> 46078 | C66: ONLINE | P66: =IFERROR(H66/Setup!$C$6,"") -> 0 | Q66: =IFERROR(H66-P66,"") -> 0
A67: =TEXT(Setup!$C$5+51,"dddd") -> Wednesday | B67: =Setup!$C$5+51 -> 46078 | C67: TOTAL | D67: =SUM(D46:D66) -> 0 | E67: =SUM(E46:E66) -> 0 | F67: =SUM(F46:F66) -> 0 | G67: =SUM(G46:G66) -> 0 | H67: =SUM(H46:H66) -> 0 | I67: =IFERROR(E67/D67,"") | J67: =IFERROR(H67/E67,"") | K67: =SUM(K46:K66) -> 0 | M67: =SUM(M46:M66) -> 0 | N67: =IFERROR(H67-Wk7!H67,"") -> 0 | O67: =IFERROR(D67-Wk7!D67,"") -> 0 | P67: =SUM(P46:P66) -> 0 | Q67: =SUM(Q46:Q66) -> 0 | R67: =IFERROR(INDEX('Last Year'!$C$6:$C$369,MATCH(B67-364,'Last Year'!$B$6:$B$369,0)),"") -> 0 | S67: =IFERROR(H67/R67-1,"")
A68: =TEXT(Setup!$C$5+52,"dddd") -> Thursday | B68: =Setup!$C$5+52 -> 46079 | C68: 9.00 - 9.30 | P68: =IFERROR(H68/Setup!$C$6,"") -> 0 | Q68: =IFERROR(H68-P68,"") -> 0
A69: =TEXT(Setup!$C$5+52,"dddd") -> Thursday | B69: =Setup!$C$5+52 -> 46079 | C69: 9.30 - 10.00 | P69: =IFERROR(H69/Setup!$C$6,"") -> 0 | Q69: =IFERROR(H69-P69,"") -> 0
A70: =TEXT(Setup!$C$5+52,"dddd") -> Thursday | B70: =Setup!$C$5+52 -> 46079 | C70: 10.00 - 10.30 | P70: =IFERROR(H70/Setup!$C$6,"") -> 0 | Q70: =IFERROR(H70-P70,"") -> 0
A71: =TEXT(Setup!$C$5+52,"dddd") -> Thursday | B71: =Setup!$C$5+52 -> 46079 | C71: 10.30 - 11.00 | P71: =IFERROR(H71/Setup!$C$6,"") -> 0 | Q71: =IFERROR(H71-P71,"") -> 0
A72: =TEXT(Setup!$C$5+52,"dddd") -> Thursday | B72: =Setup!$C$5+52 -> 46079 | C72: 11.00 - 11.30 | P72: =IFERROR(H72/Setup!$C$6,"") -> 0 | Q72: =IFERROR(H72-P72,"") -> 0
A73: =TEXT(Setup!$C$5+52,"dddd") -> Thursday | B73: =Setup!$C$5+52 -> 46079 | C73: 11.30 - 12.00 | P73: =IFERROR(H73/Setup!$C$6,"") -> 0 | Q73: =IFERROR(H73-P73,"") -> 0
A74: =TEXT(Setup!$C$5+52,"dddd") -> Thursday | B74: =Setup!$C$5+52 -> 46079 | C74: 12.00 - 12.30 | P74: =IFERROR(H74/Setup!$C$6,"") -> 0 | Q74: =IFERROR(H74-P74,"") -> 0
A75: =TEXT(Setup!$C$5+52,"dddd") -> Thursday | B75: =Setup!$C$5+52 -> 46079 | C75: 12.30 - 13.00 | P75: =IFERROR(H75/Setup!$C$6,"") -> 0 | Q75: =IFERROR(H75-P75,"") -> 0
A76: =TEXT(Setup!$C$5+52,"dddd") -> Thursday | B76: =Setup!$C$5+52 -> 46079 | C76: 13.00 - 13.30 | P76: =IFERROR(H76/Setup!$C$6,"") -> 0 | Q76: =IFERROR(H76-P76,"") -> 0
A77: =TEXT(Setup!$C$5+52,"dddd") -> Thursday | B77: =Setup!$C$5+52 -> 46079 | C77: 13.30 - 14.00 | P77: =IFERROR(H77/Setup!$C$6,"") -> 0 | Q77: =IFERROR(H77-P77,"") -> 0
A78: =TEXT(Setup!$C$5+52,"dddd") -> Thursday | B78: =Setup!$C$5+52 -> 46079 | C78: 14.00 - 14.30 | P78: =IFERROR(H78/Setup!$C$6,"") -> 0 | Q78: =IFERROR(H78-P78,"") -> 0
A79: =TEXT(Setup!$C$5+52,"dddd") -> Thursday | B79: =Setup!$C$5+52 -> 46079 | C79: 14.30 - 15.00 | P79: =IFERROR(H79/Setup!$C$6,"") -> 0 | Q79: =IFERROR(H79-P79,"") -> 0
... A88: =TEXT(Setup!$C$5+52,"dddd") -> Thursday | B88: =Setup!$C$5+52 -> 46079 | C88: ONLINE | P88: =IFERROR(H88/Setup!$C$6,"") -> 0 | Q88: =IFERROR(H88-P88,"") -> 0
A89: =TEXT(Setup!$C$5+52,"dddd") -> Thursday | B89: =Setup!$C$5+52 -> 46079 | C89: TOTAL | D89: =SUM(D68:D88) -> 0 | E89: =SUM(E68:E88) -> 0 | F89: =SUM(F68:F88) -> 0 | G89: =SUM(G68:G88) -> 0 | H89: =SUM(H68:H88) -> 0 | I89: =IFERROR(E89/D89,"") | J89: =IFERROR(H89/E89,"") | K89: =SUM(K68:K88) -> 0 | M89: =SUM(M68:M88) -> 0 | N89: =IFERROR(H89-Wk7!H89,"") -> 0 | O89: =IFERROR(D89-Wk7!D89,"") -> 0 | P89: =SUM(P68:P88) -> 0 | Q89: =SUM(Q68:Q88) -> 0 | R89: =IFERROR(INDEX('Last Year'!$C$6:$C$369,MATCH(B89-364,'Last Year'!$B$6:$B$369,0)),"") -> 0 | S89: =IFERROR(H89/R89-1,"")
A90: =TEXT(Setup!$C$5+53,"dddd") -> Friday | B90: =Setup!$C$5+53 -> 46080 | C90: 9.00 - 9.30 | P90: =IFERROR(H90/Setup!$C$6,"") -> 0 | Q90: =IFERROR(H90-P90,"") -> 0
A91: =TEXT(Setup!$C$5+53,"dddd") -> Friday | B91: =Setup!$C$5+53 -> 46080 | C91: 9.30 - 10.00 | P91: =IFERROR(H91/Setup!$C$6,"") -> 0 | Q91: =IFERROR(H91-P91,"") -> 0
A92: =TEXT(Setup!$C$5+53,"dddd") -> Friday | B92: =Setup!$C$5+53 -> 46080 | C92: 10.00 - 10.30 | P92: =IFERROR(H92/Setup!$C$6,"") -> 0 | Q92: =IFERROR(H92-P92,"") -> 0
A93: =TEXT(Setup!$C$5+53,"dddd") -> Friday | B93: =Setup!$C$5+53 -> 46080 | C93: 10.30 - 11.00 | P93: =IFERROR(H93/Setup!$C$6,"") -> 0 | Q93: =IFERROR(H93-P93,"") -> 0
A94: =TEXT(Setup!$C$5+53,"dddd") -> Friday | B94: =Setup!$C$5+53 -> 46080 | C94: 11.00 - 11.30 | P94: =IFERROR(H94/Setup!$C$6,"") -> 0 | Q94: =IFERROR(H94-P94,"") -> 0
A95: =TEXT(Setup!$C$5+53,"dddd") -> Friday | B95: =Setup!$C$5+53 -> 46080 | C95: 11.30 - 12.00 | P95: =IFERROR(H95/Setup!$C$6,"") -> 0 | Q95: =IFERROR(H95-P95,"") -> 0
A96: =TEXT(Setup!$C$5+53,"dddd") -> Friday | B96: =Setup!$C$5+53 -> 46080 | C96: 12.00 - 12.30 | P96: =IFERROR(H96/Setup!$C$6,"") -> 0 | Q96: =IFERROR(H96-P96,"") -> 0
A97: =TEXT(Setup!$C$5+53,"dddd") -> Friday | B97: =Setup!$C$5+53 -> 46080 | C97: 12.30 - 13.00 | P97: =IFERROR(H97/Setup!$C$6,"") -> 0 | Q97: =IFERROR(H97-P97,"") -> 0
A98: =TEXT(Setup!$C$5+53,"dddd") -> Friday | B98: =Setup!$C$5+53 -> 46080 | C98: 13.00 - 13.30 | P98: =IFERROR(H98/Setup!$C$6,"") -> 0 | Q98: =IFERROR(H98-P98,"") -> 0
A99: =TEXT(Setup!$C$5+53,"dddd") -> Friday | B99: =Setup!$C$5+53 -> 46080 | C99: 13.30 - 14.00 | P99: =IFERROR(H99/Setup!$C$6,"") -> 0 | Q99: =IFERROR(H99-P99,"") -> 0
A100: =TEXT(Setup!$C$5+53,"dddd") -> Friday | B100: =Setup!$C$5+53 -> 46080 | C100: 14.00 - 14.30 | P100: =IFERROR(H100/Setup!$C$6,"") -> 0 | Q100: =IFERROR(H100-P100,"") -> 0
A101: =TEXT(Setup!$C$5+53,"dddd") -> Friday | B101: =Setup!$C$5+53 -> 46080 | C101: 14.30 - 15.00 | P101: =IFERROR(H101/Setup!$C$6,"") -> 0 | Q101: =IFERROR(H101-P101,"") -> 0
... A110: =TEXT(Setup!$C$5+53,"dddd") -> Friday | B110: =Setup!$C$5+53 -> 46080 | C110: ONLINE | P110: =IFERROR(H110/Setup!$C$6,"") -> 0 | Q110: =IFERROR(H110-P110,"") -> 0
A111: =TEXT(Setup!$C$5+53,"dddd") -> Friday | B111: =Setup!$C$5+53 -> 46080 | C111: TOTAL | D111: =SUM(D90:D110) -> 0 | E111: =SUM(E90:E110) -> 0 | F111: =SUM(F90:F110) -> 0 | G111: =SUM(G90:G110) -> 0 | H111: =SUM(H90:H110) -> 0 | I111: =IFERROR(E111/D111,"") | J111: =IFERROR(H111/E111,"") | K111: =SUM(K90:K110) -> 0 | M111: =SUM(M90:M110) -> 0 | N111: =IFERROR(H111-Wk7!H111,"") -> 0 | O111: =IFERROR(D111-Wk7!D111,"") -> 0 | P111: =SUM(P90:P110) -> 0 | Q111: =SUM(Q90:Q110) -> 0 | R111: =IFERROR(INDEX('Last Year'!$C$6:$C$369,MATCH(B111-364,'Last Year'!$B$6:$B$369,0)),"") -> 0 | S111: =IFERROR(H111/R111-1,"")
A112: =TEXT(Setup!$C$5+54,"dddd") -> Saturday | B112: =Setup!$C$5+54 -> 46081 | C112: 9.00 - 9.30 | P112: =IFERROR(H112/Setup!$C$6,"") -> 0 | Q112: =IFERROR(H112-P112,"") -> 0
A113: =TEXT(Setup!$C$5+54,"dddd") -> Saturday | B113: =Setup!$C$5+54 -> 46081 | C113: 9.30 - 10.00 | P113: =IFERROR(H113/Setup!$C$6,"") -> 0 | Q113: =IFERROR(H113-P113,"") -> 0
A114: =TEXT(Setup!$C$5+54,"dddd") -> Saturday | B114: =Setup!$C$5+54 -> 46081 | C114: 10.00 - 10.30 | P114: =IFERROR(H114/Setup!$C$6,"") -> 0 | Q114: =IFERROR(H114-P114,"") -> 0
A115: =TEXT(Setup!$C$5+54,"dddd") -> Saturday | B115: =Setup!$C$5+54 -> 46081 | C115: 10.30 - 11.00 | P115: =IFERROR(H115/Setup!$C$6,"") -> 0 | Q115: =IFERROR(H115-P115,"") -> 0
A116: =TEXT(Setup!$C$5+54,"dddd") -> Saturday | B116: =Setup!$C$5+54 -> 46081 | C116: 11.00 - 11.30 | P116: =IFERROR(H116/Setup!$C$6,"") -> 0 | Q116: =IFERROR(H116-P116,"") -> 0
A117: =TEXT(Setup!$C$5+54,"dddd") -> Saturday | B117: =Setup!$C$5+54 -> 46081 | C117: 11.30 - 12.00 | P117: =IFERROR(H117/Setup!$C$6,"") -> 0 | Q117: =IFERROR(H117-P117,"") -> 0
A118: =TEXT(Setup!$C$5+54,"dddd") -> Saturday | B118: =Setup!$C$5+54 -> 46081 | C118: 12.00 - 12.30 | P118: =IFERROR(H118/Setup!$C$6,"") -> 0 | Q118: =IFERROR(H118-P118,"") -> 0
A119: =TEXT(Setup!$C$5+54,"dddd") -> Saturday | B119: =Setup!$C$5+54 -> 46081 | C119: 12.30 - 13.00 | P119: =IFERROR(H119/Setup!$C$6,"") -> 0 | Q119: =IFERROR(H119-P119,"") -> 0
A120: =TEXT(Setup!$C$5+54,"dddd") -> Saturday | B120: =Setup!$C$5+54 -> 46081 | C120: 13.00 - 13.30 | P120: =IFERROR(H120/Setup!$C$6,"") -> 0 | Q120: =IFERROR(H120-P120,"") -> 0
A121: =TEXT(Setup!$C$5+54,"dddd") -> Saturday | B121: =Setup!$C$5+54 -> 46081 | C121: 13.30 - 14.00 | P121: =IFERROR(H121/Setup!$C$6,"") -> 0 | Q121: =IFERROR(H121-P121,"") -> 0
A122: =TEXT(Setup!$C$5+54,"dddd") -> Saturday | B122: =Setup!$C$5+54 -> 46081 | C122: 14.00 - 14.30 | P122: =IFERROR(H122/Setup!$C$6,"") -> 0 | Q122: =IFERROR(H122-P122,"") -> 0
A123: =TEXT(Setup!$C$5+54,"dddd") -> Saturday | B123: =Setup!$C$5+54 -> 46081 | C123: 14.30 - 15.00 | P123: =IFERROR(H123/Setup!$C$6,"") -> 0 | Q123: =IFERROR(H123-P123,"") -> 0
... A132: =TEXT(Setup!$C$5+54,"dddd") -> Saturday | B132: =Setup!$C$5+54 -> 46081 | C132: ONLINE | P132: =IFERROR(H132/Setup!$C$6,"") -> 0 | Q132: =IFERROR(H132-P132,"") -> 0
A133: =TEXT(Setup!$C$5+54,"dddd") -> Saturday | B133: =Setup!$C$5+54 -> 46081 | C133: TOTAL | D133: =SUM(D112:D132) -> 0 | E133: =SUM(E112:E132) -> 0 | F133: =SUM(F112:F132) -> 0 | G133: =SUM(G112:G132) -> 0 | H133: =SUM(H112:H132) -> 0 | I133: =IFERROR(E133/D133,"") | J133: =IFERROR(H133/E133,"") | K133: =SUM(K112:K132) -> 0 | M133: =SUM(M112:M132) -> 0 | N133: =IFERROR(H133-Wk7!H133,"") -> 0 | O133: =IFERROR(D133-Wk7!D133,"") -> 0 | P133: =SUM(P112:P132) -> 0 | Q133: =SUM(Q112:Q132) -> 0 | R133: =IFERROR(INDEX('Last Year'!$C$6:$C$369,MATCH(B133-364,'Last Year'!$B$6:$B$369,0)),"") -> 0 | S133: =IFERROR(H133/R133-1,"")
A134: =TEXT(Setup!$C$5+55,"dddd") -> Sunday | B134: =Setup!$C$5+55 -> 46082 | C134: 9.00 - 9.30 | P134: =IFERROR(H134/Setup!$C$6,"") -> 0 | Q134: =IFERROR(H134-P134,"") -> 0
A135: =TEXT(Setup!$C$5+55,"dddd") -> Sunday | B135: =Setup!$C$5+55 -> 46082 | C135: 9.30 - 10.00 | P135: =IFERROR(H135/Setup!$C$6,"") -> 0 | Q135: =IFERROR(H135-P135,"") -> 0
A136: =TEXT(Setup!$C$5+55,"dddd") -> Sunday | B136: =Setup!$C$5+55 -> 46082 | C136: 10.00 - 10.30 | P136: =IFERROR(H136/Setup!$C$6,"") -> 0 | Q136: =IFERROR(H136-P136,"") -> 0
A137: =TEXT(Setup!$C$5+55,"dddd") -> Sunday | B137: =Setup!$C$5+55 -> 46082 | C137: 10.30 - 11.00 | P137: =IFERROR(H137/Setup!$C$6,"") -> 0 | Q137: =IFERROR(H137-P137,"") -> 0
A138: =TEXT(Setup!$C$5+55,"dddd") -> Sunday | B138: =Setup!$C$5+55 -> 46082 | C138: 11.00 - 11.30 | P138: =IFERROR(H138/Setup!$C$6,"") -> 0 | Q138: =IFERROR(H138-P138,"") -> 0
A139: =TEXT(Setup!$C$5+55,"dddd") -> Sunday | B139: =Setup!$C$5+55 -> 46082 | C139: 11.30 - 12.00 | P139: =IFERROR(H139/Setup!$C$6,"") -> 0 | Q139: =IFERROR(H139-P139,"") -> 0
A140: =TEXT(Setup!$C$5+55,"dddd") -> Sunday | B140: =Setup!$C$5+55 -> 46082 | C140: 12.00 - 12.30 | P140: =IFERROR(H140/Setup!$C$6,"") -> 0 | Q140: =IFERROR(H140-P140,"") -> 0
A141: =TEXT(Setup!$C$5+55,"dddd") -> Sunday | B141: =Setup!$C$5+55 -> 46082 | C141: 12.30 - 13.00 | P141: =IFERROR(H141/Setup!$C$6,"") -> 0 | Q141: =IFERROR(H141-P141,"") -> 0
A142: =TEXT(Setup!$C$5+55,"dddd") -> Sunday | B142: =Setup!$C$5+55 -> 46082 | C142: 13.00 - 13.30 | P142: =IFERROR(H142/Setup!$C$6,"") -> 0 | Q142: =IFERROR(H142-P142,"") -> 0
A143: =TEXT(Setup!$C$5+55,"dddd") -> Sunday | B143: =Setup!$C$5+55 -> 46082 | C143: 13.30 - 14.00 | P143: =IFERROR(H143/Setup!$C$6,"") -> 0 | Q143: =IFERROR(H143-P143,"") -> 0
A144: =TEXT(Setup!$C$5+55,"dddd") -> Sunday | B144: =Setup!$C$5+55 -> 46082 | C144: 14.00 - 14.30 | P144: =IFERROR(H144/Setup!$C$6,"") -> 0 | Q144: =IFERROR(H144-P144,"") -> 0
A145: =TEXT(Setup!$C$5+55,"dddd") -> Sunday | B145: =Setup!$C$5+55 -> 46082 | C145: 14.30 - 15.00 | P145: =IFERROR(H145/Setup!$C$6,"") -> 0 | Q145: =IFERROR(H145-P145,"") -> 0
... A154: =TEXT(Setup!$C$5+55,"dddd") -> Sunday | B154: =Setup!$C$5+55 -> 46082 | C154: ONLINE | P154: =IFERROR(H154/Setup!$C$6,"") -> 0 | Q154: =IFERROR(H154-P154,"") -> 0
A155: =TEXT(Setup!$C$5+55,"dddd") -> Sunday | B155: =Setup!$C$5+55 -> 46082 | C155: TOTAL | D155: =SUM(D134:D154) -> 0 | E155: =SUM(E134:E154) -> 0 | F155: =SUM(F134:F154) -> 0 | G155: =SUM(G134:G154) -> 0 | H155: =SUM(H134:H154) -> 0 | I155: =IFERROR(E155/D155,"") | J155: =IFERROR(H155/E155,"") | K155: =SUM(K134:K154) -> 0 | M155: =SUM(M134:M154) -> 0 | N155: =IFERROR(H155-Wk7!H155,"") -> 0 | O155: =IFERROR(D155-Wk7!D155,"") -> 0 | P155: =SUM(P134:P154) -> 0 | Q155: =SUM(Q134:Q154) -> 0 | R155: =IFERROR(INDEX('Last Year'!$C$6:$C$369,MATCH(B155-364,'Last Year'!$B$6:$B$369,0)),"") -> 0 | S155: =IFERROR(H155/R155-1,"")
C156: FULL WEEK | D156: =D23+D45+D67+D89+D111+D133+D155 -> 0 | E156: =E23+E45+E67+E89+E111+E133+E155 -> 0 | F156: =F23+F45+F67+F89+F111+F133+F155 -> 0 | G156: =G23+G45+G67+G89+G111+G133+G155 -> 0 | H156: =H23+H45+H67+H89+H111+H133+H155 -> 0 | I156: =IFERROR(E156/D156,"") | J156: =IFERROR(H156/E156,"") | K156: =K23+K45+K67+K89+K111+K133+K155 -> 0 | M156: =M23+M45+M67+M89+M111+M133+M155 -> 0 | P156: =P23+P45+P67+P89+P111+P133+P155 -> 0 | Q156: =Q23+Q45+Q67+Q89+Q111+Q133+Q155 -> 0 | R156: =R23+R45+R67+R89+R111+R133+R155 -> 0 | S156: =IFERROR(H156/R156-1,"")
...

Sheet Wk9
A1: Day | B1: Date | C1: Time | D1: Customers In | E1: Sales | F1: Vouchers Used | G1: Walk In/Out | H1: Sale Amount | I1: Conversion | J1: Avg Sale | K1: Tracked Category | L1: Notes | M1: Cash | N1: vs Last Wk € | O1: vs Last Wk Cust | P1: Est. Cost | Q1: Est. Profit | R1: Last Year Day | S1: vs Last Year
A2: =TEXT(Setup!$C$5+56,"dddd") -> Monday | B2: =Setup!$C$5+56 -> 46083 | C2: 9.00 - 9.30 | P2: =IFERROR(H2/Setup!$C$6,"") -> 0 | Q2: =IFERROR(H2-P2,"") -> 0
A3: =TEXT(Setup!$C$5+56,"dddd") -> Monday | B3: =Setup!$C$5+56 -> 46083 | C3: 9.30 - 10.00 | P3: =IFERROR(H3/Setup!$C$6,"") -> 0 | Q3: =IFERROR(H3-P3,"") -> 0
A4: =TEXT(Setup!$C$5+56,"dddd") -> Monday | B4: =Setup!$C$5+56 -> 46083 | C4: 10.00 - 10.30 | P4: =IFERROR(H4/Setup!$C$6,"") -> 0 | Q4: =IFERROR(H4-P4,"") -> 0
A5: =TEXT(Setup!$C$5+56,"dddd") -> Monday | B5: =Setup!$C$5+56 -> 46083 | C5: 10.30 - 11.00 | P5: =IFERROR(H5/Setup!$C$6,"") -> 0 | Q5: =IFERROR(H5-P5,"") -> 0
A6: =TEXT(Setup!$C$5+56,"dddd") -> Monday | B6: =Setup!$C$5+56 -> 46083 | C6: 11.00 - 11.30 | P6: =IFERROR(H6/Setup!$C$6,"") -> 0 | Q6: =IFERROR(H6-P6,"") -> 0
A7: =TEXT(Setup!$C$5+56,"dddd") -> Monday | B7: =Setup!$C$5+56 -> 46083 | C7: 11.30 - 12.00 | P7: =IFERROR(H7/Setup!$C$6,"") -> 0 | Q7: =IFERROR(H7-P7,"") -> 0
A8: =TEXT(Setup!$C$5+56,"dddd") -> Monday | B8: =Setup!$C$5+56 -> 46083 | C8: 12.00 - 12.30 | P8: =IFERROR(H8/Setup!$C$6,"") -> 0 | Q8: =IFERROR(H8-P8,"") -> 0
A9: =TEXT(Setup!$C$5+56,"dddd") -> Monday | B9: =Setup!$C$5+56 -> 46083 | C9: 12.30 - 13.00 | P9: =IFERROR(H9/Setup!$C$6,"") -> 0 | Q9: =IFERROR(H9-P9,"") -> 0
A10: =TEXT(Setup!$C$5+56,"dddd") -> Monday | B10: =Setup!$C$5+56 -> 46083 | C10: 13.00 - 13.30 | P10: =IFERROR(H10/Setup!$C$6,"") -> 0 | Q10: =IFERROR(H10-P10,"") -> 0
A11: =TEXT(Setup!$C$5+56,"dddd") -> Monday | B11: =Setup!$C$5+56 -> 46083 | C11: 13.30 - 14.00 | P11: =IFERROR(H11/Setup!$C$6,"") -> 0 | Q11: =IFERROR(H11-P11,"") -> 0
A12: =TEXT(Setup!$C$5+56,"dddd") -> Monday | B12: =Setup!$C$5+56 -> 46083 | C12: 14.00 - 14.30 | P12: =IFERROR(H12/Setup!$C$6,"") -> 0 | Q12: =IFERROR(H12-P12,"") -> 0
A13: =TEXT(Setup!$C$5+56,"dddd") -> Monday | B13: =Setup!$C$5+56 -> 46083 | C13: 14.30 - 15.00 | P13: =IFERROR(H13/Setup!$C$6,"") -> 0 | Q13: =IFERROR(H13-P13,"") -> 0
... A22: =TEXT(Setup!$C$5+56,"dddd") -> Monday | B22: =Setup!$C$5+56 -> 46083 | C22: ONLINE | P22: =IFERROR(H22/Setup!$C$6,"") -> 0 | Q22: =IFERROR(H22-P22,"") -> 0
A23: =TEXT(Setup!$C$5+56,"dddd") -> Monday | B23: =Setup!$C$5+56 -> 46083 | C23: TOTAL | D23: =SUM(D2:D22) -> 0 | E23: =SUM(E2:E22) -> 0 | F23: =SUM(F2:F22) -> 0 | G23: =SUM(G2:G22) -> 0 | H23: =SUM(H2:H22) -> 0 | I23: =IFERROR(E23/D23,"") | J23: =IFERROR(H23/E23,"") | K23: =SUM(K2:K22) -> 0 | M23: =SUM(M2:M22) -> 0 | N23: =IFERROR(H23-Wk8!H23,"") -> 0 | O23: =IFERROR(D23-Wk8!D23,"") -> 0 | P23: =SUM(P2:P22) -> 0 | Q23: =SUM(Q2:Q22) -> 0 | R23: =IFERROR(INDEX('Last Year'!$C$6:$C$369,MATCH(B23-364,'Last Year'!$B$6:$B$369,0)),"") -> 0 | S23: =IFERROR(H23/R23-1,"")
A24: =TEXT(Setup!$C$5+57,"dddd") -> Tuesday | B24: =Setup!$C$5+57 -> 46084 | C24: 9.00 - 9.30 | P24: =IFERROR(H24/Setup!$C$6,"") -> 0 | Q24: =IFERROR(H24-P24,"") -> 0
A25: =TEXT(Setup!$C$5+57,"dddd") -> Tuesday | B25: =Setup!$C$5+57 -> 46084 | C25: 9.30 - 10.00 | P25: =IFERROR(H25/Setup!$C$6,"") -> 0 | Q25: =IFERROR(H25-P25,"") -> 0
A26: =TEXT(Setup!$C$5+57,"dddd") -> Tuesday | B26: =Setup!$C$5+57 -> 46084 | C26: 10.00 - 10.30 | P26: =IFERROR(H26/Setup!$C$6,"") -> 0 | Q26: =IFERROR(H26-P26,"") -> 0
A27: =TEXT(Setup!$C$5+57,"dddd") -> Tuesday | B27: =Setup!$C$5+57 -> 46084 | C27: 10.30 - 11.00 | P27: =IFERROR(H27/Setup!$C$6,"") -> 0 | Q27: =IFERROR(H27-P27,"") -> 0
A28: =TEXT(Setup!$C$5+57,"dddd") -> Tuesday | B28: =Setup!$C$5+57 -> 46084 | C28: 11.00 - 11.30 | P28: =IFERROR(H28/Setup!$C$6,"") -> 0 | Q28: =IFERROR(H28-P28,"") -> 0
A29: =TEXT(Setup!$C$5+57,"dddd") -> Tuesday | B29: =Setup!$C$5+57 -> 46084 | C29: 11.30 - 12.00 | P29: =IFERROR(H29/Setup!$C$6,"") -> 0 | Q29: =IFERROR(H29-P29,"") -> 0
A30: =TEXT(Setup!$C$5+57,"dddd") -> Tuesday | B30: =Setup!$C$5+57 -> 46084 | C30: 12.00 - 12.30 | P30: =IFERROR(H30/Setup!$C$6,"") -> 0 | Q30: =IFERROR(H30-P30,"") -> 0
A31: =TEXT(Setup!$C$5+57,"dddd") -> Tuesday | B31: =Setup!$C$5+57 -> 46084 | C31: 12.30 - 13.00 | P31: =IFERROR(H31/Setup!$C$6,"") -> 0 | Q31: =IFERROR(H31-P31,"") -> 0
A32: =TEXT(Setup!$C$5+57,"dddd") -> Tuesday | B32: =Setup!$C$5+57 -> 46084 | C32: 13.00 - 13.30 | P32: =IFERROR(H32/Setup!$C$6,"") -> 0 | Q32: =IFERROR(H32-P32,"") -> 0
A33: =TEXT(Setup!$C$5+57,"dddd") -> Tuesday | B33: =Setup!$C$5+57 -> 46084 | C33: 13.30 - 14.00 | P33: =IFERROR(H33/Setup!$C$6,"") -> 0 | Q33: =IFERROR(H33-P33,"") -> 0
A34: =TEXT(Setup!$C$5+57,"dddd") -> Tuesday | B34: =Setup!$C$5+57 -> 46084 | C34: 14.00 - 14.30 | P34: =IFERROR(H34/Setup!$C$6,"") -> 0 | Q34: =IFERROR(H34-P34,"") -> 0
A35: =TEXT(Setup!$C$5+57,"dddd") -> Tuesday | B35: =Setup!$C$5+57 -> 46084 | C35: 14.30 - 15.00 | P35: =IFERROR(H35/Setup!$C$6,"") -> 0 | Q35: =IFERROR(H35-P35,"") -> 0
... A44: =TEXT(Setup!$C$5+57,"dddd") -> Tuesday | B44: =Setup!$C$5+57 -> 46084 | C44: ONLINE | P44: =IFERROR(H44/Setup!$C$6,"") -> 0 | Q44: =IFERROR(H44-P44,"") -> 0
A45: =TEXT(Setup!$C$5+57,"dddd") -> Tuesday | B45: =Setup!$C$5+57 -> 46084 | C45: TOTAL | D45: =SUM(D24:D44) -> 0 | E45: =SUM(E24:E44) -> 0 | F45: =SUM(F24:F44) -> 0 | G45: =SUM(G24:G44) -> 0 | H45: =SUM(H24:H44) -> 0 | I45: =IFERROR(E45/D45,"") | J45: =IFERROR(H45/E45,"") | K45: =SUM(K24:K44) -> 0 | M45: =SUM(M24:M44) -> 0 | N45: =IFERROR(H45-Wk8!H45,"") -> 0 | O45: =IFERROR(D45-Wk8!D45,"") -> 0 | P45: =SUM(P24:P44) -> 0 | Q45: =SUM(Q24:Q44) -> 0 | R45: =IFERROR(INDEX('Last Year'!$C$6:$C$369,MATCH(B45-364,'Last Year'!$B$6:$B$369,0)),"") -> 0 | S45: =IFERROR(H45/R45-1,"")
A46: =TEXT(Setup!$C$5+58,"dddd") -> Wednesday | B46: =Setup!$C$5+58 -> 46085 | C46: 9.00 - 9.30 | P46: =IFERROR(H46/Setup!$C$6,"") -> 0 | Q46: =IFERROR(H46-P46,"") -> 0
A47: =TEXT(Setup!$C$5+58,"dddd") -> Wednesday | B47: =Setup!$C$5+58 -> 46085 | C47: 9.30 - 10.00 | P47: =IFERROR(H47/Setup!$C$6,"") -> 0 | Q47: =IFERROR(H47-P47,"") -> 0
A48: =TEXT(Setup!$C$5+58,"dddd") -> Wednesday | B48: =Setup!$C$5+58 -> 46085 | C48: 10.00 - 10.30 | P48: =IFERROR(H48/Setup!$C$6,"") -> 0 | Q48: =IFERROR(H48-P48,"") -> 0
A49: =TEXT(Setup!$C$5+58,"dddd") -> Wednesday | B49: =Setup!$C$5+58 -> 46085 | C49: 10.30 - 11.00 | P49: =IFERROR(H49/Setup!$C$6,"") -> 0 | Q49: =IFERROR(H49-P49,"") -> 0
A50: =TEXT(Setup!$C$5+58,"dddd") -> Wednesday | B50: =Setup!$C$5+58 -> 46085 | C50: 11.00 - 11.30 | P50: =IFERROR(H50/Setup!$C$6,"") -> 0 | Q50: =IFERROR(H50-P50,"") -> 0
A51: =TEXT(Setup!$C$5+58,"dddd") -> Wednesday | B51: =Setup!$C$5+58 -> 46085 | C51: 11.30 - 12.00 | P51: =IFERROR(H51/Setup!$C$6,"") -> 0 | Q51: =IFERROR(H51-P51,"") -> 0
A52: =TEXT(Setup!$C$5+58,"dddd") -> Wednesday | B52: =Setup!$C$5+58 -> 46085 | C52: 12.00 - 12.30 | P52: =IFERROR(H52/Setup!$C$6,"") -> 0 | Q52: =IFERROR(H52-P52,"") -> 0
A53: =TEXT(Setup!$C$5+58,"dddd") -> Wednesday | B53: =Setup!$C$5+58 -> 46085 | C53: 12.30 - 13.00 | P53: =IFERROR(H53/Setup!$C$6,"") -> 0 | Q53: =IFERROR(H53-P53,"") -> 0
A54: =TEXT(Setup!$C$5+58,"dddd") -> Wednesday | B54: =Setup!$C$5+58 -> 46085 | C54: 13.00 - 13.30 | P54: =IFERROR(H54/Setup!$C$6,"") -> 0 | Q54: =IFERROR(H54-P54,"") -> 0
A55: =TEXT(Setup!$C$5+58,"dddd") -> Wednesday | B55: =Setup!$C$5+58 -> 46085 | C55: 13.30 - 14.00 | P55: =IFERROR(H55/Setup!$C$6,"") -> 0 | Q55: =IFERROR(H55-P55,"") -> 0
A56: =TEXT(Setup!$C$5+58,"dddd") -> Wednesday | B56: =Setup!$C$5+58 -> 46085 | C56: 14.00 - 14.30 | P56: =IFERROR(H56/Setup!$C$6,"") -> 0 | Q56: =IFERROR(H56-P56,"") -> 0
A57: =TEXT(Setup!$C$5+58,"dddd") -> Wednesday | B57: =Setup!$C$5+58 -> 46085 | C57: 14.30 - 15.00 | P57: =IFERROR(H57/Setup!$C$6,"") -> 0 | Q57: =IFERROR(H57-P57,"") -> 0
... A66: =TEXT(Setup!$C$5+58,"dddd") -> Wednesday | B66: =Setup!$C$5+58 -> 46085 | C66: ONLINE | P66: =IFERROR(H66/Setup!$C$6,"") -> 0 | Q66: =IFERROR(H66-P66,"") -> 0
A67: =TEXT(Setup!$C$5+58,"dddd") -> Wednesday | B67: =Setup!$C$5+58 -> 46085 | C67: TOTAL | D67: =SUM(D46:D66) -> 0 | E67: =SUM(E46:E66) -> 0 | F67: =SUM(F46:F66) -> 0 | G67: =SUM(G46:G66) -> 0 | H67: =SUM(H46:H66) -> 0 | I67: =IFERROR(E67/D67,"") | J67: =IFERROR(H67/E67,"") | K67: =SUM(K46:K66) -> 0 | M67: =SUM(M46:M66) -> 0 | N67: =IFERROR(H67-Wk8!H67,"") -> 0 | O67: =IFERROR(D67-Wk8!D67,"") -> 0 | P67: =SUM(P46:P66) -> 0 | Q67: =SUM(Q46:Q66) -> 0 | R67: =IFERROR(INDEX('Last Year'!$C$6:$C$369,MATCH(B67-364,'Last Year'!$B$6:$B$369,0)),"") -> 0 | S67: =IFERROR(H67/R67-1,"")
A68: =TEXT(Setup!$C$5+59,"dddd") -> Thursday | B68: =Setup!$C$5+59 -> 46086 | C68: 9.00 - 9.30 | P68: =IFERROR(H68/Setup!$C$6,"") -> 0 | Q68: =IFERROR(H68-P68,"") -> 0
A69: =TEXT(Setup!$C$5+59,"dddd") -> Thursday | B69: =Setup!$C$5+59 -> 46086 | C69: 9.30 - 10.00 | P69: =IFERROR(H69/Setup!$C$6,"") -> 0 | Q69: =IFERROR(H69-P69,"") -> 0
A70: =TEXT(Setup!$C$5+59,"dddd") -> Thursday | B70: =Setup!$C$5+59 -> 46086 | C70: 10.00 - 10.30 | P70: =IFERROR(H70/Setup!$C$6,"") -> 0 | Q70: =IFERROR(H70-P70,"") -> 0
A71: =TEXT(Setup!$C$5+59,"dddd") -> Thursday | B71: =Setup!$C$5+59 -> 46086 | C71: 10.30 - 11.00 | P71: =IFERROR(H71/Setup!$C$6,"") -> 0 | Q71: =IFERROR(H71-P71,"") -> 0
A72: =TEXT(Setup!$C$5+59,"dddd") -> Thursday | B72: =Setup!$C$5+59 -> 46086 | C72: 11.00 - 11.30 | P72: =IFERROR(H72/Setup!$C$6,"") -> 0 | Q72: =IFERROR(H72-P72,"") -> 0
A73: =TEXT(Setup!$C$5+59,"dddd") -> Thursday | B73: =Setup!$C$5+59 -> 46086 | C73: 11.30 - 12.00 | P73: =IFERROR(H73/Setup!$C$6,"") -> 0 | Q73: =IFERROR(H73-P73,"") -> 0
A74: =TEXT(Setup!$C$5+59,"dddd") -> Thursday | B74: =Setup!$C$5+59 -> 46086 | C74: 12.00 - 12.30 | P74: =IFERROR(H74/Setup!$C$6,"") -> 0 | Q74: =IFERROR(H74-P74,"") -> 0
A75: =TEXT(Setup!$C$5+59,"dddd") -> Thursday | B75: =Setup!$C$5+59 -> 46086 | C75: 12.30 - 13.00 | P75: =IFERROR(H75/Setup!$C$6,"") -> 0 | Q75: =IFERROR(H75-P75,"") -> 0
A76: =TEXT(Setup!$C$5+59,"dddd") -> Thursday | B76: =Setup!$C$5+59 -> 46086 | C76: 13.00 - 13.30 | P76: =IFERROR(H76/Setup!$C$6,"") -> 0 | Q76: =IFERROR(H76-P76,"") -> 0
A77: =TEXT(Setup!$C$5+59,"dddd") -> Thursday | B77: =Setup!$C$5+59 -> 46086 | C77: 13.30 - 14.00 | P77: =IFERROR(H77/Setup!$C$6,"") -> 0 | Q77: =IFERROR(H77-P77,"") -> 0
A78: =TEXT(Setup!$C$5+59,"dddd") -> Thursday | B78: =Setup!$C$5+59 -> 46086 | C78: 14.00 - 14.30 | P78: =IFERROR(H78/Setup!$C$6,"") -> 0 | Q78: =IFERROR(H78-P78,"") -> 0
A79: =TEXT(Setup!$C$5+59,"dddd") -> Thursday | B79: =Setup!$C$5+59 -> 46086 | C79: 14.30 - 15.00 | P79: =IFERROR(H79/Setup!$C$6,"") -> 0 | Q79: =IFERROR(H79-P79,"") -> 0
... A88: =TEXT(Setup!$C$5+59,"dddd") -> Thursday | B88: =Setup!$C$5+59 -> 46086 | C88: ONLINE | P88: =IFERROR(H88/Setup!$C$6,"") -> 0 | Q88: =IFERROR(H88-P88,"") -> 0
A89: =TEXT(Setup!$C$5+59,"dddd") -> Thursday | B89: =Setup!$C$5+59 -> 46086 | C89: TOTAL | D89: =SUM(D68:D88) -> 0 | E89: =SUM(E68:E88) -> 0 | F89: =SUM(F68:F88) -> 0 | G89: =SUM(G68:G88) -> 0 | H89: =SUM(H68:H88) -> 0 | I89: =IFERROR(E89/D89,"") | J89: =IFERROR(H89/E89,"") | K89: =SUM(K68:K88) -> 0 | M89: =SUM(M68:M88) -> 0 | N89: =IFERROR(H89-Wk8!H89,"") -> 0 | O89: =IFERROR(D89-Wk8!D89,"") -> 0 | P89: =SUM(P68:P88) -> 0 | Q89: =SUM(Q68:Q88) -> 0 | R89: =IFERROR(INDEX('Last Year'!$C$6:$C$369,MATCH(B89-364,'Last Year'!$B$6:$B$369,0)),"") -> 0 | S89: =IFERROR(H89/R89-1,"")
A90: =TEXT(Setup!$C$5+60,"dddd") -> Friday | B90: =Setup!$C$5+60 -> 46087 | C90: 9.00 - 9.30 | P90: =IFERROR(H90/Setup!$C$6,"") -> 0 | Q90: =IFERROR(H90-P90,"") -> 0
A91: =TEXT(Setup!$C$5+60,"dddd") -> Friday | B91: =Setup!$C$5+60 -> 46087 | C91: 9.30 - 10.00 | P91: =IFERROR(H91/Setup!$C$6,"") -> 0 | Q91: =IFERROR(H91-P91,"") -> 0
A92: =TEXT(Setup!$C$5+60,"dddd") -> Friday | B92: =Setup!$C$5+60 -> 46087 | C92: 10.00 - 10.30 | P92: =IFERROR(H92/Setup!$C$6,"") -> 0 | Q92: =IFERROR(H92-P92,"") -> 0
A93: =TEXT(Setup!$C$5+60,"dddd") -> Friday | B93: =Setup!$C$5+60 -> 46087 | C93: 10.30 - 11.00 | P93: =IFERROR(H93/Setup!$C$6,"") -> 0 | Q93: =IFERROR(H93-P93,"") -> 0
A94: =TEXT(Setup!$C$5+60,"dddd") -> Friday | B94: =Setup!$C$5+60 -> 46087 | C94: 11.00 - 11.30 | P94: =IFERROR(H94/Setup!$C$6,"") -> 0 | Q94: =IFERROR(H94-P94,"") -> 0
A95: =TEXT(Setup!$C$5+60,"dddd") -> Friday | B95: =Setup!$C$5+60 -> 46087 | C95: 11.30 - 12.00 | P95: =IFERROR(H95/Setup!$C$6,"") -> 0 | Q95: =IFERROR(H95-P95,"") -> 0
A96: =TEXT(Setup!$C$5+60,"dddd") -> Friday | B96: =Setup!$C$5+60 -> 46087 | C96: 12.00 - 12.30 | P96: =IFERROR(H96/Setup!$C$6,"") -> 0 | Q96: =IFERROR(H96-P96,"") -> 0
A97: =TEXT(Setup!$C$5+60,"dddd") -> Friday | B97: =Setup!$C$5+60 -> 46087 | C97: 12.30 - 13.00 | P97: =IFERROR(H97/Setup!$C$6,"") -> 0 | Q97: =IFERROR(H97-P97,"") -> 0
A98: =TEXT(Setup!$C$5+60,"dddd") -> Friday | B98: =Setup!$C$5+60 -> 46087 | C98: 13.00 - 13.30 | P98: =IFERROR(H98/Setup!$C$6,"") -> 0 | Q98: =IFERROR(H98-P98,"") -> 0
A99: =TEXT(Setup!$C$5+60,"dddd") -> Friday | B99: =Setup!$C$5+60 -> 46087 | C99: 13.30 - 14.00 | P99: =IFERROR(H99/Setup!$C$6,"") -> 0 | Q99: =IFERROR(H99-P99,"") -> 0
A100: =TEXT(Setup!$C$5+60,"dddd") -> Friday | B100: =Setup!$C$5+60 -> 46087 | C100: 14.00 - 14.30 | P100: =IFERROR(H100/Setup!$C$6,"") -> 0 | Q100: =IFERROR(H100-P100,"") -> 0
A101: =TEXT(Setup!$C$5+60,"dddd") -> Friday | B101: =Setup!$C$5+60 -> 46087 | C101: 14.30 - 15.00 | P101: =IFERROR(H101/Setup!$C$6,"") -> 0 | Q101: =IFERROR(H101-P101,"") -> 0
... A110: =TEXT(Setup!$C$5+60,"dddd") -> Friday | B110: =Setup!$C$5+60 -> 46087 | C110: ONLINE | P110: =IFERROR(H110/Setup!$C$6,"") -> 0 | Q110: =IFERROR(H110-P110,"") -> 0
A111: =TEXT(Setup!$C$5+60,"dddd") -> Friday | B111: =Setup!$C$5+60 -> 46087 | C111: TOTAL | D111: =SUM(D90:D110) -> 0 | E111: =SUM(E90:E110) -> 0 | F111: =SUM(F90:F110) -> 0 | G111: =SUM(G90:G110) -> 0 | H111: =SUM(H90:H110) -> 0 | I111: =IFERROR(E111/D111,"") | J111: =IFERROR(H111/E111,"") | K111: =SUM(K90:K110) -> 0 | M111: =SUM(M90:M110) -> 0 | N111: =IFERROR(H111-Wk8!H111,"") -> 0 | O111: =IFERROR(D111-Wk8!D111,"") -> 0 | P111: =SUM(P90:P110) -> 0 | Q111: =SUM(Q90:Q110) -> 0 | R111: =IFERROR(INDEX('Last Year'!$C$6:$C$369,MATCH(B111-364,'Last Year'!$B$6:$B$369,0)),"") -> 0 | S111: =IFERROR(H111/R111-1,"")
A112: =TEXT(Setup!$C$5+61,"dddd") -> Saturday | B112: =Setup!$C$5+61 -> 46088 | C112: 9.00 - 9.30 | P112: =IFERROR(H112/Setup!$C$6,"") -> 0 | Q112: =IFERROR(H112-P112,"") -> 0
A113: =TEXT(Setup!$C$5+61,"dddd") -> Saturday | B113: =Setup!$C$5+61 -> 46088 | C113: 9.30 - 10.00 | P113: =IFERROR(H113/Setup!$C$6,"") -> 0 | Q113: =IFERROR(H113-P113,"") -> 0
A114: =TEXT(Setup!$C$5+61,"dddd") -> Saturday | B114: =Setup!$C$5+61 -> 46088 | C114: 10.00 - 10.30 | P114: =IFERROR(H114/Setup!$C$6,"") -> 0 | Q114: =IFERROR(H114-P114,"") -> 0
A115: =TEXT(Setup!$C$5+61,"dddd") -> Saturday | B115: =Setup!$C$5+61 -> 46088 | C115: 10.30 - 11.00 | P115: =IFERROR(H115/Setup!$C$6,"") -> 0 | Q115: =IFERROR(H115-P115,"") -> 0
A116: =TEXT(Setup!$C$5+61,"dddd") -> Saturday | B116: =Setup!$C$5+61 -> 46088 | C116: 11.00 - 11.30 | P116: =IFERROR(H116/Setup!$C$6,"") -> 0 | Q116: =IFERROR(H116-P116,"") -> 0
A117: =TEXT(Setup!$C$5+61,"dddd") -> Saturday | B117: =Setup!$C$5+61 -> 46088 | C117: 11.30 - 12.00 | P117: =IFERROR(H117/Setup!$C$6,"") -> 0 | Q117: =IFERROR(H117-P117,"") -> 0
A118: =TEXT(Setup!$C$5+61,"dddd") -> Saturday | B118: =Setup!$C$5+61 -> 46088 | C118: 12.00 - 12.30 | P118: =IFERROR(H118/Setup!$C$6,"") -> 0 | Q118: =IFERROR(H118-P118,"") -> 0
A119: =TEXT(Setup!$C$5+61,"dddd") -> Saturday | B119: =Setup!$C$5+61 -> 46088 | C119: 12.30 - 13.00 | P119: =IFERROR(H119/Setup!$C$6,"") -> 0 | Q119: =IFERROR(H119-P119,"") -> 0
A120: =TEXT(Setup!$C$5+61,"dddd") -> Saturday | B120: =Setup!$C$5+61 -> 46088 | C120: 13.00 - 13.30 | P120: =IFERROR(H120/Setup!$C$6,"") -> 0 | Q120: =IFERROR(H120-P120,"") -> 0
A121: =TEXT(Setup!$C$5+61,"dddd") -> Saturday | B121: =Setup!$C$5+61 -> 46088 | C121: 13.30 - 14.00 | P121: =IFERROR(H121/Setup!$C$6,"") -> 0 | Q121: =IFERROR(H121-P121,"") -> 0
A122: =TEXT(Setup!$C$5+61,"dddd") -> Saturday | B122: =Setup!$C$5+61 -> 46088 | C122: 14.00 - 14.30 | P122: =IFERROR(H122/Setup!$C$6,"") -> 0 | Q122: =IFERROR(H122-P122,"") -> 0
A123: =TEXT(Setup!$C$5+61,"dddd") -> Saturday | B123: =Setup!$C$5+61 -> 46088 | C123: 14.30 - 15.00 | P123: =IFERROR(H123/Setup!$C$6,"") -> 0 | Q123: =IFERROR(H123-P123,"") -> 0
... A132: =TEXT(Setup!$C$5+61,"dddd") -> Saturday | B132: =Setup!$C$5+61 -> 46088 | C132: ONLINE | P132: =IFERROR(H132/Setup!$C$6,"") -> 0 | Q132: =IFERROR(H132-P132,"") -> 0
A133: =TEXT(Setup!$C$5+61,"dddd") -> Saturday | B133: =Setup!$C$5+61 -> 46088 | C133: TOTAL | D133: =SUM(D112:D132) -> 0 | E133: =SUM(E112:E132) -> 0 | F133: =SUM(F112:F132) -> 0 | G133: =SUM(G112:G132) -> 0 | H133: =SUM(H112:H132) -> 0 | I133: =IFERROR(E133/D133,"") | J133: =IFERROR(H133/E133,"") | K133: =SUM(K112:K132) -> 0 | M133: =SUM(M112:M132) -> 0 | N133: =IFERROR(H133-Wk8!H133,"") -> 0 | O133: =IFERROR(D133-Wk8!D133,"") -> 0 | P133: =SUM(P112:P132) -> 0 | Q133: =SUM(Q112:Q132) -> 0 | R133: =IFERROR(INDEX('Last Year'!$C$6:$C$369,MATCH(B133-364,'Last Year'!$B$6:$B$369,0)),"") -> 0 | S133: =IFERROR(H133/R133-1,"")
A134: =TEXT(Setup!$C$5+62,"dddd") -> Sunday | B134: =Setup!$C$5+62 -> 46089 | C134: 9.00 - 9.30 | P134: =IFERROR(H134/Setup!$C$6,"") -> 0 | Q134: =IFERROR(H134-P134,"") -> 0
A135: =TEXT(Setup!$C$5+62,"dddd") -> Sunday | B135: =Setup!$C$5+62 -> 46089 | C135: 9.30 - 10.00 | P135: =IFERROR(H135/Setup!$C$6,"") -> 0 | Q135: =IFERROR(H135-P135,"") -> 0
A136: =TEXT(Setup!$C$5+62,"dddd") -> Sunday | B136: =Setup!$C$5+62 -> 46089 | C136: 10.00 - 10.30 | P136: =IFERROR(H136/Setup!$C$6,"") -> 0 | Q136: =IFERROR(H136-P136,"") -> 0
A137: =TEXT(Setup!$C$5+62,"dddd") -> Sunday | B137: =Setup!$C$5+62 -> 46089 | C137: 10.30 - 11.00 | P137: =IFERROR(H137/Setup!$C$6,"") -> 0 | Q137: =IFERROR(H137-P137,"") -> 0
A138: =TEXT(Setup!$C$5+62,"dddd") -> Sunday | B138: =Setup!$C$5+62 -> 46089 | C138: 11.00 - 11.30 | P138: =IFERROR(H138/Setup!$C$6,"") -> 0 | Q138: =IFERROR(H138-P138,"") -> 0
A139: =TEXT(Setup!$C$5+62,"dddd") -> Sunday | B139: =Setup!$C$5+62 -> 46089 | C139: 11.30 - 12.00 | P139: =IFERROR(H139/Setup!$C$6,"") -> 0 | Q139: =IFERROR(H139-P139,"") -> 0
A140: =TEXT(Setup!$C$5+62,"dddd") -> Sunday | B140: =Setup!$C$5+62 -> 46089 | C140: 12.00 - 12.30 | P140: =IFERROR(H140/Setup!$C$6,"") -> 0 | Q140: =IFERROR(H140-P140,"") -> 0
A141: =TEXT(Setup!$C$5+62,"dddd") -> Sunday | B141: =Setup!$C$5+62 -> 46089 | C141: 12.30 - 13.00 | P141: =IFERROR(H141/Setup!$C$6,"") -> 0 | Q141: =IFERROR(H141-P141,"") -> 0
A142: =TEXT(Setup!$C$5+62,"dddd") -> Sunday | B142: =Setup!$C$5+62 -> 46089 | C142: 13.00 - 13.30 | P142: =IFERROR(H142/Setup!$C$6,"") -> 0 | Q142: =IFERROR(H142-P142,"") -> 0
A143: =TEXT(Setup!$C$5+62,"dddd") -> Sunday | B143: =Setup!$C$5+62 -> 46089 | C143: 13.30 - 14.00 | P143: =IFERROR(H143/Setup!$C$6,"") -> 0 | Q143: =IFERROR(H143-P143,"") -> 0
A144: =TEXT(Setup!$C$5+62,"dddd") -> Sunday | B144: =Setup!$C$5+62 -> 46089 | C144: 14.00 - 14.30 | P144: =IFERROR(H144/Setup!$C$6,"") -> 0 | Q144: =IFERROR(H144-P144,"") -> 0
A145: =TEXT(Setup!$C$5+62,"dddd") -> Sunday | B145: =Setup!$C$5+62 -> 46089 | C145: 14.30 - 15.00 | P145: =IFERROR(H145/Setup!$C$6,"") -> 0 | Q145: =IFERROR(H145-P145,"") -> 0
... A154: =TEXT(Setup!$C$5+62,"dddd") -> Sunday | B154: =Setup!$C$5+62 -> 46089 | C154: ONLINE | P154: =IFERROR(H154/Setup!$C$6,"") -> 0 | Q154: =IFERROR(H154-P154,"") -> 0
A155: =TEXT(Setup!$C$5+62,"dddd") -> Sunday | B155: =Setup!$C$5+62 -> 46089 | C155: TOTAL | D155: =SUM(D134:D154) -> 0 | E155: =SUM(E134:E154) -> 0 | F155: =SUM(F134:F154) -> 0 | G155: =SUM(G134:G154) -> 0 | H155: =SUM(H134:H154) -> 0 | I155: =IFERROR(E155/D155,"") | J155: =IFERROR(H155/E155,"") | K155: =SUM(K134:K154) -> 0 | M155: =SUM(M134:M154) -> 0 | N155: =IFERROR(H155-Wk8!H155,"") -> 0 | O155: =IFERROR(D155-Wk8!D155,"") -> 0 | P155: =SUM(P134:P154) -> 0 | Q155: =SUM(Q134:Q154) -> 0 | R155: =IFERROR(INDEX('Last Year'!$C$6:$C$369,MATCH(B155-364,'Last Year'!$B$6:$B$369,0)),"") -> 0 | S155: =IFERROR(H155/R155-1,"")
C156: FULL WEEK | D156: =D23+D45+D67+D89+D111+D133+D155 -> 0 | E156: =E23+E45+E67+E89+E111+E133+E155 -> 0 | F156: =F23+F45+F67+F89+F111+F133+F155 -> 0 | G156: =G23+G45+G67+G89+G111+G133+G155 -> 0 | H156: =H23+H45+H67+H89+H111+H133+H155 -> 0 | I156: =IFERROR(E156/D156,"") | J156: =IFERROR(H156/E156,"") | K156: =K23+K45+K67+K89+K111+K133+K155 -> 0 | M156: =M23+M45+M67+M89+M111+M133+M155 -> 0 | P156: =P23+P45+P67+P89+P111+P133+P155 -> 0 | Q156: =Q23+Q45+Q67+Q89+Q111+Q133+Q155 -> 0 | R156: =R23+R45+R67+R89+R111+R133+R155 -> 0 | S156: =IFERROR(H156/R156-1,"")
...

Sheet Wk10
A1: Day | B1: Date | C1: Time | D1: Customers In | E1: Sales | F1: Vouchers Used | G1: Walk In/Out | H1: Sale Amount | I1: Conversion | J1: Avg Sale | K1: Tracked Category | L1: Notes | M1: Cash | N1: vs Last Wk € | O1: vs Last Wk Cust | P1: Est. Cost | Q1: Est. Profit | R1: Last Year Day | S1: vs Last Year
A2: =TEXT(Setup!$C$5+63,"dddd") -> Monday | B2: =Setup!$C$5+63 -> 46090 | C2: 9.00 - 9.30 | P2: =IFERROR(H2/Setup!$C$6,"") -> 0 | Q2: =IFERROR(H2-P2,"") -> 0
A3: =TEXT(Setup!$C$5+63,"dddd") -> Monday | B3: =Setup!$C$5+63 -> 46090 | C3: 9.30 - 10.00 | P3: =IFERROR(H3/Setup!$C$6,"") -> 0 | Q3: =IFERROR(H3-P3,"") -> 0
A4: =TEXT(Setup!$C$5+63,"dddd") -> Monday | B4: =Setup!$C$5+63 -> 46090 | C4: 10.00 - 10.30 | P4: =IFERROR(H4/Setup!$C$6,"") -> 0 | Q4: =IFERROR(H4-P4,"") -> 0
A5: =TEXT(Setup!$C$5+63,"dddd") -> Monday | B5: =Setup!$C$5+63 -> 46090 | C5: 10.30 - 11.00 | P5: =IFERROR(H5/Setup!$C$6,"") -> 0 | Q5: =IFERROR(H5-P5,"") -> 0
A6: =TEXT(Setup!$C$5+63,"dddd") -> Monday | B6: =Setup!$C$5+63 -> 46090 | C6: 11.00 - 11.30 | P6: =IFERROR(H6/Setup!$C$6,"") -> 0 | Q6: =IFERROR(H6-P6,"") -> 0
A7: =TEXT(Setup!$C$5+63,"dddd") -> Monday | B7: =Setup!$C$5+63 -> 46090 | C7: 11.30 - 12.00 | P7: =IFERROR(H7/Setup!$C$6,"") -> 0 | Q7: =IFERROR(H7-P7,"") -> 0
A8: =TEXT(Setup!$C$5+63,"dddd") -> Monday | B8: =Setup!$C$5+63 -> 46090 | C8: 12.00 - 12.30 | P8: =IFERROR(H8/Setup!$C$6,"") -> 0 | Q8: =IFERROR(H8-P8,"") -> 0
A9: =TEXT(Setup!$C$5+63,"dddd") -> Monday | B9: =Setup!$C$5+63 -> 46090 | C9: 12.30 - 13.00 | P9: =IFERROR(H9/Setup!$C$6,"") -> 0 | Q9: =IFERROR(H9-P9,"") -> 0
A10: =TEXT(Setup!$C$5+63,"dddd") -> Monday | B10: =Setup!$C$5+63 -> 46090 | C10: 13.00 - 13.30 | P10: =IFERROR(H10/Setup!$C$6,"") -> 0 | Q10: =IFERROR(H10-P10,"") -> 0
A11: =TEXT(Setup!$C$5+63,"dddd") -> Monday | B11: =Setup!$C$5+63 -> 46090 | C11: 13.30 - 14.00 | P11: =IFERROR(H11/Setup!$C$6,"") -> 0 | Q11: =IFERROR(H11-P11,"") -> 0
A12: =TEXT(Setup!$C$5+63,"dddd") -> Monday | B12: =Setup!$C$5+63 -> 46090 | C12: 14.00 - 14.30 | P12: =IFERROR(H12/Setup!$C$6,"") -> 0 | Q12: =IFERROR(H12-P12,"") -> 0
A13: =TEXT(Setup!$C$5+63,"dddd") -> Monday | B13: =Setup!$C$5+63 -> 46090 | C13: 14.30 - 15.00 | P13: =IFERROR(H13/Setup!$C$6,"") -> 0 | Q13: =IFERROR(H13-P13,"") -> 0
... A22: =TEXT(Setup!$C$5+63,"dddd") -> Monday | B22: =Setup!$C$5+63 -> 46090 | C22: ONLINE | P22: =IFERROR(H22/Setup!$C$6,"") -> 0 | Q22: =IFERROR(H22-P22,"") -> 0
A23: =TEXT(Setup!$C$5+63,"dddd") -> Monday | B23: =Setup!$C$5+63 -> 46090 | C23: TOTAL | D23: =SUM(D2:D22) -> 0 | E23: =SUM(E2:E22) -> 0 | F23: =SUM(F2:F22) -> 0 | G23: =SUM(G2:G22) -> 0 | H23: =SUM(H2:H22) -> 0 | I23: =IFERROR(E23/D23,"") | J23: =IFERROR(H23/E23,"") | K23: =SUM(K2:K22) -> 0 | M23: =SUM(M2:M22) -> 0 | N23: =IFERROR(H23-Wk9!H23,"") -> 0 | O23: =IFERROR(D23-Wk9!D23,"") -> 0 | P23: =SUM(P2:P22) -> 0 | Q23: =SUM(Q2:Q22) -> 0 | R23: =IFERROR(INDEX('Last Year'!$C$6:$C$369,MATCH(B23-364,'Last Year'!$B$6:$B$369,0)),"") -> 0 | S23: =IFERROR(H23/R23-1,"")
A24: =TEXT(Setup!$C$5+64,"dddd") -> Tuesday | B24: =Setup!$C$5+64 -> 46091 | C24: 9.00 - 9.30 | P24: =IFERROR(H24/Setup!$C$6,"") -> 0 | Q24: =IFERROR(H24-P24,"") -> 0
A25: =TEXT(Setup!$C$5+64,"dddd") -> Tuesday | B25: =Setup!$C$5+64 -> 46091 | C25: 9.30 - 10.00 | P25: =IFERROR(H25/Setup!$C$6,"") -> 0 | Q25: =IFERROR(H25-P25,"") -> 0
A26: =TEXT(Setup!$C$5+64,"dddd") -> Tuesday | B26: =Setup!$C$5+64 -> 46091 | C26: 10.00 - 10.30 | P26: =IFERROR(H26/Setup!$C$6,"") -> 0 | Q26: =IFERROR(H26-P26,"") -> 0
A27: =TEXT(Setup!$C$5+64,"dddd") -> Tuesday | B27: =Setup!$C$5+64 -> 46091 | C27: 10.30 - 11.00 | P27: =IFERROR(H27/Setup!$C$6,"") -> 0 | Q27: =IFERROR(H27-P27,"") -> 0
A28: =TEXT(Setup!$C$5+64,"dddd") -> Tuesday | B28: =Setup!$C$5+64 -> 46091 | C28: 11.00 - 11.30 | P28: =IFERROR(H28/Setup!$C$6,"") -> 0 | Q28: =IFERROR(H28-P28,"") -> 0
A29: =TEXT(Setup!$C$5+64,"dddd") -> Tuesday | B29: =Setup!$C$5+64 -> 46091 | C29: 11.30 - 12.00 | P29: =IFERROR(H29/Setup!$C$6,"") -> 0 | Q29: =IFERROR(H29-P29,"") -> 0
A30: =TEXT(Setup!$C$5+64,"dddd") -> Tuesday | B30: =Setup!$C$5+64 -> 46091 | C30: 12.00 - 12.30 | P30: =IFERROR(H30/Setup!$C$6,"") -> 0 | Q30: =IFERROR(H30-P30,"") -> 0
A31: =TEXT(Setup!$C$5+64,"dddd") -> Tuesday | B31: =Setup!$C$5+64 -> 46091 | C31: 12.30 - 13.00 | P31: =IFERROR(H31/Setup!$C$6,"") -> 0 | Q31: =IFERROR(H31-P31,"") -> 0
A32: =TEXT(Setup!$C$5+64,"dddd") -> Tuesday | B32: =Setup!$C$5+64 -> 46091 | C32: 13.00 - 13.30 | P32: =IFERROR(H32/Setup!$C$6,"") -> 0 | Q32: =IFERROR(H32-P32,"") -> 0
A33: =TEXT(Setup!$C$5+64,"dddd") -> Tuesday | B33: =Setup!$C$5+64 -> 46091 | C33: 13.30 - 14.00 | P33: =IFERROR(H33/Setup!$C$6,"") -> 0 | Q33: =IFERROR(H33-P33,"") -> 0
A34: =TEXT(Setup!$C$5+64,"dddd") -> Tuesday | B34: =Setup!$C$5+64 -> 46091 | C34: 14.00 - 14.30 | P34: =IFERROR(H34/Setup!$C$6,"") -> 0 | Q34: =IFERROR(H34-P34,"") -> 0
A35: =TEXT(Setup!$C$5+64,"dddd") -> Tuesday | B35: =Setup!$C$5+64 -> 46091 | C35: 14.30 - 15.00 | P35: =IFERROR(H35/Setup!$C$6,"") -> 0 | Q35: =IFERROR(H35-P35,"") -> 0
... A44: =TEXT(Setup!$C$5+64,"dddd") -> Tuesday | B44: =Setup!$C$5+64 -> 46091 | C44: ONLINE | P44: =IFERROR(H44/Setup!$C$6,"") -> 0 | Q44: =IFERROR(H44-P44,"") -> 0
A45: =TEXT(Setup!$C$5+64,"dddd") -> Tuesday | B45: =Setup!$C$5+64 -> 46091 | C45: TOTAL | D45: =SUM(D24:D44) -> 0 | E45: =SUM(E24:E44) -> 0 | F45: =SUM(F24:F44) -> 0 | G45: =SUM(G24:G44) -> 0 | H45: =SUM(H24:H44) -> 0 | I45: =IFERROR(E45/D45,"") | J45: =IFERROR(H45/E45,"") | K45: =SUM(K24:K44) -> 0 | M45: =SUM(M24:M44) -> 0 | N45: =IFERROR(H45-Wk9!H45,"") -> 0 | O45: =IFERROR(D45-Wk9!D45,"") -> 0 | P45: =SUM(P24:P44) -> 0 | Q45: =SUM(Q24:Q44) -> 0 | R45: =IFERROR(INDEX('Last Year'!$C$6:$C$369,MATCH(B45-364,'Last Year'!$B$6:$B$369,0)),"") -> 0 | S45: =IFERROR(H45/R45-1,"")
A46: =TEXT(Setup!$C$5+65,"dddd") -> Wednesday | B46: =Setup!$C$5+65 -> 46092 | C46: 9.00 - 9.30 | P46: =IFERROR(H46/Setup!$C$6,"") -> 0 | Q46: =IFERROR(H46-P46,"") -> 0
A47: =TEXT(Setup!$C$5+65,"dddd") -> Wednesday | B47: =Setup!$C$5+65 -> 46092 | C47: 9.30 - 10.00 | P47: =IFERROR(H47/Setup!$C$6,"") -> 0 | Q47: =IFERROR(H47-P47,"") -> 0
A48: =TEXT(Setup!$C$5+65,"dddd") -> Wednesday | B48: =Setup!$C$5+65 -> 46092 | C48: 10.00 - 10.30 | P48: =IFERROR(H48/Setup!$C$6,"") -> 0 | Q48: =IFERROR(H48-P48,"") -> 0
A49: =TEXT(Setup!$C$5+65,"dddd") -> Wednesday | B49: =Setup!$C$5+65 -> 46092 | C49: 10.30 - 11.00 | P49: =IFERROR(H49/Setup!$C$6,"") -> 0 | Q49: =IFERROR(H49-P49,"") -> 0
A50: =TEXT(Setup!$C$5+65,"dddd") -> Wednesday | B50: =Setup!$C$5+65 -> 46092 | C50: 11.00 - 11.30 | P50: =IFERROR(H50/Setup!$C$6,"") -> 0 | Q50: =IFERROR(H50-P50,"") -> 0
A51: =TEXT(Setup!$C$5+65,"dddd") -> Wednesday | B51: =Setup!$C$5+65 -> 46092 | C51: 11.30 - 12.00 | P51: =IFERROR(H51/Setup!$C$6,"") -> 0 | Q51: =IFERROR(H51-P51,"") -> 0
A52: =TEXT(Setup!$C$5+65,"dddd") -> Wednesday | B52: =Setup!$C$5+65 -> 46092 | C52: 12.00 - 12.30 | P52: =IFERROR(H52/Setup!$C$6,"") -> 0 | Q52: =IFERROR(H52-P52,"") -> 0
A53: =TEXT(Setup!$C$5+65,"dddd") -> Wednesday | B53: =Setup!$C$5+65 -> 46092 | C53: 12.30 - 13.00 | P53: =IFERROR(H53/Setup!$C$6,"") -> 0 | Q53: =IFERROR(H53-P53,"") -> 0
A54: =TEXT(Setup!$C$5+65,"dddd") -> Wednesday | B54: =Setup!$C$5+65 -> 46092 | C54: 13.00 - 13.30 | P54: =IFERROR(H54/Setup!$C$6,"") -> 0 | Q54: =IFERROR(H54-P54,"") -> 0
A55: =TEXT(Setup!$C$5+65,"dddd") -> Wednesday | B55: =Setup!$C$5+65 -> 46092 | C55: 13.30 - 14.00 | P55: =IFERROR(H55/Setup!$C$6,"") -> 0 | Q55: =IFERROR(H55-P55,"") -> 0
A56: =TEXT(Setup!$C$5+65,"dddd") -> Wednesday | B56: =Setup!$C$5+65 -> 46092 | C56: 14.00 - 14.30 | P56: =IFERROR(H56/Setup!$C$6,"") -> 0 | Q56: =IFERROR(H56-P56,"") -> 0
A57: =TEXT(Setup!$C$5+65,"dddd") -> Wednesday | B57: =Setup!$C$5+65 -> 46092 | C57: 14.30 - 15.00 | P57: =IFERROR(H57/Setup!$C$6,"") -> 0 | Q57: =IFERROR(H57-P57,"") -> 0
... A66: =TEXT(Setup!$C$5+65,"dddd") -> Wednesday | B66: =Setup!$C$5+65 -> 46092 | C66: ONLINE | P66: =IFERROR(H66/Setup!$C$6,"") -> 0 | Q66: =IFERROR(H66-P66,"") -> 0
A67: =TEXT(Setup!$C$5+65,"dddd") -> Wednesday | B67: =Setup!$C$5+65 -> 46092 | C67: TOTAL | D67: =SUM(D46:D66) -> 0 | E67: =SUM(E46:E66) -> 0 | F67: =SUM(F46:F66) -> 0 | G67: =SUM(G46:G66) -> 0 | H67: =SUM(H46:H66) -> 0 | I67: =IFERROR(E67/D67,"") | J67: =IFERROR(H67/E67,"") | K67: =SUM(K46:K66) -> 0 | M67: =SUM(M46:M66) -> 0 | N67: =IFERROR(H67-Wk9!H67,"") -> 0 | O67: =IFERROR(D67-Wk9!D67,"") -> 0 | P67: =SUM(P46:P66) -> 0 | Q67: =SUM(Q46:Q66) -> 0 | R67: =IFERROR(INDEX('Last Year'!$C$6:$C$369,MATCH(B67-364,'Last Year'!$B$6:$B$369,0)),"") -> 0 | S67: =IFERROR(H67/R67-1,"")
A68: =TEXT(Setup!$C$5+66,"dddd") -> Thursday | B68: =Setup!$C$5+66 -> 46093 | C68: 9.00 - 9.30 | P68: =IFERROR(H68/Setup!$C$6,"") -> 0 | Q68: =IFERROR(H68-P68,"") -> 0
A69: =TEXT(Setup!$C$5+66,"dddd") -> Thursday | B69: =Setup!$C$5+66 -> 46093 | C69: 9.30 - 10.00 | P69: =IFERROR(H69/Setup!$C$6,"") -> 0 | Q69: =IFERROR(H69-P69,"") -> 0
A70: =TEXT(Setup!$C$5+66,"dddd") -> Thursday | B70: =Setup!$C$5+66 -> 46093 | C70: 10.00 - 10.30 | P70: =IFERROR(H70/Setup!$C$6,"") -> 0 | Q70: =IFERROR(H70-P70,"") -> 0
A71: =TEXT(Setup!$C$5+66,"dddd") -> Thursday | B71: =Setup!$C$5+66 -> 46093 | C71: 10.30 - 11.00 | P71: =IFERROR(H71/Setup!$C$6,"") -> 0 | Q71: =IFERROR(H71-P71,"") -> 0
A72: =TEXT(Setup!$C$5+66,"dddd") -> Thursday | B72: =Setup!$C$5+66 -> 46093 | C72: 11.00 - 11.30 | P72: =IFERROR(H72/Setup!$C$6,"") -> 0 | Q72: =IFERROR(H72-P72,"") -> 0
A73: =TEXT(Setup!$C$5+66,"dddd") -> Thursday | B73: =Setup!$C$5+66 -> 46093 | C73: 11.30 - 12.00 | P73: =IFERROR(H73/Setup!$C$6,"") -> 0 | Q73: =IFERROR(H73-P73,"") -> 0
A74: =TEXT(Setup!$C$5+66,"dddd") -> Thursday | B74: =Setup!$C$5+66 -> 46093 | C74: 12.00 - 12.30 | P74: =IFERROR(H74/Setup!$C$6,"") -> 0 | Q74: =IFERROR(H74-P74,"") -> 0
A75: =TEXT(Setup!$C$5+66,"dddd") -> Thursday | B75: =Setup!$C$5+66 -> 46093 | C75: 12.30 - 13.00 | P75: =IFERROR(H75/Setup!$C$6,"") -> 0 | Q75: =IFERROR(H75-P75,"") -> 0
A76: =TEXT(Setup!$C$5+66,"dddd") -> Thursday | B76: =Setup!$C$5+66 -> 46093 | C76: 13.00 - 13.30 | P76: =IFERROR(H76/Setup!$C$6,"") -> 0 | Q76: =IFERROR(H76-P76,"") -> 0
A77: =TEXT(Setup!$C$5+66,"dddd") -> Thursday | B77: =Setup!$C$5+66 -> 46093 | C77: 13.30 - 14.00 | P77: =IFERROR(H77/Setup!$C$6,"") -> 0 | Q77: =IFERROR(H77-P77,"") -> 0
A78: =TEXT(Setup!$C$5+66,"dddd") -> Thursday | B78: =Setup!$C$5+66 -> 46093 | C78: 14.00 - 14.30 | P78: =IFERROR(H78/Setup!$C$6,"") -> 0 | Q78: =IFERROR(H78-P78,"") -> 0
A79: =TEXT(Setup!$C$5+66,"dddd") -> Thursday | B79: =Setup!$C$5+66 -> 46093 | C79: 14.30 - 15.00 | P79: =IFERROR(H79/Setup!$C$6,"") -> 0 | Q79: =IFERROR(H79-P79,"") -> 0
... A88: =TEXT(Setup!$C$5+66,"dddd") -> Thursday | B88: =Setup!$C$5+66 -> 46093 | C88: ONLINE | P88: =IFERROR(H88/Setup!$C$6,"") -> 0 | Q88: =IFERROR(H88-P88,"") -> 0
A89: =TEXT(Setup!$C$5+66,"dddd") -> Thursday | B89: =Setup!$C$5+66 -> 46093 | C89: TOTAL | D89: =SUM(D68:D88) -> 0 | E89: =SUM(E68:E88) -> 0 | F89: =SUM(F68:F88) -> 0 | G89: =SUM(G68:G88) -> 0 | H89: =SUM(H68:H88) -> 0 | I89: =IFERROR(E89/D89,"") | J89: =IFERROR(H89/E89,"") | K89: =SUM(K68:K88) -> 0 | M89: =SUM(M68:M88) -> 0 | N89: =IFERROR(H89-Wk9!H89,"") -> 0 | O89: =IFERROR(D89-Wk9!D89,"") -> 0 | P89: =SUM(P68:P88) -> 0 | Q89: =SUM(Q68:Q88) -> 0 | R89: =IFERROR(INDEX('Last Year'!$C$6:$C$369,MATCH(B89-364,'Last Year'!$B$6:$B$369,0)),"") -> 0 | S89: =IFERROR(H89/R89-1,"")
A90: =TEXT(Setup!$C$5+67,"dddd") -> Friday | B90: =Setup!$C$5+67 -> 46094 | C90: 9.00 - 9.30 | P90: =IFERROR(H90/Setup!$C$6,"") -> 0 | Q90: =IFERROR(H90-P90,"") -> 0
A91: =TEXT(Setup!$C$5+67,"dddd") -> Friday | B91: =Setup!$C$5+67 -> 46094 | C91: 9.30 - 10.00 | P91: =IFERROR(H91/Setup!$C$6,"") -> 0 | Q91: =IFERROR(H91-P91,"") -> 0
A92: =TEXT(Setup!$C$5+67,"dddd") -> Friday | B92: =Setup!$C$5+67 -> 46094 | C92: 10.00 - 10.30 | P92: =IFERROR(H92/Setup!$C$6,"") -> 0 | Q92: =IFERROR(H92-P92,"") -> 0
A93: =TEXT(Setup!$C$5+67,"dddd") -> Friday | B93: =Setup!$C$5+67 -> 46094 | C93: 10.30 - 11.00 | P93: =IFERROR(H93/Setup!$C$6,"") -> 0 | Q93: =IFERROR(H93-P93,"") -> 0
A94: =TEXT(Setup!$C$5+67,"dddd") -> Friday | B94: =Setup!$C$5+67 -> 46094 | C94: 11.00 - 11.30 | P94: =IFERROR(H94/Setup!$C$6,"") -> 0 | Q94: =IFERROR(H94-P94,"") -> 0
A95: =TEXT(Setup!$C$5+67,"dddd") -> Friday | B95: =Setup!$C$5+67 -> 46094 | C95: 11.30 - 12.00 | P95: =IFERROR(H95/Setup!$C$6,"") -> 0 | Q95: =IFERROR(H95-P95,"") -> 0
A96: =TEXT(Setup!$C$5+67,"dddd") -> Friday | B96: =Setup!$C$5+67 -> 46094 | C96: 12.00 - 12.30 | P96: =IFERROR(H96/Setup!$C$6,"") -> 0 | Q96: =IFERROR(H96-P96,"") -> 0
A97: =TEXT(Setup!$C$5+67,"dddd") -> Friday | B97: =Setup!$C$5+67 -> 46094 | C97: 12.30 - 13.00 | P97: =IFERROR(H97/Setup!$C$6,"") -> 0 | Q97: =IFERROR(H97-P97,"") -> 0
A98: =TEXT(Setup!$C$5+67,"dddd") -> Friday | B98: =Setup!$C$5+67 -> 46094 | C98: 13.00 - 13.30 | P98: =IFERROR(H98/Setup!$C$6,"") -> 0 | Q98: =IFERROR(H98-P98,"") -> 0
A99: =TEXT(Setup!$C$5+67,"dddd") -> Friday | B99: =Setup!$C$5+67 -> 46094 | C99: 13.30 - 14.00 | P99: =IFERROR(H99/Setup!$C$6,"") -> 0 | Q99: =IFERROR(H99-P99,"") -> 0
